Workbook
Name POLIWAG: 'Localizações'!$A$14
Name figh: Search!$A$1
Name blastoise: 'Localizações'!$A$377:$A$387
Name vaporeon: #REF!
Name slowking: #REF!
Name StarObjetivo: 'Star Level'!$A$15:$E$15
Name brown: Search!$A$4:$A$1000
Name rhydon: 'Localizações'!$A$2
Name mouse: Search!$2:$2
Name charmander: Search!$A$2:$A$3
Name pinsir: 'Localizações'!$C$128
Name miss: #REF!
Name forretres: #REF!
Name Typhlosion: 'Localizações'!$B$392
Name rampardos: 'Localizações'!$A$1
Name arca: 'Localizações'!$E$14:$E$1000
Name ursarin: 'Localizações'!$E$2:$E$13
Name hitmontop: 'Localizações'!$C$274
Name fire: #REF!
Name onix: 'Localizações'!$A:$A
Name Grass: 'Tier List'!$C:$C
Name sky: Brokes!$A$1
Name seal: 'Localizações'!$C$1

Sheet Drops
A1: =IFERROR(__xludf.DUMMYFUNCTION("IMPORTRANGE(""Https://docs.google.com/spreadsheets/d/1ID3qu1P4Zey82OSLntg4O0xoZlY1hGK58tte0D_Cv_s/edit?gid=709790984#gid=709790984"", ""Drops!A1:K1600"")"),"Pokemon") -> Pokemon | B1: =IFERROR(__xludf.DUMMYFUNCTION("""COMPUTED_VALUE"""),"DROPS") -> DROPS
A2: =IFERROR(__xludf.DUMMYFUNCTION("""COMPUTED_VALUE"""),"Bulbasaur") -> Bulbasaur | B2: =IFERROR(__xludf.DUMMYFUNCTION("""COMPUTED_VALUE"""),"seed") -> seed | C2: =IFERROR(__xludf.DUMMYFUNCTION("""COMPUTED_VALUE"""),"bottle of poison") -> bottle of poison | D2: =IFERROR(__xludf.DUMMYFUNCTION("""COMPUTED_VALUE"""),"bulb") -> bulb
A3: =IFERROR(__xludf.DUMMYFUNCTION("""COMPUTED_VALUE"""),"Shiny Bulbasaur") -> Shiny Bulbasaur | B3: =IFERROR(__xludf.DUMMYFUNCTION("""COMPUTED_VALUE"""),"seed") -> seed | C3: =IFERROR(__xludf.DUMMYFUNCTION("""COMPUTED_VALUE"""),"bottle of poison") -> bottle of poison | D3: =IFERROR(__xludf.DUMMYFUNCTION("""COMPUTED_VALUE"""),"brown bulb") -> brown bulb | E3: =IFERROR(__xludf.DUMMYFUNCTION("""COMPUTED_VALUE"""),"leaf stone") -> leaf stone | F3: =IFERROR(__xludf.DUMMYFUNCTION("""COMPUTED_VALUE"""),"venom stone") -> venom stone | G3: =IFERROR(__xludf.DUMMYFUNCTION("""COMPUTED_VALUE"""),"simple grass orb") -> simple grass orb
A4: =IFERROR(__xludf.DUMMYFUNCTION("""COMPUTED_VALUE"""),"Ivysaur") -> Ivysaur | B4: =IFERROR(__xludf.DUMMYFUNCTION("""COMPUTED_VALUE"""),"seed") -> seed | C4: =IFERROR(__xludf.DUMMYFUNCTION("""COMPUTED_VALUE"""),"bottle of poison") -> bottle of poison | D4: =IFERROR(__xludf.DUMMYFUNCTION("""COMPUTED_VALUE"""),"leaf") -> leaf | E4: =IFERROR(__xludf.DUMMYFUNCTION("""COMPUTED_VALUE"""),"leaf stone") -> leaf stone | F4: =IFERROR(__xludf.DUMMYFUNCTION("""COMPUTED_VALUE"""),"venom stone") -> venom stone
A5: =IFERROR(__xludf.DUMMYFUNCTION("""COMPUTED_VALUE"""),"Shiny Ivysaur") -> Shiny Ivysaur | B5: =IFERROR(__xludf.DUMMYFUNCTION("""COMPUTED_VALUE"""),"seed") -> seed | C5: =IFERROR(__xludf.DUMMYFUNCTION("""COMPUTED_VALUE"""),"bottle of poison") -> bottle of poison | D5: =IFERROR(__xludf.DUMMYFUNCTION("""COMPUTED_VALUE"""),"purple leaf") -> purple leaf | E5: =IFERROR(__xludf.DUMMYFUNCTION("""COMPUTED_VALUE"""),"leaf stone") -> leaf stone | F5: =IFERROR(__xludf.DUMMYFUNCTION("""COMPUTED_VALUE"""),"venom stone") -> venom stone | G5: =IFERROR(__xludf.DUMMYFUNCTION("""COMPUTED_VALUE"""),"arcane grass orb") -> arcane grass orb
A6: =IFERROR(__xludf.DUMMYFUNCTION("""COMPUTED_VALUE"""),"Venusaur") -> Venusaur | B6: =IFERROR(__xludf.DUMMYFUNCTION("""COMPUTED_VALUE"""),"seed") -> seed | C6: =IFERROR(__xludf.DUMMYFUNCTION("""COMPUTED_VALUE"""),"bottle of poison") -> bottle of poison | D6: =IFERROR(__xludf.DUMMYFUNCTION("""COMPUTED_VALUE"""),"red petal") -> red petal | E6: =IFERROR(__xludf.DUMMYFUNCTION("""COMPUTED_VALUE"""),"leaf stone") -> leaf stone | F6: =IFERROR(__xludf.DUMMYFUNCTION("""COMPUTED_VALUE"""),"venom stone") -> venom stone
A7: =IFERROR(__xludf.DUMMYFUNCTION("""COMPUTED_VALUE"""),"Shiny Venusaur") -> Shiny Venusaur | B7: =IFERROR(__xludf.DUMMYFUNCTION("""COMPUTED_VALUE"""),"seed") -> seed | C7: =IFERROR(__xludf.DUMMYFUNCTION("""COMPUTED_VALUE"""),"bottle of poison") -> bottle of poison | D7: =IFERROR(__xludf.DUMMYFUNCTION("""COMPUTED_VALUE"""),"brown petal") -> brown petal | E7: =IFERROR(__xludf.DUMMYFUNCTION("""COMPUTED_VALUE"""),"leaf stone") -> leaf stone | F7: =IFERROR(__xludf.DUMMYFUNCTION("""COMPUTED_VALUE"""),"venom stone") -> venom stone | G7: =IFERROR(__xludf.DUMMYFUNCTION("""COMPUTED_VALUE"""),"mythic grass orb") -> mythic grass orb
A8: =IFERROR(__xludf.DUMMYFUNCTION("""COMPUTED_VALUE"""),"Charmander") -> Charmander | B8: =IFERROR(__xludf.DUMMYFUNCTION("""COMPUTED_VALUE"""),"essence of fire") -> essence of fire | C8: =IFERROR(__xludf.DUMMYFUNCTION("""COMPUTED_VALUE"""),"fire tail") -> fire tail
A9: =IFERROR(__xludf.DUMMYFUNCTION("""COMPUTED_VALUE"""),"Shiny Charmander") -> Shiny Charmander | B9: =IFERROR(__xludf.DUMMYFUNCTION("""COMPUTED_VALUE"""),"essence of fire") -> essence of fire | C9: =IFERROR(__xludf.DUMMYFUNCTION("""COMPUTED_VALUE"""),"black tail") -> black tail | D9: =IFERROR(__xludf.DUMMYFUNCTION("""COMPUTED_VALUE"""),"fire stone") -> fire stone | E9: =IFERROR(__xludf.DUMMYFUNCTION("""COMPUTED_VALUE"""),"simple fire orb") -> simple fire orb
A10: =IFERROR(__xludf.DUMMYFUNCTION("""COMPUTED_VALUE"""),"Charmelion") -> Charmelion | B10: =IFERROR(__xludf.DUMMYFUNCTION("""COMPUTED_VALUE"""),"essence of fire") -> essence of fire | C10: =IFERROR(__xludf.DUMMYFUNCTION("""COMPUTED_VALUE"""),"lizard tail") -> lizard tail | D10: =IFERROR(__xludf.DUMMYFUNCTION("""COMPUTED_VALUE"""),"fire stone") -> fire stone
A11: =IFERROR(__xludf.DUMMYFUNCTION("""COMPUTED_VALUE"""),"Shiny Charmelion") -> Shiny Charmelion | B11: =IFERROR(__xludf.DUMMYFUNCTION("""COMPUTED_VALUE"""),"essence of fire") -> essence of fire | C11: =IFERROR(__xludf.DUMMYFUNCTION("""COMPUTED_VALUE"""),"black lizard tail") -> black lizard tail | D11: =IFERROR(__xludf.DUMMYFUNCTION("""COMPUTED_VALUE"""),"fire stone") -> fire stone | E11: =IFERROR(__xludf.DUMMYFUNCTION("""COMPUTED_VALUE"""),"arcane fire orb") -> arcane fire orb
A12: =IFERROR(__xludf.DUMMYFUNCTION("""COMPUTED_VALUE"""),"Charizard") -> Charizard | B12: =IFERROR(__xludf.DUMMYFUNCTION("""COMPUTED_VALUE"""),"essence of fire") -> essence of fire | C12: =IFERROR(__xludf.DUMMYFUNCTION("""COMPUTED_VALUE"""),"straw") -> straw | D12: =IFERROR(__xludf.DUMMYFUNCTION("""COMPUTED_VALUE"""),"fire wing") -> fire wing | E12: =IFERROR(__xludf.DUMMYFUNCTION("""COMPUTED_VALUE"""),"fire stone") -> fire stone | F12: =IFERROR(__xludf.DUMMYFUNCTION("""COMPUTED_VALUE"""),"feather stone") -> feather stone
A13: =IFERROR(__xludf.DUMMYFUNCTION("""COMPUTED_VALUE"""),"Shiny Charizard") -> Shiny Charizard | B13: =IFERROR(__xludf.DUMMYFUNCTION("""COMPUTED_VALUE"""),"essence of fire") -> essence of fire | C13: =IFERROR(__xludf.DUMMYFUNCTION("""COMPUTED_VALUE"""),"essence of fire") -> essence of fire | D13: =IFERROR(__xludf.DUMMYFUNCTION("""COMPUTED_VALUE"""),"straw") -> straw | E13: =IFERROR(__xludf.DUMMYFUNCTION("""COMPUTED_VALUE"""),"dark wing") -> dark wing | F13: =IFERROR(__xludf.DUMMYFUNCTION("""COMPUTED_VALUE"""),"fire stone") -> fire stone | G13: =IFERROR(__xludf.DUMMYFUNCTION("""COMPUTED_VALUE"""),"feather stone") -> feather stone | H13: =IFERROR(__xludf.DUMMYFUNCTION("""COMPUTED_VALUE"""),"mythic fire orb") -> mythic fire orb
A14: =IFERROR(__xludf.DUMMYFUNCTION("""COMPUTED_VALUE"""),"Squirtle") -> Squirtle | B14: =IFERROR(__xludf.DUMMYFUNCTION("""COMPUTED_VALUE"""),"water gem") -> water gem | C14: =IFERROR(__xludf.DUMMYFUNCTION("""COMPUTED_VALUE"""),"squirtle hull") -> squirtle hull
A15: =IFERROR(__xludf.DUMMYFUNCTION("""COMPUTED_VALUE"""),"Shiny Squirtle") -> Shiny Squirtle | B15: =IFERROR(__xludf.DUMMYFUNCTION("""COMPUTED_VALUE"""),"water gem") -> water gem | C15: =IFERROR(__xludf.DUMMYFUNCTION("""COMPUTED_VALUE"""),"cyan hull") -> cyan hull | D15: =IFERROR(__xludf.DUMMYFUNCTION("""COMPUTED_VALUE"""),"water stone") -> water stone | E15: =IFERROR(__xludf.DUMMYFUNCTION("""COMPUTED_VALUE"""),"simple water orb") -> simple water orb
A16: =IFERROR(__xludf.DUMMYFUNCTION("""COMPUTED_VALUE"""),"Wartortle") -> Wartortle | B16: =IFERROR(__xludf.DUMMYFUNCTION("""COMPUTED_VALUE"""),"water gem") -> water gem | C16: =IFERROR(__xludf.DUMMYFUNCTION("""COMPUTED_VALUE"""),"water gem") -> water gem | D16: =IFERROR(__xludf.DUMMYFUNCTION("""COMPUTED_VALUE"""),"wartortle ear") -> wartortle ear | E16: =IFERROR(__xludf.DUMMYFUNCTION("""COMPUTED_VALUE"""),"water stone") -> water stone
A17: =IFERROR(__xludf.DUMMYFUNCTION("""COMPUTED_VALUE"""),"Shiny Wartortle") -> Shiny Wartortle | B17: =IFERROR(__xludf.DUMMYFUNCTION("""COMPUTED_VALUE"""),"water gem") -> water gem | C17: =IFERROR(__xludf.DUMMYFUNCTION("""COMPUTED_VALUE"""),"water gem") -> water gem | D17: =IFERROR(__xludf.DUMMYFUNCTION("""COMPUTED_VALUE"""),"cyan ear") -> cyan ear | E17: =IFERROR(__xludf.DUMMYFUNCTION("""COMPUTED_VALUE"""),"water stone") -> water stone | F17: =IFERROR(__xludf.DUMMYFUNCTION("""COMPUTED_VALUE"""),"arcane water orb") -> arcane water orb
A18: =IFERROR(__xludf.DUMMYFUNCTION("""COMPUTED_VALUE"""),"Blastoise") -> Blastoise | B18: =IFERROR(__xludf.DUMMYFUNCTION("""COMPUTED_VALUE"""),"water gem") -> water gem | C18: =IFERROR(__xludf.DUMMYFUNCTION("""COMPUTED_VALUE"""),"water cannon") -> water cannon | D18: =IFERROR(__xludf.DUMMYFUNCTION("""COMPUTED_VALUE"""),"water stone") -> water stone
A19: =IFERROR(__xludf.DUMMYFUNCTION("""COMPUTED_VALUE"""),"Shiny Blastoise") -> Shiny Blastoise | B19: =IFERROR(__xludf.DUMMYFUNCTION("""COMPUTED_VALUE"""),"water gem") -> water gem | C19: =IFERROR(__xludf.DUMMYFUNCTION("""COMPUTED_VALUE"""),"giant water cannon") -> giant water cannon | D19: =IFERROR(__xludf.DUMMYFUNCTION("""COMPUTED_VALUE"""),"water stone") -> water stone | E19: =IFERROR(__xludf.DUMMYFUNCTION("""COMPUTED_VALUE"""),"mythic water orb") -> mythic water orb
A20: =IFERROR(__xludf.DUMMYFUNCTION("""COMPUTED_VALUE"""),"Caterpie") -> Caterpie | B20: =IFERROR(__xludf.DUMMYFUNCTION("""COMPUTED_VALUE"""),"bug gosme") -> bug gosme | C20: =IFERROR(__xludf.DUMMYFUNCTION("""COMPUTED_VALUE"""),"caterpie antenna") -> caterpie antenna
A21: =IFERROR(__xludf.DUMMYFUNCTION("""COMPUTED_VALUE"""),"Shiny Caterpie") -> Shiny Caterpie | B21: =IFERROR(__xludf.DUMMYFUNCTION("""COMPUTED_VALUE"""),"bug gosme") -> bug gosme | C21: =IFERROR(__xludf.DUMMYFUNCTION("""COMPUTED_VALUE"""),"sparkle antenna") -> sparkle antenna | D21: =IFERROR(__xludf.DUMMYFUNCTION("""COMPUTED_VALUE"""),"simple bug orb") -> simple bug orb
A22: =IFERROR(__xludf.DUMMYFUNCTION("""COMPUTED_VALUE"""),"Metapod") -> Metapod | B22: =IFERROR(__xludf.DUMMYFUNCTION("""COMPUTED_VALUE"""),"bug gosme") -> bug gosme | C22: =IFERROR(__xludf.DUMMYFUNCTION("""COMPUTED_VALUE"""),"piece of cocoon") -> piece of cocoon | D22: =IFERROR(__xludf.DUMMYFUNCTION("""COMPUTED_VALUE"""),"cocoon stone") -> cocoon stone
A23: =IFERROR(__xludf.DUMMYFUNCTION("""COMPUTED_VALUE"""),"Shiny Metapod") -> Shiny Metapod | B23: =IFERROR(__xludf.DUMMYFUNCTION("""COMPUTED_VALUE"""),"bug gosme") -> bug gosme | C23: =IFERROR(__xludf.DUMMYFUNCTION("""COMPUTED_VALUE"""),"red piece of cocoon") -> red piece of cocoon | D23: =IFERROR(__xludf.DUMMYFUNCTION("""COMPUTED_VALUE"""),"cocoon stone") -> cocoon stone | E23: =IFERROR(__xludf.DUMMYFUNCTION("""COMPUTED_VALUE"""),"simple bug orb") -> simple bug orb
A24: =IFERROR(__xludf.DUMMYFUNCTION("""COMPUTED_VALUE"""),"Butterfree") -> Butterfree | B24: =IFERROR(__xludf.DUMMYFUNCTION("""COMPUTED_VALUE"""),"bug gosme") -> bug gosme | C24: =IFERROR(__xludf.DUMMYFUNCTION("""COMPUTED_VALUE"""),"straw") -> straw | D24: =IFERROR(__xludf.DUMMYFUNCTION("""COMPUTED_VALUE"""),"butterfree wing") -> butterfree wing | E24: =IFERROR(__xludf.DUMMYFUNCTION("""COMPUTED_VALUE"""),"cocoon stone") -> cocoon stone | F24: =IFERROR(__xludf.DUMMYFUNCTION("""COMPUTED_VALUE"""),"feather stone") -> feather stone
A25: =IFERROR(__xludf.DUMMYFUNCTION("""COMPUTED_VALUE"""),"Shiny Butterfree") -> Shiny Butterfree | B25: =IFERROR(__xludf.DUMMYFUNCTION("""COMPUTED_VALUE"""),"bug gosme") -> bug gosme | C25: =IFERROR(__xludf.DUMMYFUNCTION("""COMPUTED_VALUE"""),"straw") -> straw | D25: =IFERROR(__xludf.DUMMYFUNCTION("""COMPUTED_VALUE"""),"pink wing") -> pink wing | E25: =IFERROR(__xludf.DUMMYFUNCTION("""COMPUTED_VALUE"""),"cocoon stone") -> cocoon stone | F25: =IFERROR(__xludf.DUMMYFUNCTION("""COMPUTED_VALUE"""),"feather stone") -> feather stone | G25: =IFERROR(__xludf.DUMMYFUNCTION("""COMPUTED_VALUE"""),"arcane bug orb") -> arcane bug orb
A26: =IFERROR(__xludf.DUMMYFUNCTION("""COMPUTED_VALUE"""),"Weedle") -> Weedle | B26: =IFERROR(__xludf.DUMMYFUNCTION("""COMPUTED_VALUE"""),"bug gosme") -> bug gosme | C26: =IFERROR(__xludf.DUMMYFUNCTION("""COMPUTED_VALUE"""),"bottle of poison") -> bottle of poison | D26: =IFERROR(__xludf.DUMMYFUNCTION("""COMPUTED_VALUE"""),"poison sting") -> poison sting
A27: =IFERROR(__xludf.DUMMYFUNCTION("""COMPUTED_VALUE"""),"Shiny Weedle") -> Shiny Weedle | B27: =IFERROR(__xludf.DUMMYFUNCTION("""COMPUTED_VALUE"""),"bug gosme") -> bug gosme | C27: =IFERROR(__xludf.DUMMYFUNCTION("""COMPUTED_VALUE"""),"bottle of poison") -> bottle of poison | D27: =IFERROR(__xludf.DUMMYFUNCTION("""COMPUTED_VALUE"""),"yellow sting") -> yellow sting | E27: =IFERROR(__xludf.DUMMYFUNCTION("""COMPUTED_VALUE"""),"simple bug orb") -> simple bug orb
A28: =IFERROR(__xludf.DUMMYFUNCTION("""COMPUTED_VALUE"""),"Kakuna") -> Kakuna | B28: =IFERROR(__xludf.DUMMYFUNCTION("""COMPUTED_VALUE"""),"bug gosme") -> bug gosme | C28: =IFERROR(__xludf.DUMMYFUNCTION("""COMPUTED_VALUE"""),"bottle of poison") -> bottle of poison | D28: =IFERROR(__xludf.DUMMYFUNCTION("""COMPUTED_VALUE"""),"yellow cocoon") -> yellow cocoon | E28: =IFERROR(__xludf.DUMMYFUNCTION("""COMPUTED_VALUE"""),"cocoon stone") -> cocoon stone
A29: =IFERROR(__xludf.DUMMYFUNCTION("""COMPUTED_VALUE"""),"Shiny Kakuna") -> Shiny Kakuna | B29: =IFERROR(__xludf.DUMMYFUNCTION("""COMPUTED_VALUE"""),"bug gosme") -> bug gosme | C29: =IFERROR(__xludf.DUMMYFUNCTION("""COMPUTED_VALUE"""),"bottle of poison") -> bottle of poison | D29: =IFERROR(__xludf.DUMMYFUNCTION("""COMPUTED_VALUE"""),"red cocoon") -> red cocoon | E29: =IFERROR(__xludf.DUMMYFUNCTION("""COMPUTED_VALUE"""),"cocoon stone") -> cocoon stone | F29: =IFERROR(__xludf.DUMMYFUNCTION("""COMPUTED_VALUE"""),"venom stone") -> venom stone | G29: =IFERROR(__xludf.DUMMYFUNCTION("""COMPUTED_VALUE"""),"simple bug orb") -> simple bug orb
A30: =IFERROR(__xludf.DUMMYFUNCTION("""COMPUTED_VALUE"""),"Beedrill") -> Beedrill | B30: =IFERROR(__xludf.DUMMYFUNCTION("""COMPUTED_VALUE"""),"bug gosme") -> bug gosme | C30: =IFERROR(__xludf.DUMMYFUNCTION("""COMPUTED_VALUE"""),"bottle of poison") -> bottle of poison | D30: =IFERROR(__xludf.DUMMYFUNCTION("""COMPUTED_VALUE"""),"bee sting") -> bee sting | E30: =IFERROR(__xludf.DUMMYFUNCTION("""COMPUTED_VALUE"""),"cocoon stone") -> cocoon stone | F30: =IFERROR(__xludf.DUMMYFUNCTION("""COMPUTED_VALUE"""),"venom stone") -> venom stone
A31: =IFERROR(__xludf.DUMMYFUNCTION("""COMPUTED_VALUE"""),"Shiny Beedrill") -> Shiny Beedrill | B31: =IFERROR(__xludf.DUMMYFUNCTION("""COMPUTED_VALUE"""),"bug gosme") -> bug gosme | C31: =IFERROR(__xludf.DUMMYFUNCTION("""COMPUTED_VALUE"""),"bottle of poison") -> bottle of poison | D31: =IFERROR(__xludf.DUMMYFUNCTION("""COMPUTED_VALUE"""),"red bee sting") -> red bee sting | E31: =IFERROR(__xludf.DUMMYFUNCTION("""COMPUTED_VALUE"""),"cocoon stone") -> cocoon stone | F31: =IFERROR(__xludf.DUMMYFUNCTION("""COMPUTED_VALUE"""),"venom stone") -> venom stone | G31: =IFERROR(__xludf.DUMMYFUNCTION("""COMPUTED_VALUE"""),"arcane bug orb") -> arcane bug orb
A32: =IFERROR(__xludf.DUMMYFUNCTION("""COMPUTED_VALUE"""),"Pidgey") -> Pidgey | B32: =IFERROR(__xludf.DUMMYFUNCTION("""COMPUTED_VALUE"""),"rubber ball") -> rubber ball | C32: =IFERROR(__xludf.DUMMYFUNCTION("""COMPUTED_VALUE"""),"straw") -> straw | D32: =IFERROR(__xludf.DUMMYFUNCTION("""COMPUTED_VALUE"""),"bird crest") -> bird crest
A33: =IFERROR(__xludf.DUMMYFUNCTION("""COMPUTED_VALUE"""),"Shiny Pidgey") -> Shiny Pidgey | B33: =IFERROR(__xludf.DUMMYFUNCTION("""COMPUTED_VALUE"""),"rubber ball") -> rubber ball | C33: =IFERROR(__xludf.DUMMYFUNCTION("""COMPUTED_VALUE"""),"straw") -> straw | D33: =IFERROR(__xludf.DUMMYFUNCTION("""COMPUTED_VALUE"""),"yellow bird crest") -> yellow bird crest | E33: =IFERROR(__xludf.DUMMYFUNCTION("""COMPUTED_VALUE"""),"simple flying orb") -> simple flying orb
A34: =IFERROR(__xludf.DUMMYFUNCTION("""COMPUTED_VALUE"""),"Pidgeotto") -> Pidgeotto | B34: =IFERROR(__xludf.DUMMYFUNCTION("""COMPUTED_VALUE"""),"rubber ball") -> rubber ball | C34: =IFERROR(__xludf.DUMMYFUNCTION("""COMPUTED_VALUE"""),"straw") -> straw | D34: =IFERROR(__xludf.DUMMYFUNCTION("""COMPUTED_VALUE"""),"bird tail") -> bird tail | E34: =IFERROR(__xludf.DUMMYFUNCTION("""COMPUTED_VALUE"""),"heart stone") -> heart stone | F34: =IFERROR(__xludf.DUMMYFUNCTION("""COMPUTED_VALUE"""),"feather stone") -> feather stone
A35: =IFERROR(__xludf.DUMMYFUNCTION("""COMPUTED_VALUE"""),"Shiny Pidgeotto") -> Shiny Pidgeotto | B35: =IFERROR(__xludf.DUMMYFUNCTION("""COMPUTED_VALUE"""),"rubber ball") -> rubber ball | C35: =IFERROR(__xludf.DUMMYFUNCTION("""COMPUTED_VALUE"""),"straw") -> straw | D35: =IFERROR(__xludf.DUMMYFUNCTION("""COMPUTED_VALUE"""),"two-colored tail") -> two-colored tail | E35: =IFERROR(__xludf.DUMMYFUNCTION("""COMPUTED_VALUE"""),"heart stone") -> heart stone | F35: =IFERROR(__xludf.DUMMYFUNCTION("""COMPUTED_VALUE"""),"feather stone") -> feather stone | G35: =IFERROR(__xludf.DUMMYFUNCTION("""COMPUTED_VALUE"""),"arcane flying orb") -> arcane flying orb
A36: =IFERROR(__xludf.DUMMYFUNCTION("""COMPUTED_VALUE"""),"Pidgeot") -> Pidgeot | B36: =IFERROR(__xludf.DUMMYFUNCTION("""COMPUTED_VALUE"""),"rubber ball") -> rubber ball | C36: =IFERROR(__xludf.DUMMYFUNCTION("""COMPUTED_VALUE"""),"straw") -> straw | D36: =IFERROR(__xludf.DUMMYFUNCTION("""COMPUTED_VALUE"""),"bird beak") -> bird beak | E36: =IFERROR(__xludf.DUMMYFUNCTION("""COMPUTED_VALUE"""),"heart stone") -> heart stone | F36: =IFERROR(__xludf.DUMMYFUNCTION("""COMPUTED_VALUE"""),"feather stone") -> feather stone
A37: =IFERROR(__xludf.DUMMYFUNCTION("""COMPUTED_VALUE"""),"Shiny Pidgeot") -> Shiny Pidgeot | B37: =IFERROR(__xludf.DUMMYFUNCTION("""COMPUTED_VALUE"""),"rubber ball") -> rubber ball | C37: =IFERROR(__xludf.DUMMYFUNCTION("""COMPUTED_VALUE"""),"straw") -> straw | D37: =IFERROR(__xludf.DUMMYFUNCTION("""COMPUTED_VALUE"""),"two-colored crest") -> two-colored crest | E37: =IFERROR(__xludf.DUMMYFUNCTION("""COMPUTED_VALUE"""),"heart stone") -> heart stone | F37: =IFERROR(__xludf.DUMMYFUNCTION("""COMPUTED_VALUE"""),"feather stone") -> feather stone | G37: =IFERROR(__xludf.DUMMYFUNCTION("""COMPUTED_VALUE"""),"mythic flying orb") -> mythic flying orb
A38: =IFERROR(__xludf.DUMMYFUNCTION("""COMPUTED_VALUE"""),"Rattata") -> Rattata | B38: =IFERROR(__xludf.DUMMYFUNCTION("""COMPUTED_VALUE"""),"rubber ball") -> rubber ball | C38: =IFERROR(__xludf.DUMMYFUNCTION("""COMPUTED_VALUE"""),"mouse tail") -> mouse tail
A39: =IFERROR(__xludf.DUMMYFUNCTION("""COMPUTED_VALUE"""),"Shiny Rattata") -> Shiny Rattata | B39: =IFERROR(__xludf.DUMMYFUNCTION("""COMPUTED_VALUE"""),"rubber ball") -> rubber ball | C39: =IFERROR(__xludf.DUMMYFUNCTION("""COMPUTED_VALUE"""),"blue Mouse Tail") -> blue Mouse Tail | D39: =IFERROR(__xludf.DUMMYFUNCTION("""COMPUTED_VALUE"""),"simple normal orb") -> simple normal orb
A40: =IFERROR(__xludf.DUMMYFUNCTION("""COMPUTED_VALUE"""),"Raticate") -> Raticate | B40: =IFERROR(__xludf.DUMMYFUNCTION("""COMPUTED_VALUE"""),"rubber ball") -> rubber ball | C40: =IFERROR(__xludf.DUMMYFUNCTION("""COMPUTED_VALUE"""),"rat ear") -> rat ear | D40: =IFERROR(__xludf.DUMMYFUNCTION("""COMPUTED_VALUE"""),"heart stone") -> heart stone
A41: =IFERROR(__xludf.DUMMYFUNCTION("""COMPUTED_VALUE"""),"Shiny Raticate") -> Shiny Raticate | B41: =IFERROR(__xludf.DUMMYFUNCTION("""COMPUTED_VALUE"""),"rubber ball") -> rubber ball | C41: =IFERROR(__xludf.DUMMYFUNCTION("""COMPUTED_VALUE"""),"blue rat ear") -> blue rat ear | D41: =IFERROR(__xludf.DUMMYFUNCTION("""COMPUTED_VALUE"""),"heart stone") -> heart stone | E41: =IFERROR(__xludf.DUMMYFUNCTION("""COMPUTED_VALUE"""),"arcane normal orb") -> arcane normal orb
A42: =IFERROR(__xludf.DUMMYFUNCTION("""COMPUTED_VALUE"""),"Spearow") -> Spearow | B42: =IFERROR(__xludf.DUMMYFUNCTION("""COMPUTED_VALUE"""),"rubber ball") -> rubber ball | C42: =IFERROR(__xludf.DUMMYFUNCTION("""COMPUTED_VALUE"""),"straw") -> straw | D42: =IFERROR(__xludf.DUMMYFUNCTION("""COMPUTED_VALUE"""),"bird wing") -> bird wing
A43: =IFERROR(__xludf.DUMMYFUNCTION("""COMPUTED_VALUE"""),"Shiny Spearow") -> Shiny Spearow | B43: =IFERROR(__xludf.DUMMYFUNCTION("""COMPUTED_VALUE"""),"rubber ball") -> rubber ball | C43: =IFERROR(__xludf.DUMMYFUNCTION("""COMPUTED_VALUE"""),"straw") -> straw | D43: =IFERROR(__xludf.DUMMYFUNCTION("""COMPUTED_VALUE"""),"carmine wing") -> carmine wing | E43: =IFERROR(__xludf.DUMMYFUNCTION("""COMPUTED_VALUE"""),"simple flying orb") -> simple flying orb
A44: =IFERROR(__xludf.DUMMYFUNCTION("""COMPUTED_VALUE"""),"Fearow") -> Fearow | B44: =IFERROR(__xludf.DUMMYFUNCTION("""COMPUTED_VALUE"""),"rubber ball") -> rubber ball | C44: =IFERROR(__xludf.DUMMYFUNCTION("""COMPUTED_VALUE"""),"straw") -> straw | D44: =IFERROR(__xludf.DUMMYFUNCTION("""COMPUTED_VALUE"""),"pointy beak") -> pointy beak | E44: =IFERROR(__xludf.DUMMYFUNCTION("""COMPUTED_VALUE"""),"heart stone") -> heart stone | F44: =IFERROR(__xludf.DUMMYFUNCTION("""COMPUTED_VALUE"""),"feather stone") -> feather stone
A45: =IFERROR(__xludf.DUMMYFUNCTION("""COMPUTED_VALUE"""),"Shiny Fearow") -> Shiny Fearow | B45: =IFERROR(__xludf.DUMMYFUNCTION("""COMPUTED_VALUE"""),"rubber ball") -> rubber ball | C45: =IFERROR(__xludf.DUMMYFUNCTION("""COMPUTED_VALUE"""),"straw") -> straw | D45: =IFERROR(__xludf.DUMMYFUNCTION("""COMPUTED_VALUE"""),"red pointy beak") -> red pointy beak | E45: =IFERROR(__xludf.DUMMYFUNCTION("""COMPUTED_VALUE"""),"heart stone") -> heart stone | F45: =IFERROR(__xludf.DUMMYFUNCTION("""COMPUTED_VALUE"""),"feather stone") -> feather stone | G45: =IFERROR(__xludf.DUMMYFUNCTION("""COMPUTED_VALUE"""),"arcane flying orb") -> arcane flying orb
A46: =IFERROR(__xludf.DUMMYFUNCTION("""COMPUTED_VALUE"""),"Ekans") -> Ekans | B46: =IFERROR(__xludf.DUMMYFUNCTION("""COMPUTED_VALUE"""),"bottle of poison") -> bottle of poison | C46: =IFERROR(__xludf.DUMMYFUNCTION("""COMPUTED_VALUE"""),"snake tail") -> snake tail
A47: =IFERROR(__xludf.DUMMYFUNCTION("""COMPUTED_VALUE"""),"Shiny Ekans") -> Shiny Ekans | B47: =IFERROR(__xludf.DUMMYFUNCTION("""COMPUTED_VALUE"""),"bottle of poison") -> bottle of poison | C47: =IFERROR(__xludf.DUMMYFUNCTION("""COMPUTED_VALUE"""),"gray snake tail") -> gray snake tail | D47: =IFERROR(__xludf.DUMMYFUNCTION("""COMPUTED_VALUE"""),"venom stone") -> venom stone | E47: =IFERROR(__xludf.DUMMYFUNCTION("""COMPUTED_VALUE"""),"simple poison orb") -> simple poison orb
A48: =IFERROR(__xludf.DUMMYFUNCTION("""COMPUTED_VALUE"""),"Arbok") -> Arbok | B48: =IFERROR(__xludf.DUMMYFUNCTION("""COMPUTED_VALUE"""),"bottle of poison") -> bottle of poison | C48: =IFERROR(__xludf.DUMMYFUNCTION("""COMPUTED_VALUE"""),"cobra tail") -> cobra tail | D48: =IFERROR(__xludf.DUMMYFUNCTION("""COMPUTED_VALUE"""),"venom stone") -> venom stone
A49: =IFERROR(__xludf.DUMMYFUNCTION("""COMPUTED_VALUE"""),"Shiny Arbok") -> Shiny Arbok | B49: =IFERROR(__xludf.DUMMYFUNCTION("""COMPUTED_VALUE"""),"bottle of poison") -> bottle of poison | C49: =IFERROR(__xludf.DUMMYFUNCTION("""COMPUTED_VALUE"""),"black cobra tail") -> black cobra tail | D49: =IFERROR(__xludf.DUMMYFUNCTION("""COMPUTED_VALUE"""),"venom stone") -> venom stone | E49: =IFERROR(__xludf.DUMMYFUNCTION("""COMPUTED_VALUE"""),"arcane poison orb") -> arcane poison orb
A50: =IFERROR(__xludf.DUMMYFUNCTION("""COMPUTED_VALUE"""),"Pikachu") -> Pikachu | B50: =IFERROR(__xludf.DUMMYFUNCTION("""COMPUTED_VALUE"""),"screw") -> screw | C50: =IFERROR(__xludf.DUMMYFUNCTION("""COMPUTED_VALUE"""),"electric rat tail") -> electric rat tail | D50: =IFERROR(__xludf.DUMMYFUNCTION("""COMPUTED_VALUE"""),"thunder stone") -> thunder stone
A51: =IFERROR(__xludf.DUMMYFUNCTION("""COMPUTED_VALUE"""),"Shiny Pikachu") -> Shiny Pikachu | B51: =IFERROR(__xludf.DUMMYFUNCTION("""COMPUTED_VALUE"""),"screw") -> screw | C51: =IFERROR(__xludf.DUMMYFUNCTION("""COMPUTED_VALUE"""),"electric rat tail") -> electric rat tail | D51: =IFERROR(__xludf.DUMMYFUNCTION("""COMPUTED_VALUE"""),"thunder stone") -> thunder stone | E51: =IFERROR(__xludf.DUMMYFUNCTION("""COMPUTED_VALUE"""),"arcane electric orb") -> arcane electric orb
A52: =IFERROR(__xludf.DUMMYFUNCTION("""COMPUTED_VALUE"""),"Raichu") -> Raichu | B52: =IFERROR(__xludf.DUMMYFUNCTION("""COMPUTED_VALUE"""),"screw") -> screw | C52: =IFERROR(__xludf.DUMMYFUNCTION("""COMPUTED_VALUE"""),"electric ear") -> electric ear | D52: =IFERROR(__xludf.DUMMYFUNCTION("""COMPUTED_VALUE"""),"thunder stone") -> thunder stone
A53: =IFERROR(__xludf.DUMMYFUNCTION("""COMPUTED_VALUE"""),"Shiny Raichu") -> Shiny Raichu | B53: =IFERROR(__xludf.DUMMYFUNCTION("""COMPUTED_VALUE"""),"screw") -> screw | C53: =IFERROR(__xludf.DUMMYFUNCTION("""COMPUTED_VALUE"""),"electric white ear") -> electric white ear | D53: =IFERROR(__xludf.DUMMYFUNCTION("""COMPUTED_VALUE"""),"thunder stone") -> thunder stone | E53: =IFERROR(__xludf.DUMMYFUNCTION("""COMPUTED_VALUE"""),"mythic electric orb") -> mythic electric orb
A54: =IFERROR(__xludf.DUMMYFUNCTION("""COMPUTED_VALUE"""),"Sandshrew") -> Sandshrew | B54: =IFERROR(__xludf.DUMMYFUNCTION("""COMPUTED_VALUE"""),"earth ball") -> earth ball | C54: =IFERROR(__xludf.DUMMYFUNCTION("""COMPUTED_VALUE"""),"armadillo tail") -> armadillo tail
A55: =IFERROR(__xludf.DUMMYFUNCTION("""COMPUTED_VALUE"""),"Shiny Sandshrew") -> Shiny Sandshrew | B55: =IFERROR(__xludf.DUMMYFUNCTION("""COMPUTED_VALUE"""),"earth ball") -> earth ball | C55: =IFERROR(__xludf.DUMMYFUNCTION("""COMPUTED_VALUE"""),"armadillo red tail") -> armadillo red tail | D55: =IFERROR(__xludf.DUMMYFUNCTION("""COMPUTED_VALUE"""),"earth stone") -> earth stone | E55: =IFERROR(__xludf.DUMMYFUNCTION("""COMPUTED_VALUE"""),"simple ground orb") -> simple ground orb
A56: =IFERROR(__xludf.DUMMYFUNCTION("""COMPUTED_VALUE"""),"Sandslash") -> Sandslash | B56: =IFERROR(__xludf.DUMMYFUNCTION("""COMPUTED_VALUE"""),"earth ball") -> earth ball | C56: =IFERROR(__xludf.DUMMYFUNCTION("""COMPUTED_VALUE"""),"armadillo claw") -> armadillo claw | D56: =IFERROR(__xludf.DUMMYFUNCTION("""COMPUTED_VALUE"""),"earth stone") -> earth stone
A57: =IFERROR(__xludf.DUMMYFUNCTION("""COMPUTED_VALUE"""),"Shiny Sandslash") -> Shiny Sandslash | B57: =IFERROR(__xludf.DUMMYFUNCTION("""COMPUTED_VALUE"""),"earth ball") -> earth ball | C57: =IFERROR(__xludf.DUMMYFUNCTION("""COMPUTED_VALUE"""),"shining claws") -> shining claws | D57: =IFERROR(__xludf.DUMMYFUNCTION("""COMPUTED_VALUE"""),"earth stone") -> earth stone | E57: =IFERROR(__xludf.DUMMYFUNCTION("""COMPUTED_VALUE"""),"arcane ground orb") -> arcane ground orb
A58: =IFERROR(__xludf.DUMMYFUNCTION("""COMPUTED_VALUE"""),"Nidoran female") -> Nidoran female | B58: =IFERROR(__xludf.DUMMYFUNCTION("""COMPUTED_VALUE"""),"bottle of poison") -> bottle of poison | C58: =IFERROR(__xludf.DUMMYFUNCTION("""COMPUTED_VALUE"""),"small blue ear") -> small blue ear
A59: =IFERROR(__xludf.DUMMYFUNCTION("""COMPUTED_VALUE"""),"Shiny Nidoran female") -> Shiny Nidoran female | B59: =IFERROR(__xludf.DUMMYFUNCTION("""COMPUTED_VALUE"""),"bottle of poison") -> bottle of poison | C59: =IFERROR(__xludf.DUMMYFUNCTION("""COMPUTED_VALUE"""),"small green ear") -> small green ear | D59: =IFERROR(__xludf.DUMMYFUNCTION("""COMPUTED_VALUE"""),"simple poison orb") -> simple poison orb
A60: =IFERROR(__xludf.DUMMYFUNCTION("""COMPUTED_VALUE"""),"Nidorina") -> Nidorina | B60: =IFERROR(__xludf.DUMMYFUNCTION("""COMPUTED_VALUE"""),"bottle of poison") -> bottle of poison | C60: =IFERROR(__xludf.DUMMYFUNCTION("""COMPUTED_VALUE"""),"blue nido ear") -> blue nido ear | D60: =IFERROR(__xludf.DUMMYFUNCTION("""COMPUTED_VALUE"""),"venom stone") -> venom stone
A61: =IFERROR(__xludf.DUMMYFUNCTION("""COMPUTED_VALUE"""),"Shiny Nidorina") -> Shiny Nidorina | B61: =IFERROR(__xludf.DUMMYFUNCTION("""COMPUTED_VALUE"""),"bottle of poison") -> bottle of poison | C61: =IFERROR(__xludf.DUMMYFUNCTION("""COMPUTED_VALUE"""),"green nido ear") -> green nido ear | D61: =IFERROR(__xludf.DUMMYFUNCTION("""COMPUTED_VALUE"""),"venom stone") -> venom stone | E61: =IFERROR(__xludf.DUMMYFUNCTION("""COMPUTED_VALUE"""),"arcane poison orb") -> arcane poison orb
A62: =IFERROR(__xludf.DUMMYFUNCTION("""COMPUTED_VALUE"""),"Nidoqueen") -> Nidoqueen | B62: =IFERROR(__xludf.DUMMYFUNCTION("""COMPUTED_VALUE"""),"bottle of poison") -> bottle of poison | C62: =IFERROR(__xludf.DUMMYFUNCTION("""COMPUTED_VALUE"""),"earth ball") -> earth ball | D62: =IFERROR(__xludf.DUMMYFUNCTION("""COMPUTED_VALUE"""),"queen ear") -> queen ear | E62: =IFERROR(__xludf.DUMMYFUNCTION("""COMPUTED_VALUE"""),"venom stone") -> venom stone | F62: =IFERROR(__xludf.DUMMYFUNCTION("""COMPUTED_VALUE"""),"earth stone") -> earth stone
A63: =IFERROR(__xludf.DUMMYFUNCTION("""COMPUTED_VALUE"""),"Shiny Nidoqueen") -> Shiny Nidoqueen | B63: =IFERROR(__xludf.DUMMYFUNCTION("""COMPUTED_VALUE"""),"bottle of poison") -> bottle of poison | C63: =IFERROR(__xludf.DUMMYFUNCTION("""COMPUTED_VALUE"""),"earth ball") -> earth ball | D63: =IFERROR(__xludf.DUMMYFUNCTION("""COMPUTED_VALUE"""),"green queen ear") -> green queen ear | E63: =IFERROR(__xludf.DUMMYFUNCTION("""COMPUTED_VALUE"""),"venom stone") -> venom stone | F63: =IFERROR(__xludf.DUMMYFUNCTION("""COMPUTED_VALUE"""),"earth stone") -> earth stone | G63: =IFERROR(__xludf.DUMMYFUNCTION("""COMPUTED_VALUE"""),"mythic poison orb") -> mythic poison orb
A64: =IFERROR(__xludf.DUMMYFUNCTION("""COMPUTED_VALUE"""),"Nidoran Male") -> Nidoran Male | B64: =IFERROR(__xludf.DUMMYFUNCTION("""COMPUTED_VALUE"""),"bottle of poison") -> bottle of poison | C64: =IFERROR(__xludf.DUMMYFUNCTION("""COMPUTED_VALUE"""),"small purple ear") -> small purple ear
A65: =IFERROR(__xludf.DUMMYFUNCTION("""COMPUTED_VALUE"""),"Shiny Nidoran Male") -> Shiny Nidoran Male | B65: =IFERROR(__xludf.DUMMYFUNCTION("""COMPUTED_VALUE"""),"bottle of poison") -> bottle of poison | C65: =IFERROR(__xludf.DUMMYFUNCTION("""COMPUTED_VALUE"""),"small blue ear") -> small blue ear | D65: =IFERROR(__xludf.DUMMYFUNCTION("""COMPUTED_VALUE"""),"simple poison orb") -> simple poison orb
A66: =IFERROR(__xludf.DUMMYFUNCTION("""COMPUTED_VALUE"""),"Nidorino") -> Nidorino | B66: =IFERROR(__xludf.DUMMYFUNCTION("""COMPUTED_VALUE"""),"bottle of poison") -> bottle of poison | C66: =IFERROR(__xludf.DUMMYFUNCTION("""COMPUTED_VALUE"""),"purple nido ear") -> purple nido ear | D66: =IFERROR(__xludf.DUMMYFUNCTION("""COMPUTED_VALUE"""),"venom stone") -> venom stone
A67: =IFERROR(__xludf.DUMMYFUNCTION("""COMPUTED_VALUE"""),"Shiny Nidorino") -> Shiny Nidorino | B67: =IFERROR(__xludf.DUMMYFUNCTION("""COMPUTED_VALUE"""),"bottle of poison") -> bottle of poison | C67: =IFERROR(__xludf.DUMMYFUNCTION("""COMPUTED_VALUE"""),"blue nido ear ear") -> blue nido ear ear | D67: =IFERROR(__xludf.DUMMYFUNCTION("""COMPUTED_VALUE"""),"venom stone") -> venom stone | E67: =IFERROR(__xludf.DUMMYFUNCTION("""COMPUTED_VALUE"""),"arcane poison orb") -> arcane poison orb
A68: =IFERROR(__xludf.DUMMYFUNCTION("""COMPUTED_VALUE"""),"Nidoking") -> Nidoking | B68: =IFERROR(__xludf.DUMMYFUNCTION("""COMPUTED_VALUE"""),"bottle of poison") -> bottle of poison | C68: =IFERROR(__xludf.DUMMYFUNCTION("""COMPUTED_VALUE"""),"earth ball") -> earth ball | D68: =IFERROR(__xludf.DUMMYFUNCTION("""COMPUTED_VALUE"""),"king ear") -> king ear | E68: =IFERROR(__xludf.DUMMYFUNCTION("""COMPUTED_VALUE"""),"venom stone") -> venom stone | F68: =IFERROR(__xludf.DUMMYFUNCTION("""COMPUTED_VALUE"""),"earth stone") -> earth stone
A69: =IFERROR(__xludf.DUMMYFUNCTION("""COMPUTED_VALUE"""),"Shiny Nidoking") -> Shiny Nidoking | B69: =IFERROR(__xludf.DUMMYFUNCTION("""COMPUTED_VALUE"""),"bottle of poison") -> bottle of poison | C69: =IFERROR(__xludf.DUMMYFUNCTION("""COMPUTED_VALUE"""),"earth ball") -> earth ball | D69: =IFERROR(__xludf.DUMMYFUNCTION("""COMPUTED_VALUE"""),"blue king ear") -> blue king ear | E69: =IFERROR(__xludf.DUMMYFUNCTION("""COMPUTED_VALUE"""),"venom stone") -> venom stone | F69: =IFERROR(__xludf.DUMMYFUNCTION("""COMPUTED_VALUE"""),"earth stone") -> earth stone | G69: =IFERROR(__xludf.DUMMYFUNCTION("""COMPUTED_VALUE"""),"mythic poison orb") -> mythic poison orb
A70: =IFERROR(__xludf.DUMMYFUNCTION("""COMPUTED_VALUE"""),"Clefairy") -> Clefairy | B70: =IFERROR(__xludf.DUMMYFUNCTION("""COMPUTED_VALUE"""),"fairy essence") -> fairy essence | C70: =IFERROR(__xludf.DUMMYFUNCTION("""COMPUTED_VALUE"""),"moon topknot") -> moon topknot | D70: =IFERROR(__xludf.DUMMYFUNCTION("""COMPUTED_VALUE"""),"fairy stone") -> fairy stone
A71: =IFERROR(__xludf.DUMMYFUNCTION("""COMPUTED_VALUE"""),"Shiny Clefairy") -> Shiny Clefairy | B71: =IFERROR(__xludf.DUMMYFUNCTION("""COMPUTED_VALUE"""),"fairy essence") -> fairy essence | C71: =IFERROR(__xludf.DUMMYFUNCTION("""COMPUTED_VALUE"""),"purple moon topknot") -> purple moon topknot | D71: =IFERROR(__xludf.DUMMYFUNCTION("""COMPUTED_VALUE"""),"fairy stone") -> fairy stone | E71: =IFERROR(__xludf.DUMMYFUNCTION("""COMPUTED_VALUE"""),"simple fairy orb") -> simple fairy orb
A72: =IFERROR(__xludf.DUMMYFUNCTION("""COMPUTED_VALUE"""),"Clefable") -> Clefable | B72: =IFERROR(__xludf.DUMMYFUNCTION("""COMPUTED_VALUE"""),"fairy essence") -> fairy essence | C72: =IFERROR(__xludf.DUMMYFUNCTION("""COMPUTED_VALUE"""),"pink wings") -> pink wings | D72: =IFERROR(__xludf.DUMMYFUNCTION("""COMPUTED_VALUE"""),"fairy stone") -> fairy stone
A73: =IFERROR(__xludf.DUMMYFUNCTION("""COMPUTED_VALUE"""),"Shiny Clefable") -> Shiny Clefable | B73: =IFERROR(__xludf.DUMMYFUNCTION("""COMPUTED_VALUE"""),"fairy essence") -> fairy essence | C73: =IFERROR(__xludf.DUMMYFUNCTION("""COMPUTED_VALUE"""),"blue wings") -> blue wings | D73: =IFERROR(__xludf.DUMMYFUNCTION("""COMPUTED_VALUE"""),"fairy stone") -> fairy stone | E73: =IFERROR(__xludf.DUMMYFUNCTION("""COMPUTED_VALUE"""),"arcane fairy orb") -> arcane fairy orb
A74: =IFERROR(__xludf.DUMMYFUNCTION("""COMPUTED_VALUE"""),"Vulpix") -> Vulpix | B74: =IFERROR(__xludf.DUMMYFUNCTION("""COMPUTED_VALUE"""),"essence of fire") -> essence of fire | C74: =IFERROR(__xludf.DUMMYFUNCTION("""COMPUTED_VALUE"""),"canine tail") -> canine tail
A75: =IFERROR(__xludf.DUMMYFUNCTION("""COMPUTED_VALUE"""),"Shiny Vulpix") -> Shiny Vulpix | B75: =IFERROR(__xludf.DUMMYFUNCTION("""COMPUTED_VALUE"""),"essence of fire") -> essence of fire | C75: =IFERROR(__xludf.DUMMYFUNCTION("""COMPUTED_VALUE"""),"blue canine tail") -> blue canine tail | D75: =IFERROR(__xludf.DUMMYFUNCTION("""COMPUTED_VALUE"""),"fire stone") -> fire stone | E75: =IFERROR(__xludf.DUMMYFUNCTION("""COMPUTED_VALUE"""),"simple fire orb") -> simple fire orb
A76: =IFERROR(__xludf.DUMMYFUNCTION("""COMPUTED_VALUE"""),"Ninetales") -> Ninetales | B76: =IFERROR(__xludf.DUMMYFUNCTION("""COMPUTED_VALUE"""),"essence of fire") -> essence of fire | C76: =IFERROR(__xludf.DUMMYFUNCTION("""COMPUTED_VALUE"""),"fox tail") -> fox tail | D76: =IFERROR(__xludf.DUMMYFUNCTION("""COMPUTED_VALUE"""),"fire stone") -> fire stone
A77: =IFERROR(__xludf.DUMMYFUNCTION("""COMPUTED_VALUE"""),"Shiny Ninetales") -> Shiny Ninetales | B77: =IFERROR(__xludf.DUMMYFUNCTION("""COMPUTED_VALUE"""),"essence of fire") -> essence of fire | C77: =IFERROR(__xludf.DUMMYFUNCTION("""COMPUTED_VALUE"""),"blue fox tail") -> blue fox tail | D77: =IFERROR(__xludf.DUMMYFUNCTION("""COMPUTED_VALUE"""),"fire stone") -> fire stone | E77: =IFERROR(__xludf.DUMMYFUNCTION("""COMPUTED_VALUE"""),"mythic fire orb") -> mythic fire orb
A78: =IFERROR(__xludf.DUMMYFUNCTION("""COMPUTED_VALUE"""),"Jigglypuff") -> Jigglypuff | B78: =IFERROR(__xludf.DUMMYFUNCTION("""COMPUTED_VALUE"""),"rubber ball") -> rubber ball | C78: =IFERROR(__xludf.DUMMYFUNCTION("""COMPUTED_VALUE"""),"fairy essence") -> fairy essence | D78: =IFERROR(__xludf.DUMMYFUNCTION("""COMPUTED_VALUE"""),"microphone") -> microphone | E78: =IFERROR(__xludf.DUMMYFUNCTION("""COMPUTED_VALUE"""),"fairy stone") -> fairy stone
A79: =IFERROR(__xludf.DUMMYFUNCTION("""COMPUTED_VALUE"""),"Shiny Jigglypuff") -> Shiny Jigglypuff | B79: =IFERROR(__xludf.DUMMYFUNCTION("""COMPUTED_VALUE"""),"rubber ball") -> rubber ball | C79: =IFERROR(__xludf.DUMMYFUNCTION("""COMPUTED_VALUE"""),"fairy essence") -> fairy essence | D79: =IFERROR(__xludf.DUMMYFUNCTION("""COMPUTED_VALUE"""),"loud microphone") -> loud microphone | E79: =IFERROR(__xludf.DUMMYFUNCTION("""COMPUTED_VALUE"""),"fairy stone") -> fairy stone | F79: =IFERROR(__xludf.DUMMYFUNCTION("""COMPUTED_VALUE"""),"simple fairy orb") -> simple fairy orb
A80: =IFERROR(__xludf.DUMMYFUNCTION("""COMPUTED_VALUE"""),"Wigglytuff") -> Wigglytuff | B80: =IFERROR(__xludf.DUMMYFUNCTION("""COMPUTED_VALUE"""),"rubber ball") -> rubber ball | C80: =IFERROR(__xludf.DUMMYFUNCTION("""COMPUTED_VALUE"""),"fairy essence") -> fairy essence | D80: =IFERROR(__xludf.DUMMYFUNCTION("""COMPUTED_VALUE"""),"wigglytuff ear") -> wigglytuff ear | E80: =IFERROR(__xludf.DUMMYFUNCTION("""COMPUTED_VALUE"""),"fairy stone") -> fairy stone
A81: =IFERROR(__xludf.DUMMYFUNCTION("""COMPUTED_VALUE"""),"Shiny Wigglytuff") -> Shiny Wigglytuff | B81: =IFERROR(__xludf.DUMMYFUNCTION("""COMPUTED_VALUE"""),"rubber ball") -> rubber ball | C81: =IFERROR(__xludf.DUMMYFUNCTION("""COMPUTED_VALUE"""),"fairy essence") -> fairy essence | D81: =IFERROR(__xludf.DUMMYFUNCTION("""COMPUTED_VALUE"""),"big cute ear") -> big cute ear | E81: =IFERROR(__xludf.DUMMYFUNCTION("""COMPUTED_VALUE"""),"fairy stone") -> fairy stone | F81: =IFERROR(__xludf.DUMMYFUNCTION("""COMPUTED_VALUE"""),"arcane fairy orb") -> arcane fairy orb
A82: =IFERROR(__xludf.DUMMYFUNCTION("""COMPUTED_VALUE"""),"Zubat") -> Zubat | B82: =IFERROR(__xludf.DUMMYFUNCTION("""COMPUTED_VALUE"""),"bottle of poison") -> bottle of poison | C82: =IFERROR(__xludf.DUMMYFUNCTION("""COMPUTED_VALUE"""),"straw") -> straw | D82: =IFERROR(__xludf.DUMMYFUNCTION("""COMPUTED_VALUE"""),"bat wing") -> bat wing
A83: =IFERROR(__xludf.DUMMYFUNCTION("""COMPUTED_VALUE"""),"Shiny Zubat") -> Shiny Zubat | B83: =IFERROR(__xludf.DUMMYFUNCTION("""COMPUTED_VALUE"""),"bottle of poison") -> bottle of poison | C83: =IFERROR(__xludf.DUMMYFUNCTION("""COMPUTED_VALUE"""),"straw") -> straw | D83: =IFERROR(__xludf.DUMMYFUNCTION("""COMPUTED_VALUE"""),"green bat wing") -> green bat wing | E83: =IFERROR(__xludf.DUMMYFUNCTION("""COMPUTED_VALUE"""),"venom stone") -> venom stone | F83: =IFERROR(__xludf.DUMMYFUNCTION("""COMPUTED_VALUE"""),"feather stone") -> feather stone | G83: =IFERROR(__xludf.DUMMYFUNCTION("""COMPUTED_VALUE"""),"simple poison orb") -> simple poison orb
A84: =IFERROR(__xludf.DUMMYFUNCTION("""COMPUTED_VALUE"""),"Golbat") -> Golbat | B84: =IFERROR(__xludf.DUMMYFUNCTION("""COMPUTED_VALUE"""),"bottle of poison") -> bottle of poison | C84: =IFERROR(__xludf.DUMMYFUNCTION("""COMPUTED_VALUE"""),"straw") -> straw | D84: =IFERROR(__xludf.DUMMYFUNCTION("""COMPUTED_VALUE"""),"vampire wing") -> vampire wing | E84: =IFERROR(__xludf.DUMMYFUNCTION("""COMPUTED_VALUE"""),"venom stone") -> venom stone | F84: =IFERROR(__xludf.DUMMYFUNCTION("""COMPUTED_VALUE"""),"feather stone") -> feather stone
A85: =IFERROR(__xludf.DUMMYFUNCTION("""COMPUTED_VALUE"""),"Shiny Golbat") -> Shiny Golbat | B85: =IFERROR(__xludf.DUMMYFUNCTION("""COMPUTED_VALUE"""),"bottle of poison") -> bottle of poison | C85: =IFERROR(__xludf.DUMMYFUNCTION("""COMPUTED_VALUE"""),"straw") -> straw | D85: =IFERROR(__xludf.DUMMYFUNCTION("""COMPUTED_VALUE"""),"green vampire wing") -> green vampire wing | E85: =IFERROR(__xludf.DUMMYFUNCTION("""COMPUTED_VALUE"""),"venom stone") -> venom stone | F85: =IFERROR(__xludf.DUMMYFUNCTION("""COMPUTED_VALUE"""),"feather stone") -> feather stone | G85: =IFERROR(__xludf.DUMMYFUNCTION("""COMPUTED_VALUE"""),"arcane poison orb") -> arcane poison orb
A86: =IFERROR(__xludf.DUMMYFUNCTION("""COMPUTED_VALUE"""),"Oddish") -> Oddish | B86: =IFERROR(__xludf.DUMMYFUNCTION("""COMPUTED_VALUE"""),"seed") -> seed | C86: =IFERROR(__xludf.DUMMYFUNCTION("""COMPUTED_VALUE"""),"bottle of poison") -> bottle of poison | D86: =IFERROR(__xludf.DUMMYFUNCTION("""COMPUTED_VALUE"""),"leaves") -> leaves
A87: =IFERROR(__xludf.DUMMYFUNCTION("""COMPUTED_VALUE"""),"Shiny Oddish") -> Shiny Oddish | B87: =IFERROR(__xludf.DUMMYFUNCTION("""COMPUTED_VALUE"""),"seed") -> seed | C87: =IFERROR(__xludf.DUMMYFUNCTION("""COMPUTED_VALUE"""),"bottle of poison") -> bottle of poison | D87: =IFERROR(__xludf.DUMMYFUNCTION("""COMPUTED_VALUE"""),"radiant leaves") -> radiant leaves | E87: =IFERROR(__xludf.DUMMYFUNCTION("""COMPUTED_VALUE"""),"simple grass orb") -> simple grass orb
A88: =IFERROR(__xludf.DUMMYFUNCTION("""COMPUTED_VALUE"""),"Gloom") -> Gloom | B88: =IFERROR(__xludf.DUMMYFUNCTION("""COMPUTED_VALUE"""),"seed") -> seed | C88: =IFERROR(__xludf.DUMMYFUNCTION("""COMPUTED_VALUE"""),"bottle of poison") -> bottle of poison | D88: =IFERROR(__xludf.DUMMYFUNCTION("""COMPUTED_VALUE"""),"poison bulb") -> poison bulb | E88: =IFERROR(__xludf.DUMMYFUNCTION("""COMPUTED_VALUE"""),"leaf stone") -> leaf stone | F88: =IFERROR(__xludf.DUMMYFUNCTION("""COMPUTED_VALUE"""),"venom stone") -> venom stone
A89: =IFERROR(__xludf.DUMMYFUNCTION("""COMPUTED_VALUE"""),"Shiny Gloom") -> Shiny Gloom | B89: =IFERROR(__xludf.DUMMYFUNCTION("""COMPUTED_VALUE"""),"seed") -> seed | C89: =IFERROR(__xludf.DUMMYFUNCTION("""COMPUTED_VALUE"""),"bottle of poison") -> bottle of poison | D89: =IFERROR(__xludf.DUMMYFUNCTION("""COMPUTED_VALUE"""),"brown poison bulb") -> brown poison bulb | E89: =IFERROR(__xludf.DUMMYFUNCTION("""COMPUTED_VALUE"""),"leaf stone") -> leaf stone | F89: =IFERROR(__xludf.DUMMYFUNCTION("""COMPUTED_VALUE"""),"venom stone") -> venom stone | G89: =IFERROR(__xludf.DUMMYFUNCTION("""COMPUTED_VALUE"""),"arcane grass orb") -> arcane grass orb
A90: =IFERROR(__xludf.DUMMYFUNCTION("""COMPUTED_VALUE"""),"Vileplume") -> Vileplume | B90: =IFERROR(__xludf.DUMMYFUNCTION("""COMPUTED_VALUE"""),"seed") -> seed | C90: =IFERROR(__xludf.DUMMYFUNCTION("""COMPUTED_VALUE"""),"bottle of poison") -> bottle of poison | D90: =IFERROR(__xludf.DUMMYFUNCTION("""COMPUTED_VALUE"""),"poison petal") -> poison petal | E90: =IFERROR(__xludf.DUMMYFUNCTION("""COMPUTED_VALUE"""),"leaf stone") -> leaf stone | F90: =IFERROR(__xludf.DUMMYFUNCTION("""COMPUTED_VALUE"""),"venom stone") -> venom stone
A91: =IFERROR(__xludf.DUMMYFUNCTION("""COMPUTED_VALUE"""),"Shiny Vileplume") -> Shiny Vileplume | B91: =IFERROR(__xludf.DUMMYFUNCTION("""COMPUTED_VALUE"""),"seed") -> seed | C91: =IFERROR(__xludf.DUMMYFUNCTION("""COMPUTED_VALUE"""),"bottle of poison") -> bottle of poison | D91: =IFERROR(__xludf.DUMMYFUNCTION("""COMPUTED_VALUE"""),"yellow poison petal") -> yellow poison petal | E91: =IFERROR(__xludf.DUMMYFUNCTION("""COMPUTED_VALUE"""),"leaf stone") -> leaf stone | F91: =IFERROR(__xludf.DUMMYFUNCTION("""COMPUTED_VALUE"""),"venom stone") -> venom stone | G91: =IFERROR(__xludf.DUMMYFUNCTION("""COMPUTED_VALUE"""),"arcane grass orb") -> arcane grass orb
A92: =IFERROR(__xludf.DUMMYFUNCTION("""COMPUTED_VALUE"""),"Paras") -> Paras | B92: =IFERROR(__xludf.DUMMYFUNCTION("""COMPUTED_VALUE"""),"bug gosme") -> bug gosme | C92: =IFERROR(__xludf.DUMMYFUNCTION("""COMPUTED_VALUE"""),"seed") -> seed | D92: =IFERROR(__xludf.DUMMYFUNCTION("""COMPUTED_VALUE"""),"mushroom") -> mushroom
A93: =IFERROR(__xludf.DUMMYFUNCTION("""COMPUTED_VALUE"""),"Shiny Paras") -> Shiny Paras | B93: =IFERROR(__xludf.DUMMYFUNCTION("""COMPUTED_VALUE"""),"bug gosme") -> bug gosme | C93: =IFERROR(__xludf.DUMMYFUNCTION("""COMPUTED_VALUE"""),"seed") -> seed | D93: =IFERROR(__xludf.DUMMYFUNCTION("""COMPUTED_VALUE"""),"green mushroom") -> green mushroom | E93: =IFERROR(__xludf.DUMMYFUNCTION("""COMPUTED_VALUE"""),"cocoon stone") -> cocoon stone | F93: =IFERROR(__xludf.DUMMYFUNCTION("""COMPUTED_VALUE"""),"leaf stone") -> leaf stone | G93: =IFERROR(__xludf.DUMMYFUNCTION("""COMPUTED_VALUE"""),"simple bug orb") -> simple bug orb
A94: =IFERROR(__xludf.DUMMYFUNCTION("""COMPUTED_VALUE"""),"Parasect") -> Parasect | B94: =IFERROR(__xludf.DUMMYFUNCTION("""COMPUTED_VALUE"""),"bug gosme") -> bug gosme | C94: =IFERROR(__xludf.DUMMYFUNCTION("""COMPUTED_VALUE"""),"seed") -> seed | D94: =IFERROR(__xludf.DUMMYFUNCTION("""COMPUTED_VALUE"""),"big mushroom") -> big mushroom | E94: =IFERROR(__xludf.DUMMYFUNCTION("""COMPUTED_VALUE"""),"cocoon stone") -> cocoon stone | F94: =IFERROR(__xludf.DUMMYFUNCTION("""COMPUTED_VALUE"""),"leaf stone") -> leaf stone
A95: =IFERROR(__xludf.DUMMYFUNCTION("""COMPUTED_VALUE"""),"Shiny Parasect") -> Shiny Parasect | B95: =IFERROR(__xludf.DUMMYFUNCTION("""COMPUTED_VALUE"""),"bug gosme") -> bug gosme | C95: =IFERROR(__xludf.DUMMYFUNCTION("""COMPUTED_VALUE"""),"seed") -> seed | D95: =IFERROR(__xludf.DUMMYFUNCTION("""COMPUTED_VALUE"""),"green big mushroom") -> green big mushroom | E95: =IFERROR(__xludf.DUMMYFUNCTION("""COMPUTED_VALUE"""),"cocoon stone") -> cocoon stone | F95: =IFERROR(__xludf.DUMMYFUNCTION("""COMPUTED_VALUE"""),"leaf stone") -> leaf stone | G95: =IFERROR(__xludf.DUMMYFUNCTION("""COMPUTED_VALUE"""),"arcane bug orb") -> arcane bug orb
A96: =IFERROR(__xludf.DUMMYFUNCTION("""COMPUTED_VALUE"""),"Venonat") -> Venonat | B96: =IFERROR(__xludf.DUMMYFUNCTION("""COMPUTED_VALUE"""),"bug gosme") -> bug gosme | C96: =IFERROR(__xludf.DUMMYFUNCTION("""COMPUTED_VALUE"""),"bottle of poison") -> bottle of poison | D96: =IFERROR(__xludf.DUMMYFUNCTION("""COMPUTED_VALUE"""),"bug antenna") -> bug antenna
A97: =IFERROR(__xludf.DUMMYFUNCTION("""COMPUTED_VALUE"""),"Shiny Venonat") -> Shiny Venonat | B97: =IFERROR(__xludf.DUMMYFUNCTION("""COMPUTED_VALUE"""),"bug gosme") -> bug gosme | C97: =IFERROR(__xludf.DUMMYFUNCTION("""COMPUTED_VALUE"""),"bottle of poison") -> bottle of poison | D97: =IFERROR(__xludf.DUMMYFUNCTION("""COMPUTED_VALUE"""),"blue bug antenna") -> blue bug antenna | E97: =IFERROR(__xludf.DUMMYFUNCTION("""COMPUTED_VALUE"""),"cocoon stone") -> cocoon stone | F97: =IFERROR(__xludf.DUMMYFUNCTION("""COMPUTED_VALUE"""),"venom stone") -> venom stone | G97: =IFERROR(__xludf.DUMMYFUNCTION("""COMPUTED_VALUE"""),"simple bug orb") -> simple bug orb
A98: =IFERROR(__xludf.DUMMYFUNCTION("""COMPUTED_VALUE"""),"Venomoth") -> Venomoth | B98: =IFERROR(__xludf.DUMMYFUNCTION("""COMPUTED_VALUE"""),"bug gosme") -> bug gosme | C98: =IFERROR(__xludf.DUMMYFUNCTION("""COMPUTED_VALUE"""),"bottle of poison") -> bottle of poison | D98: =IFERROR(__xludf.DUMMYFUNCTION("""COMPUTED_VALUE"""),"moth wing") -> moth wing | E98: =IFERROR(__xludf.DUMMYFUNCTION("""COMPUTED_VALUE"""),"cocoon stone") -> cocoon stone | F98: =IFERROR(__xludf.DUMMYFUNCTION("""COMPUTED_VALUE"""),"venom stone") -> venom stone
A99: =IFERROR(__xludf.DUMMYFUNCTION("""COMPUTED_VALUE"""),"Shiny Venomoth") -> Shiny Venomoth | B99: =IFERROR(__xludf.DUMMYFUNCTION("""COMPUTED_VALUE"""),"bug gosme") -> bug gosme | C99: =IFERROR(__xludf.DUMMYFUNCTION("""COMPUTED_VALUE"""),"bottle of poison") -> bottle of poison | D99: =IFERROR(__xludf.DUMMYFUNCTION("""COMPUTED_VALUE"""),"blue moth wing") -> blue moth wing | E99: =IFERROR(__xludf.DUMMYFUNCTION("""COMPUTED_VALUE"""),"cocoon stone") -> cocoon stone | F99: =IFERROR(__xludf.DUMMYFUNCTION("""COMPUTED_VALUE"""),"venom stone") -> venom stone | G99: =IFERROR(__xludf.DUMMYFUNCTION("""COMPUTED_VALUE"""),"arcane poison orb") -> arcane poison orb
A100: =IFERROR(__xludf.DUMMYFUNCTION("""COMPUTED_VALUE"""),"Diglett") -> Diglett | B100: =IFERROR(__xludf.DUMMYFUNCTION("""COMPUTED_VALUE"""),"earth ball") -> earth ball | C100: =IFERROR(__xludf.DUMMYFUNCTION("""COMPUTED_VALUE"""),"small handfull of stones") -> small handfull of stones
...

Sheet Index
B8: =HYPERLINK("https://docs.google.com/spreadsheets/d/1GCH3PmFKQrBj7AA51hgqfg6Q2SrvNgrNlxgIidVeTMU/edit?pli=1&gid=1112155848#gid=1112155848",IMAGE("https://i.imgur.com/uwh7mPY.png")) | F8: =HYPERLINK("https://docs.google.com/spreadsheets/d/1GCH3PmFKQrBj7AA51hgqfg6Q2SrvNgrNlxgIidVeTMU/edit?pli=1&gid=1881536412#gid=1881536412",IMAGE("https://i.imgur.com/pjoG0fa.png")) | J8: =HYPERLINK("https://docs.google.com/spreadsheets/d/1GCH3PmFKQrBj7AA51hgqfg6Q2SrvNgrNlxgIidVeTMU/edit?pli=1&gid=622619474#gid=622619474",IMAGE("https://i.imgur.com/EDc1VZz.png"))
J13: =HYPERLINK("https://docs.google.com/spreadsheets/d/1GCH3PmFKQrBj7AA51hgqfg6Q2SrvNgrNlxgIidVeTMU/edit?pli=1&gid=1112155848#gid=1112155848",IMAGE("https://imgur.com/a/FhRl6MG"))
B14: =HYPERLINK("https://docs.google.com/spreadsheets/d/1GCH3PmFKQrBj7AA51hgqfg6Q2SrvNgrNlxgIidVeTMU/edit?pli=1&gid=751365694#gid=751365694",IMAGE("https://i.imgur.com/mQmfFCu.png")) | F14: =HYPERLINK("https://docs.google.com/spreadsheets/d/1GCH3PmFKQrBj7AA51hgqfg6Q2SrvNgrNlxgIidVeTMU/edit?pli=1&gid=1798431963#gid=1798431963",IMAGE("https://i.imgur.com/u9P90MY.png"))
B20: =HYPERLINK("https://docs.google.com/spreadsheets/d/1GCH3PmFKQrBj7AA51hgqfg6Q2SrvNgrNlxgIidVeTMU/edit?pli=1&gid=1684775291#gid=1684775291",IMAGE("https://i.imgur.com/h5PYsbu.png")) | F20: =HYPERLINK("https://docs.google.com/spreadsheets/d/1GCH3PmFKQrBj7AA51hgqfg6Q2SrvNgrNlxgIidVeTMU/edit?pli=1&gid=1372498596#gid=1372498596",IMAGE("https://i.imgur.com/TIQizsS.png"))

Sheet FAQ
A1: star | B1: Star Ascension: wiki.pokealliance.com/sistemas/star-machine / Calculadora de custos pra estrelar: tinyurl.com/planilha-pka-star A máquina fica subindo uma escada no TC | C1: ",
A2: boost | B2: Boost Pokémon: wiki.pokealliance.com/guias/boost_stone A máquina de boost fica no meio do TC, do lado direito | C2: ",
A3: up | B3: Guia de up até o lvl 150: https://discord.com/channels/1159230367803392022/1308522087517782047 / Primeiros passos: wiki.pokealliance.com/guias/primeiros-passos | C3: ",
A4: fly | B4: Order no seu pé pra montar no fly. Subir e descer configura as hotkeys no Ctrl K -> Movements -> Fly Up e Fly Down. Se quiser tirar os botões que aparecem na tela, é em Config -> Game -> Show Fly Up/Down buttons | C4: ",
A5: ilhas laranja | B5: Ilhas laranja (lvl150+): Fala com o Captain Frederic, na praia sul de Cianwood, e depois pega a chave escondida atrás do coqueiro (imgur.com/a/uu36dVY), e entrega a chave para o capitão. Depois só voar pra ilha que precisa ir | C5: ",
A6: mapa | B6: Pra liberar o mapa completo: tinyurl.com/discord-pka-mapa Fecha o jogo, e importa o arquivo pelo launcher: imgur.com/a/FzbjhL0 | C6: ",
A7: ditto | B7: Pra fazer o shiny Ditto: wiki.pokealliance.com/quests/quests-principais#dr-oliveira-e-shiny-ditto O NPC Fica no lab de Pallet | C7: ",
A8: combo autocombo | B8: Autocombo: Botão direito nas skills -> Open Auto Combo. Arrasta a skills pra baixo na ordem que quiser. Fecha a interface, botão direito no terceiro botão da action bar (o monstrinho) e seta a hotkey. imgur.com/6xFdECI | C8: ",
A9: pesca | B9: Pra pescar, tem que procurar os fishing spots (uns peixes na água) direita ou sul de Saffron. Quando achar, aperta Ctrl Z e clica nele. Pescar só upa a skill de pesca, não da xp pro personagem, e nem vem muito shiny | C9: ",
A10: fundir | B10: Fundir helds: wiki.pokealliance.com/sistemas/helds#fusao-de-helds A máquina fica no meio do TC | C10: ",
A11: trocar | B11: Trocar tokens por helds: youtu.be/Bvq8_LrDuXo?t=50 | C11: ",
A12: cupom | B12: Cupons: Biskella, Anunaki, Bandicot, Lemes, Safnaw, Loxas, Lele, Emprego, Twooplayerss, Kaka, Lixito | C12: ",
... A100: ping | B100: Nâo tem como ver o ping dentro do jogo. O mais próximo é mandar um "ping pokealliance.com" no cmd | C100: ",
B101: 100k cargas premium upam 1 pokemon do lvl 0 até lvl 23 + 30% | C101: ",
A102: 150 | B102: Depois do lvl 150 vc upa em qualquer wildscape (hunt com caveira) que vc tenha pokes pra caçar: tinyurl.com/planilha-pka-hunts | C102: ",
A103: tubos | B103: Tubos (Hunt lvl 350+): imgur.com/a/wFcUcVR | C103: ",
A104: python | B104: Fiz um scriptzinho em python onde eu aperto um atalho, digito uma palavra chave da pergunta, e ele ja traz a mensagem pro meu Ctrl C | C104: ",
A105: qwilfish | B105: NPC pra trocar o item do Qwilfish pelo shiny: imgur.com/a/fmnPze7 | C105: ",
A106: reinicia reabre | B106: Reabre o client, e força atualização pelo launcher, clicando na engrenagem em cima/direita -> Verificar atualizações | C106: ",
A107: package | B107: Usa um Package Kit no item pra tirar ele da house. Compra por 1k na NPC July na entrada do TC -> | C107: ",
A108: quest | B108: Quests principais: wiki.pokealliance.com/quests/quests-principais | C108: ",
A109: wiki | B109: Wiki oficial do PKA: wiki.pokealliance.com | C109: ",
A110: outland | B110: .h outland north/east/south | C110: ",
A111: depot | B111: Depot stash no TC, uma caixa azul perto da televisão | C111: ",
A112: autoloot | B112: autoloot é só pra vip. Se não for, aperta espaço perto dos corpos pra lootear. E se quiser trocar a hotkey, Ctrl K -> Others -> Auto Loot | C112: ",
A113: tracker rastreador | B113: Tracker de Linked/Pokelog: Ctrl T -> Pokelog -> Open Tracker / Tracker de Brokes: Ctrl T -> Pokemon Brokes -> Open Tracker. Clica na mira do lado do pokemon pra adicionar ele no tracker | C113: ",
A114: revendedor | B114: Revendedor oficial do PKA: curse.com.br/pokealliance | C114: ",
... A122: dailyguild | B122: Daily guild são 42 tasks por semana (7 diárias + 35 tickets). Mais detalhes: https://discord.com/channels/1159230367803392022/1159230368940032093/1536193255350345848 | C122: ",
A123: surf | B123: pra surfar é só andar em direção à água, tendo um poke pra fora que tenha surf
A124: ability habilidade | B124: pra saber se o pokemon tem fly, surf, dig... olha na Pokedex -> Info -> Field Abilities
A125: comandos | B125: wiki.pokealliance.com/guias/comandos-disponiveis
A126: ticket | B126: Pra abrir ticket, pokealliance.com/ faz o login e clica em "Tickets"
A127: instancia canal | B127: Pra saber se um poke tem instância, procura a foto dele no Ctrl Tab. Geralmente ta em uma das hunts dele. Vai até lá, clica na porta pra escolher o canal. Caveira vermelha = wildscape(Lvl 150+). Brotinho = hunt normal
A128: topmenu | B128: Passa o mouse no meio da tela em cima que vai aparecer o botão pra abrir o menu
A129: help | B129: deixa o chat de Help só pra dúvidas sobre o jogo, por favor. Se for bug, abre um ticket no site. Sugestão manda no #sugestões no discord. Resto manda no GC
A130: mc | B130: pode abrir 2 clients, mas tem restrições. Da uma lida no chat #regras no Discord
A131: calendario | B131: calendário premium vc consegue resgatar os dias anteriores pagando 100 online points pra cada dia
A132: critico critical | B132: o efeito que aparece às vezes quando joga a ball é o critical catch. Naquela ball, a chance é dobrada
A133: technological | B133: revive normal só funciona até o lvl 219. Max revive funciona a partir do lvl 220. Technological revive é o único que funciona nas hunts de rotação (Lvl 350+)
A134: trade | B134: pra dar trade, ctrl click no item -> Trade With, e clica na pessoa
... A167: anuncio | B167: Fica expressamente proibido todo tipo de anúncio em qualquer Game-Chat (PT-BR, ESP, EN, PL), seja de Lives, Grupos de Whatsapp, comércio, formação de grupos, formação de Guild, etc. Recomendamos que utilizem o Trade Center do respectivo mundo.

Sheet Linked Tasks
A1: Qtd | B1: Pokemon | C1: Tipo de hunt | D1: Hunt | E1: Kills/h
A2: 30 | B2: Rattata | C2: Normal | D2: =IF(B2<>"", SWITCH(C2, "Wild", VLOOKUP(B2, 'Localizações'!$A$2:$D992, 2, FALSE), "Normal", VLOOKUP(B2, 'Localizações'!$A$2:$D992, 3, FALSE), "Hoenn", VLOOKUP(B2, 'Localizações'!$A$2:$D992, 4, FALSE), ""), "") -> https://imgur.com/a/ZyszZOZ | F2: Pra ver as tasks, aperta Ctrl L no jogo Completando uma task, libera a próxima Mais detalhes: https://discord.com/channels/1159230367803392022/1159230368940032093/1495879078094311494
A3: 30 | B3: Oddish | C3: Normal | D3: =IF(B3<>"", SWITCH(C3, "Wild", VLOOKUP(B3, 'Localizações'!$A$2:$D992, 2, FALSE), "Normal", VLOOKUP(B3, 'Localizações'!$A$2:$D992, 3, FALSE), "Hoenn", VLOOKUP(B3, 'Localizações'!$A$2:$D992, 4, FALSE), ""), "") -> https://imgur.com/a/2SuUURl
A4: 30 | B4: Geodude | C4: Normal | D4: =IF(B4<>"", SWITCH(C4, "Wild", VLOOKUP(B4, 'Localizações'!$A$2:$D992, 2, FALSE), "Normal", VLOOKUP(B4, 'Localizações'!$A$2:$D992, 3, FALSE), "Hoenn", VLOOKUP(B4, 'Localizações'!$A$2:$D992, 4, FALSE), ""), "") -> https://imgur.com/a/IhJ17iJ
A5: 60 | B5: Mankey | C5: Normal | D5: =IF(B5<>"", SWITCH(C5, "Wild", VLOOKUP(B5, 'Localizações'!$A$2:$D992, 2, FALSE), "Normal", VLOOKUP(B5, 'Localizações'!$A$2:$D992, 3, FALSE), "Hoenn", VLOOKUP(B5, 'Localizações'!$A$2:$D992, 4, FALSE), ""), "") -> https://imgur.com/a/4E7gOtq
A6: 60 | B6: Rhyhorn | C6: Normal | D6: =IF(B6<>"", SWITCH(C6, "Wild", VLOOKUP(B6, 'Localizações'!$A$2:$D992, 2, FALSE), "Normal", VLOOKUP(B6, 'Localizações'!$A$2:$D992, 3, FALSE), "Hoenn", VLOOKUP(B6, 'Localizações'!$A$2:$D992, 4, FALSE), ""), "") -> https://imgur.com/a/cPbYaoO
A7: 60 | B7: Gloom | C7: Normal | D7: =IF(B7<>"", SWITCH(C7, "Wild", VLOOKUP(B7, 'Localizações'!$A$2:$D992, 2, FALSE), "Normal", VLOOKUP(B7, 'Localizações'!$A$2:$D992, 3, FALSE), "Hoenn", VLOOKUP(B7, 'Localizações'!$A$2:$D992, 4, FALSE), ""), "") -> https://imgur.com/a/TaH2l6m
A8: 100 | B8: Graveler | C8: Normal | D8: =IF(B8<>"", SWITCH(C8, "Wild", VLOOKUP(B8, 'Localizações'!$A$2:$D992, 2, FALSE), "Normal", VLOOKUP(B8, 'Localizações'!$A$2:$D992, 3, FALSE), "Hoenn", VLOOKUP(B8, 'Localizações'!$A$2:$D992, 4, FALSE), ""), "") -> https://imgur.com/a/SHzJxH4
A9: 100 | B9: Golbat | C9: Normal | D9: =IF(B9<>"", SWITCH(C9, "Wild", VLOOKUP(B9, 'Localizações'!$A$2:$D992, 2, FALSE), "Normal", VLOOKUP(B9, 'Localizações'!$A$2:$D992, 3, FALSE), "Hoenn", VLOOKUP(B9, 'Localizações'!$A$2:$D992, 4, FALSE), ""), "") -> https://imgur.com/a/uvfPxaO
A10: 250 | B10: Tangela | C10: Normal | D10: =IF(B10<>"", SWITCH(C10, "Wild", VLOOKUP(B10, 'Localizações'!$A$2:$D992, 2, FALSE), "Normal", VLOOKUP(B10, 'Localizações'!$A$2:$D992, 3, FALSE), "Hoenn", VLOOKUP(B10, 'Localizações'!$A$2:$D992, 4, FALSE), ""), "") -> https://imgur.com/a/IZyOqys
A11: 250 | B11: Marowak | C11: Normal | D11: =IF(B11<>"", SWITCH(C11, "Wild", VLOOKUP(B11, 'Localizações'!$A$2:$D992, 2, FALSE), "Normal", VLOOKUP(B11, 'Localizações'!$A$2:$D992, 3, FALSE), "Hoenn", VLOOKUP(B11, 'Localizações'!$A$2:$D992, 4, FALSE), ""), "") -> https://imgur.com/a/VrqZwDG | E11: 2150
A12: 250 | B12: Electrode | C12: Normal | D12: =IF(B12<>"", SWITCH(C12, "Wild", VLOOKUP(B12, 'Localizações'!$A$2:$D992, 2, FALSE), "Normal", VLOOKUP(B12, 'Localizações'!$A$2:$D992, 3, FALSE), "Hoenn", VLOOKUP(B12, 'Localizações'!$A$2:$D992, 4, FALSE), ""), "") -> https://imgur.com/a/ZNQjOvj
A13: 400 | B13: Magneton | C13: Normal | D13: =IF(B13<>"", SWITCH(C13, "Wild", VLOOKUP(B13, 'Localizações'!$A$2:$D992, 2, FALSE), "Normal", VLOOKUP(B13, 'Localizações'!$A$2:$D992, 3, FALSE), "Hoenn", VLOOKUP(B13, 'Localizações'!$A$2:$D992, 4, FALSE), ""), "") -> https://imgur.com/a/ZNQjOvj
A14: 500 | B14: Fearow | C14: Normal | D14: =IF(B14<>"", SWITCH(C14, "Wild", VLOOKUP(B14, 'Localizações'!$A$2:$D992, 2, FALSE), "Normal", VLOOKUP(B14, 'Localizações'!$A$2:$D992, 3, FALSE), "Hoenn", VLOOKUP(B14, 'Localizações'!$A$2:$D992, 4, FALSE), ""), "") -> https://imgur.com/a/NVXqWOp
A15: 800 | B15: Venusaur | C15: Normal | D15: =IF(B15<>"", SWITCH(C15, "Wild", VLOOKUP(B15, 'Localizações'!$A$2:$D992, 2, FALSE), "Normal", VLOOKUP(B15, 'Localizações'!$A$2:$D992, 3, FALSE), "Hoenn", VLOOKUP(B15, 'Localizações'!$A$2:$D992, 4, FALSE), ""), "") -> https://imgur.com/a/zRcrSLP
A16: 800 | B16: Blastoise | C16: Normal | D16: =IF(B16<>"", SWITCH(C16, "Wild", VLOOKUP(B16, 'Localizações'!$A$2:$D992, 2, FALSE), "Normal", VLOOKUP(B16, 'Localizações'!$A$2:$D992, 3, FALSE), "Hoenn", VLOOKUP(B16, 'Localizações'!$A$2:$D992, 4, FALSE), ""), "") -> https://imgur.com/a/o6O5mnt | E16: 2900
A17: 800 | B17: Charizard | C17: Normal | D17: =IF(B17<>"", SWITCH(C17, "Wild", VLOOKUP(B17, 'Localizações'!$A$2:$D992, 2, FALSE), "Normal", VLOOKUP(B17, 'Localizações'!$A$2:$D992, 3, FALSE), "Hoenn", VLOOKUP(B17, 'Localizações'!$A$2:$D992, 4, FALSE), ""), "") -> https://imgur.com/a/ksXMwHN
A18: 10000 | B18: Ampharos | C18: Wild | D18: =IF(B18<>"", SWITCH(C18, "Wild", VLOOKUP(B18, 'Localizações'!$A$2:$D992, 2, FALSE), "Normal", VLOOKUP(B18, 'Localizações'!$A$2:$D992, 3, FALSE), "Hoenn", VLOOKUP(B18, 'Localizações'!$A$2:$D992, 4, FALSE), ""), "") -> https://imgur.com/a/O7GKc00 | E18: 3000
A19: 10000 | B19: Blastoise | C19: Wild | D19: =IF(B19<>"", SWITCH(C19, "Wild", VLOOKUP(B19, 'Localizações'!$A$2:$D992, 2, FALSE), "Normal", VLOOKUP(B19, 'Localizações'!$A$2:$D992, 3, FALSE), "Hoenn", VLOOKUP(B19, 'Localizações'!$A$2:$D992, 4, FALSE), ""), "") -> https://imgur.com/a/H98mIzg | E19: 2000
A20: 10000 | B20: Charizard | C20: Wild | D20: =IF(B20<>"", SWITCH(C20, "Wild", VLOOKUP(B20, 'Localizações'!$A$2:$D992, 2, FALSE), "Normal", VLOOKUP(B20, 'Localizações'!$A$2:$D992, 3, FALSE), "Hoenn", VLOOKUP(B20, 'Localizações'!$A$2:$D992, 4, FALSE), ""), "") -> https://imgur.com/a/thSWZiw | E20: 2500
A21: 10000 | B21: Dodrio | C21: Wild | D21: =IF(B21<>"", SWITCH(C21, "Wild", VLOOKUP(B21, 'Localizações'!$A$2:$D992, 2, FALSE), "Normal", VLOOKUP(B21, 'Localizações'!$A$2:$D992, 3, FALSE), "Hoenn", VLOOKUP(B21, 'Localizações'!$A$2:$D992, 4, FALSE), ""), "") -> https://imgur.com/a/mZdWvFw | E21: 2350
A22: 10000 | B22: Espeon | C22: Wild | D22: =IF(B22<>"", SWITCH(C22, "Wild", VLOOKUP(B22, 'Localizações'!$A$2:$D992, 2, FALSE), "Normal", VLOOKUP(B22, 'Localizações'!$A$2:$D992, 3, FALSE), "Hoenn", VLOOKUP(B22, 'Localizações'!$A$2:$D992, 4, FALSE), ""), "") -> https://imgur.com/a/CkBSqXN
A23: 10000 | B23: Farfetch'd | C23: Wild | D23: =IF(B23<>"", SWITCH(C23, "Wild", VLOOKUP(B23, 'Localizações'!$A$2:$D992, 2, FALSE), "Normal", VLOOKUP(B23, 'Localizações'!$A$2:$D992, 3, FALSE), "Hoenn", VLOOKUP(B23, 'Localizações'!$A$2:$D992, 4, FALSE), ""), "") -> https://imgur.com/a/mZdWvFw | E23: 2150
A24: 10000 | B24: Feraligatr | C24: Wild | D24: =IF(B24<>"", SWITCH(C24, "Wild", VLOOKUP(B24, 'Localizações'!$A$2:$D992, 2, FALSE), "Normal", VLOOKUP(B24, 'Localizações'!$A$2:$D992, 3, FALSE), "Hoenn", VLOOKUP(B24, 'Localizações'!$A$2:$D992, 4, FALSE), ""), "") -> https://imgur.com/a/H98mIzg | E24: 2700
A25: 10000 | B25: Flareon | C25: Wild | D25: =IF(B25<>"", SWITCH(C25, "Wild", VLOOKUP(B25, 'Localizações'!$A$2:$D992, 2, FALSE), "Normal", VLOOKUP(B25, 'Localizações'!$A$2:$D992, 3, FALSE), "Hoenn", VLOOKUP(B25, 'Localizações'!$A$2:$D992, 4, FALSE), ""), "") -> https://imgur.com/a/0QTUhoj | E25: 2500
A26: 10000 | B26: Golem | C26: Wild | D26: =IF(B26<>"", SWITCH(C26, "Wild", VLOOKUP(B26, 'Localizações'!$A$2:$D992, 2, FALSE), "Normal", VLOOKUP(B26, 'Localizações'!$A$2:$D992, 3, FALSE), "Hoenn", VLOOKUP(B26, 'Localizações'!$A$2:$D992, 4, FALSE), ""), "") -> https://imgur.com/a/rg5qYI4 | E26: 3150
A27: 10000 | B27: Hitmonchan | C27: Wild | D27: =IF(B27<>"", SWITCH(C27, "Wild", VLOOKUP(B27, 'Localizações'!$A$2:$D992, 2, FALSE), "Normal", VLOOKUP(B27, 'Localizações'!$A$2:$D992, 3, FALSE), "Hoenn", VLOOKUP(B27, 'Localizações'!$A$2:$D992, 4, FALSE), ""), "") -> https://imgur.com/a/pjIUv00
A28: 10000 | B28: Hitmonlee | C28: Wild | D28: =IF(B28<>"", SWITCH(C28, "Wild", VLOOKUP(B28, 'Localizações'!$A$2:$D992, 2, FALSE), "Normal", VLOOKUP(B28, 'Localizações'!$A$2:$D992, 3, FALSE), "Hoenn", VLOOKUP(B28, 'Localizações'!$A$2:$D992, 4, FALSE), ""), "") -> https://imgur.com/a/pjIUv00 | E28: 3300
A29: 10000 | B29: Hitmontop | C29: Wild | D29: =IF(B29<>"", SWITCH(C29, "Wild", VLOOKUP(B29, 'Localizações'!$A$2:$D992, 2, FALSE), "Normal", VLOOKUP(B29, 'Localizações'!$A$2:$D992, 3, FALSE), "Hoenn", VLOOKUP(B29, 'Localizações'!$A$2:$D992, 4, FALSE), ""), "") -> https://imgur.com/a/30cn4iq
A30: 10000 | B30: Jolteon | C30: Wild | D30: =IF(B30<>"", SWITCH(C30, "Wild", VLOOKUP(B30, 'Localizações'!$A$2:$D992, 2, FALSE), "Normal", VLOOKUP(B30, 'Localizações'!$A$2:$D992, 3, FALSE), "Hoenn", VLOOKUP(B30, 'Localizações'!$A$2:$D992, 4, FALSE), ""), "") -> https://imgur.com/a/clP3jSD
A31: 10000 | B31: Jynx | C31: Wild | D31: =IF(B31<>"", SWITCH(C31, "Wild", VLOOKUP(B31, 'Localizações'!$A$2:$D992, 2, FALSE), "Normal", VLOOKUP(B31, 'Localizações'!$A$2:$D992, 3, FALSE), "Hoenn", VLOOKUP(B31, 'Localizações'!$A$2:$D992, 4, FALSE), ""), "") -> https://imgur.com/a/3LppiO7 | E31: 3750
A32: 100 | B32: Kabutops | C32: Normal | D32: =IF(B32<>"", SWITCH(C32, "Wild", VLOOKUP(B32, 'Localizações'!$A$2:$D992, 2, FALSE), "Normal", VLOOKUP(B32, 'Localizações'!$A$2:$D992, 3, FALSE), "Hoenn", VLOOKUP(B32, 'Localizações'!$A$2:$D992, 4, FALSE), ""), "") -> https://imgur.com/a/hGRDfmM
A33: 10000 | B33: Lapras | C33: Wild | D33: =IF(B33<>"", SWITCH(C33, "Wild", VLOOKUP(B33, 'Localizações'!$A$2:$D992, 2, FALSE), "Normal", VLOOKUP(B33, 'Localizações'!$A$2:$D992, 3, FALSE), "Hoenn", VLOOKUP(B33, 'Localizações'!$A$2:$D992, 4, FALSE), ""), "") -> https://imgur.com/a/ca4NlMA
A34: 10000 | B34: Magcargo | C34: Wild | D34: =IF(B34<>"", SWITCH(C34, "Wild", VLOOKUP(B34, 'Localizações'!$A$2:$D992, 2, FALSE), "Normal", VLOOKUP(B34, 'Localizações'!$A$2:$D992, 3, FALSE), "Hoenn", VLOOKUP(B34, 'Localizações'!$A$2:$D992, 4, FALSE), ""), "") -> https://imgur.com/a/PjJgh5m
A35: 10000 | B35: Mantine | C35: Wild | D35: =IF(B35<>"", SWITCH(C35, "Wild", VLOOKUP(B35, 'Localizações'!$A$2:$D992, 2, FALSE), "Normal", VLOOKUP(B35, 'Localizações'!$A$2:$D992, 3, FALSE), "Hoenn", VLOOKUP(B35, 'Localizações'!$A$2:$D992, 4, FALSE), ""), "") -> https://imgur.com/a/H98mIzg | E35: 2750
A36: 10000 | B36: Marowak | C36: Wild | D36: =IF(B36<>"", SWITCH(C36, "Wild", VLOOKUP(B36, 'Localizações'!$A$2:$D992, 2, FALSE), "Normal", VLOOKUP(B36, 'Localizações'!$A$2:$D992, 3, FALSE), "Hoenn", VLOOKUP(B36, 'Localizações'!$A$2:$D992, 4, FALSE), ""), "") -> https://imgur.com/a/AYaHOY2
A37: 10000 | B37: Meganium | C37: Wild | D37: =IF(B37<>"", SWITCH(C37, "Wild", VLOOKUP(B37, 'Localizações'!$A$2:$D992, 2, FALSE), "Normal", VLOOKUP(B37, 'Localizações'!$A$2:$D992, 3, FALSE), "Hoenn", VLOOKUP(B37, 'Localizações'!$A$2:$D992, 4, FALSE), ""), "") -> https://imgur.com/uw0XICj | E37: 2100
A38: 10000 | B38: Miltank | C38: Wild | D38: =IF(B38<>"", SWITCH(C38, "Wild", VLOOKUP(B38, 'Localizações'!$A$2:$D992, 2, FALSE), "Normal", VLOOKUP(B38, 'Localizações'!$A$2:$D992, 3, FALSE), "Hoenn", VLOOKUP(B38, 'Localizações'!$A$2:$D992, 4, FALSE), ""), "") -> https://imgur.com/a/doQnA6i
A39: 10000 | B39: Muk | C39: Wild | D39: =IF(B39<>"", SWITCH(C39, "Wild", VLOOKUP(B39, 'Localizações'!$A$2:$D992, 2, FALSE), "Normal", VLOOKUP(B39, 'Localizações'!$A$2:$D992, 3, FALSE), "Hoenn", VLOOKUP(B39, 'Localizações'!$A$2:$D992, 4, FALSE), ""), "") -> https://imgur.com/a/vgGrrfT | E39: 2400
A40: 10000 | B40: Nidoking | C40: Wild | D40: =IF(B40<>"", SWITCH(C40, "Wild", VLOOKUP(B40, 'Localizações'!$A$2:$D992, 2, FALSE), "Normal", VLOOKUP(B40, 'Localizações'!$A$2:$D992, 3, FALSE), "Hoenn", VLOOKUP(B40, 'Localizações'!$A$2:$D992, 4, FALSE), ""), "") -> https://imgur.com/a/HWxtEs3 | E40: 2300
A41: 10000 | B41: Nidoqueen | C41: Wild | D41: =IF(B41<>"", SWITCH(C41, "Wild", VLOOKUP(B41, 'Localizações'!$A$2:$D992, 2, FALSE), "Normal", VLOOKUP(B41, 'Localizações'!$A$2:$D992, 3, FALSE), "Hoenn", VLOOKUP(B41, 'Localizações'!$A$2:$D992, 4, FALSE), ""), "") -> https://imgur.com/a/lnONjUq
A42: 10000 | B42: Ninetales | C42: Wild | D42: =IF(B42<>"", SWITCH(C42, "Wild", VLOOKUP(B42, 'Localizações'!$A$2:$D992, 2, FALSE), "Normal", VLOOKUP(B42, 'Localizações'!$A$2:$D992, 3, FALSE), "Hoenn", VLOOKUP(B42, 'Localizações'!$A$2:$D992, 4, FALSE), ""), "") -> https://imgur.com/a/2uMZqFZ | E42: 3000
A43: 100 | B43: Omastar | C43: Normal | D43: =IF(B43<>"", SWITCH(C43, "Wild", VLOOKUP(B43, 'Localizações'!$A$2:$D992, 2, FALSE), "Normal", VLOOKUP(B43, 'Localizações'!$A$2:$D992, 3, FALSE), "Hoenn", VLOOKUP(B43, 'Localizações'!$A$2:$D992, 4, FALSE), ""), "") -> https://imgur.com/a/lrEa6jJ
A44: 10000 | B44: Pidgeot | C44: Wild | D44: =IF(B44<>"", SWITCH(C44, "Wild", VLOOKUP(B44, 'Localizações'!$A$2:$D992, 2, FALSE), "Normal", VLOOKUP(B44, 'Localizações'!$A$2:$D992, 3, FALSE), "Hoenn", VLOOKUP(B44, 'Localizações'!$A$2:$D992, 4, FALSE), ""), "") -> https://imgur.com/a/mZdWvFw
A45: 10000 | B45: Politoed | C45: Wild | D45: =IF(B45<>"", SWITCH(C45, "Wild", VLOOKUP(B45, 'Localizações'!$A$2:$D992, 2, FALSE), "Normal", VLOOKUP(B45, 'Localizações'!$A$2:$D992, 3, FALSE), "Hoenn", VLOOKUP(B45, 'Localizações'!$A$2:$D992, 4, FALSE), ""), "") -> https://imgur.com/a/zMl0ekj | E45: 3220
A46: 10000 | B46: Poliwrath | C46: Wild | D46: =IF(B46<>"", SWITCH(C46, "Wild", VLOOKUP(B46, 'Localizações'!$A$2:$D992, 2, FALSE), "Normal", VLOOKUP(B46, 'Localizações'!$A$2:$D992, 3, FALSE), "Hoenn", VLOOKUP(B46, 'Localizações'!$A$2:$D992, 4, FALSE), ""), "") -> https://imgur.com/a/c9ewG6a
A47: 10000 | B47: Raichu | C47: Wild | D47: =IF(B47<>"", SWITCH(C47, "Wild", VLOOKUP(B47, 'Localizações'!$A$2:$D992, 2, FALSE), "Normal", VLOOKUP(B47, 'Localizações'!$A$2:$D992, 3, FALSE), "Hoenn", VLOOKUP(B47, 'Localizações'!$A$2:$D992, 4, FALSE), ""), "") -> https://imgur.com/a/clP3jSD
A48: 10000 | B48: Rapidash | C48: Wild | D48: =IF(B48<>"", SWITCH(C48, "Wild", VLOOKUP(B48, 'Localizações'!$A$2:$D992, 2, FALSE), "Normal", VLOOKUP(B48, 'Localizações'!$A$2:$D992, 3, FALSE), "Hoenn", VLOOKUP(B48, 'Localizações'!$A$2:$D992, 4, FALSE), ""), "") -> https://imgur.com/a/lwqRvJB
A49: 10000 | B49: Slowking | C49: Wild | D49: =IF(B49<>"", SWITCH(C49, "Wild", VLOOKUP(B49, 'Localizações'!$A$2:$D992, 2, FALSE), "Normal", VLOOKUP(B49, 'Localizações'!$A$2:$D992, 3, FALSE), "Hoenn", VLOOKUP(B49, 'Localizações'!$A$2:$D992, 4, FALSE), ""), "") -> https://imgur.com/a/XUZFbv9 | E49: 3500
A50: 10000 | B50: Steelix | C50: Wild | D50: =IF(B50<>"", SWITCH(C50, "Wild", VLOOKUP(B50, 'Localizações'!$A$2:$D992, 2, FALSE), "Normal", VLOOKUP(B50, 'Localizações'!$A$2:$D992, 3, FALSE), "Hoenn", VLOOKUP(B50, 'Localizações'!$A$2:$D992, 4, FALSE), ""), "") -> https://imgur.com/a/GWp5vC7 | E50: 2300
A51: 10000 | B51: Tentacruel | C51: Wild | D51: =IF(B51<>"", SWITCH(C51, "Wild", VLOOKUP(B51, 'Localizações'!$A$2:$D992, 2, FALSE), "Normal", VLOOKUP(B51, 'Localizações'!$A$2:$D992, 3, FALSE), "Hoenn", VLOOKUP(B51, 'Localizações'!$A$2:$D992, 4, FALSE), ""), "") -> https://imgur.com/a/1MIh0TT | E51: 1800
A52: 10000 | B52: Typhlosion | C52: Wild | D52: =IF(B52<>"", SWITCH(C52, "Wild", VLOOKUP(B52, 'Localizações'!$A$2:$D992, 2, FALSE), "Normal", VLOOKUP(B52, 'Localizações'!$A$2:$D992, 3, FALSE), "Hoenn", VLOOKUP(B52, 'Localizações'!$A$2:$D992, 4, FALSE), ""), "") -> https://imgur.com/a/nmnNuO5
A53: 10000 | B53: Umbreon | C53: Wild | D53: =IF(B53<>"", SWITCH(C53, "Wild", VLOOKUP(B53, 'Localizações'!$A$2:$D992, 2, FALSE), "Normal", VLOOKUP(B53, 'Localizações'!$A$2:$D992, 3, FALSE), "Hoenn", VLOOKUP(B53, 'Localizações'!$A$2:$D992, 4, FALSE), ""), "") -> https://imgur.com/a/CkBSqXN
A54: 10000 | B54: Ursaring | C54: Wild | D54: =IF(B54<>"", SWITCH(C54, "Wild", VLOOKUP(B54, 'Localizações'!$A$2:$D992, 2, FALSE), "Normal", VLOOKUP(B54, 'Localizações'!$A$2:$D992, 3, FALSE), "Hoenn", VLOOKUP(B54, 'Localizações'!$A$2:$D992, 4, FALSE), ""), "") -> https://imgur.com/a/nBXkwSw | E54: 2300
A55: 10000 | B55: Vaporeon | C55: Wild | D55: =IF(B55<>"", SWITCH(C55, "Wild", VLOOKUP(B55, 'Localizações'!$A$2:$D992, 2, FALSE), "Normal", VLOOKUP(B55, 'Localizações'!$A$2:$D992, 3, FALSE), "Hoenn", VLOOKUP(B55, 'Localizações'!$A$2:$D992, 4, FALSE), ""), "") -> https://imgur.com/a/RI7U1mv
A56: 10000 | B56: Venusaur | C56: Wild | D56: =IF(B56<>"", SWITCH(C56, "Wild", VLOOKUP(B56, 'Localizações'!$A$2:$D992, 2, FALSE), "Normal", VLOOKUP(B56, 'Localizações'!$A$2:$D992, 3, FALSE), "Hoenn", VLOOKUP(B56, 'Localizações'!$A$2:$D992, 4, FALSE), ""), "") -> https://imgur.com/a/QZY9tMI | E56: 2600
A57: 10000 | B57: Misdreavus | C57: Wild | D57: =IF(B57<>"", SWITCH(C57, "Wild", VLOOKUP(B57, 'Localizações'!$A$2:$D992, 2, FALSE), "Normal", VLOOKUP(B57, 'Localizações'!$A$2:$D992, 3, FALSE), "Hoenn", VLOOKUP(B57, 'Localizações'!$A$2:$D992, 4, FALSE), ""), "") -> https://imgur.com/a/xfYPzTw
A58: 10000 | B58: Mr. Mime | C58: Wild | D58: =IF(B58<>"", SWITCH(C58, "Wild", VLOOKUP(B58, 'Localizações'!$A$2:$D992, 2, FALSE), "Normal", VLOOKUP(B58, 'Localizações'!$A$2:$D992, 3, FALSE), "Hoenn", VLOOKUP(B58, 'Localizações'!$A$2:$D992, 4, FALSE), ""), "") -> https://imgur.com/a/bIuz6Tm
A59: 10000 | B59: Pinsir | C59: Wild | D59: =IF(B59<>"", SWITCH(C59, "Wild", VLOOKUP(B59, 'Localizações'!$A$2:$D992, 2, FALSE), "Normal", VLOOKUP(B59, 'Localizações'!$A$2:$D992, 3, FALSE), "Hoenn", VLOOKUP(B59, 'Localizações'!$A$2:$D992, 4, FALSE), ""), "") -> https://imgur.com/a/T3rOBjE
A60: 10000 | B60: Pupitar | C60: Wild | D60: =IF(B60<>"", SWITCH(C60, "Wild", VLOOKUP(B60, 'Localizações'!$A$2:$D992, 2, FALSE), "Normal", VLOOKUP(B60, 'Localizações'!$A$2:$D992, 3, FALSE), "Hoenn", VLOOKUP(B60, 'Localizações'!$A$2:$D992, 4, FALSE), ""), "") -> https://imgur.com/a/SJntAUa
A61: 10000 | B61: Scyther | C61: Wild | D61: =IF(B61<>"", SWITCH(C61, "Wild", VLOOKUP(B61, 'Localizações'!$A$2:$D992, 2, FALSE), "Normal", VLOOKUP(B61, 'Localizações'!$A$2:$D992, 3, FALSE), "Hoenn", VLOOKUP(B61, 'Localizações'!$A$2:$D992, 4, FALSE), ""), "") -> https://imgur.com/a/df36NrE
A62: 10000 | B62: Skarmory | C62: Wild | D62: =IF(B62<>"", SWITCH(C62, "Wild", VLOOKUP(B62, 'Localizações'!$A$2:$D992, 2, FALSE), "Normal", VLOOKUP(B62, 'Localizações'!$A$2:$D992, 3, FALSE), "Hoenn", VLOOKUP(B62, 'Localizações'!$A$2:$D992, 4, FALSE), ""), "") -> https://imgur.com/a/otQbKEE
A63: 10000 | B63: Tauros | C63: Wild | D63: =IF(B63<>"", SWITCH(C63, "Wild", VLOOKUP(B63, 'Localizações'!$A$2:$D992, 2, FALSE), "Normal", VLOOKUP(B63, 'Localizações'!$A$2:$D992, 3, FALSE), "Hoenn", VLOOKUP(B63, 'Localizações'!$A$2:$D992, 4, FALSE), ""), "") -> https://imgur.com/a/j21SPSA
A64: 10000 | B64: Houndoom | C64: Wild | D64: =IF(B64<>"", SWITCH(C64, "Wild", VLOOKUP(B64, 'Localizações'!$A$2:$D992, 2, FALSE), "Normal", VLOOKUP(B64, 'Localizações'!$A$2:$D992, 3, FALSE), "Hoenn", VLOOKUP(B64, 'Localizações'!$A$2:$D992, 4, FALSE), ""), "") -> https://imgur.com/a/kUQvKbL
A65: 10000 | B65: Kangaskhan | C65: Wild | D65: =IF(B65<>"", SWITCH(C65, "Wild", VLOOKUP(B65, 'Localizações'!$A$2:$D992, 2, FALSE), "Normal", VLOOKUP(B65, 'Localizações'!$A$2:$D992, 3, FALSE), "Hoenn", VLOOKUP(B65, 'Localizações'!$A$2:$D992, 4, FALSE), ""), "") -> https://imgur.com/a/j21SPSA
A66: 10000 | B66: Kingdra | C66: Wild | D66: =IF(B66<>"", SWITCH(C66, "Wild", VLOOKUP(B66, 'Localizações'!$A$2:$D992, 2, FALSE), "Normal", VLOOKUP(B66, 'Localizações'!$A$2:$D992, 3, FALSE), "Hoenn", VLOOKUP(B66, 'Localizações'!$A$2:$D992, 4, FALSE), ""), "") -> https://imgur.com/a/W6HZl3X
A67: 10000 | B67: Machamp | C67: Wild | D67: =IF(B67<>"", SWITCH(C67, "Wild", VLOOKUP(B67, 'Localizações'!$A$2:$D992, 2, FALSE), "Normal", VLOOKUP(B67, 'Localizações'!$A$2:$D992, 3, FALSE), "Hoenn", VLOOKUP(B67, 'Localizações'!$A$2:$D992, 4, FALSE), ""), "") -> https://imgur.com/a/yB63tms
A68: 10000 | B68: Wobbuffet | C68: Wild | D68: =IF(B68<>"", SWITCH(C68, "Wild", VLOOKUP(B68, 'Localizações'!$A$2:$D992, 2, FALSE), "Normal", VLOOKUP(B68, 'Localizações'!$A$2:$D992, 3, FALSE), "Hoenn", VLOOKUP(B68, 'Localizações'!$A$2:$D992, 4, FALSE), ""), "") -> https://imgur.com/a/ZlGOsvk | E68: 3700
A69: 10000 | B69: Dusknoir | C69: Wild | D69: =IF(B69<>"", SWITCH(C69, "Wild", VLOOKUP(B69, 'Localizações'!$A$2:$D992, 2, FALSE), "Normal", VLOOKUP(B69, 'Localizações'!$A$2:$D992, 3, FALSE), "Hoenn", VLOOKUP(B69, 'Localizações'!$A$2:$D992, 4, FALSE), ""), "") -> https://imgur.com/a/DMCBxm0 | E69: 2300
A70: 10000 | B70: Luxray | C70: Wild | D70: =IF(B70<>"", SWITCH(C70, "Wild", VLOOKUP(B70, 'Localizações'!$A$2:$D992, 2, FALSE), "Normal", VLOOKUP(B70, 'Localizações'!$A$2:$D992, 3, FALSE), "Hoenn", VLOOKUP(B70, 'Localizações'!$A$2:$D992, 4, FALSE), ""), "") -> https://imgur.com/a/L0bj8Vd | E70: 2100
A71: 10000 | B71: Mimikyu | C71: Wild | D71: =IF(B71<>"", SWITCH(C71, "Wild", VLOOKUP(B71, 'Localizações'!$A$2:$D992, 2, FALSE), "Normal", VLOOKUP(B71, 'Localizações'!$A$2:$D992, 3, FALSE), "Hoenn", VLOOKUP(B71, 'Localizações'!$A$2:$D992, 4, FALSE), ""), "") -> https://imgur.com/a/tBNDQGq | E71: 2400
A72: 10000 | B72: Toxicroak | C72: Wild | D72: =IF(B72<>"", SWITCH(C72, "Wild", VLOOKUP(B72, 'Localizações'!$A$2:$D992, 2, FALSE), "Normal", VLOOKUP(B72, 'Localizações'!$A$2:$D992, 3, FALSE), "Hoenn", VLOOKUP(B72, 'Localizações'!$A$2:$D992, 4, FALSE), ""), "") -> https://imgur.com/a/voSoRee | E72: 2900
A73: 10000 | B73: Torterra | C73: Wild | D73: =IF(B73<>"", SWITCH(C73, "Wild", VLOOKUP(B73, 'Localizações'!$A$2:$D992, 2, FALSE), "Normal", VLOOKUP(B73, 'Localizações'!$A$2:$D992, 3, FALSE), "Hoenn", VLOOKUP(B73, 'Localizações'!$A$2:$D992, 4, FALSE), ""), "") -> https://imgur.com/a/OSpmhX3 | E73: 2600
A74: 10000 | B74: Tangrowth | C74: Wild | D74: =IF(B74<>"", SWITCH(C74, "Wild", VLOOKUP(B74, 'Localizações'!$A$2:$D992, 2, FALSE), "Normal", VLOOKUP(B74, 'Localizações'!$A$2:$D992, 3, FALSE), "Hoenn", VLOOKUP(B74, 'Localizações'!$A$2:$D992, 4, FALSE), ""), "") -> https://imgur.com/a/6PD5gEv | E74: 2800
A75: 10000 | B75: Arcanine | C75: Wild | D75: =IF(B75<>"", SWITCH(C75, "Wild", VLOOKUP(B75, 'Localizações'!$A$2:$D992, 2, FALSE), "Normal", VLOOKUP(B75, 'Localizações'!$A$2:$D992, 3, FALSE), "Hoenn", VLOOKUP(B75, 'Localizações'!$A$2:$D992, 4, FALSE), ""), "") -> https://imgur.com/a/NnkwV5t | E75: 2800
A76: 10000 | B76: Florges | C76: Wild | D76: =IF(B76<>"", SWITCH(C76, "Wild", VLOOKUP(B76, 'Localizações'!$A$2:$D992, 2, FALSE), "Normal", VLOOKUP(B76, 'Localizações'!$A$2:$D992, 3, FALSE), "Hoenn", VLOOKUP(B76, 'Localizações'!$A$2:$D992, 4, FALSE), ""), "") -> https://imgur.com/a/dHnsWqn | E76: 3400
A77: 10000 | B77: Hydreigon | C77: Wild | D77: =IF(B77<>"", SWITCH(C77, "Wild", VLOOKUP(B77, 'Localizações'!$A$2:$D992, 2, FALSE), "Normal", VLOOKUP(B77, 'Localizações'!$A$2:$D992, 3, FALSE), "Hoenn", VLOOKUP(B77, 'Localizações'!$A$2:$D992, 4, FALSE), ""), "") -> https://imgur.com/a/tkRwGdL | E77: 2600
A78: 4000 | B78: Walrein | C78: Hoenn | D78: =IF(B78<>"", SWITCH(C78, "Wild", VLOOKUP(B78, 'Localizações'!$A$2:$D992, 2, FALSE), "Normal", VLOOKUP(B78, 'Localizações'!$A$2:$D992, 3, FALSE), "Hoenn", VLOOKUP(B78, 'Localizações'!$A$2:$D992, 4, FALSE), ""), "") -> https://imgur.com/a/MtwwL6b | E78: 1120
A79: 4000 | B79: Seviper | C79: Hoenn | D79: =IF(B79<>"", SWITCH(C79, "Wild", VLOOKUP(B79, 'Localizações'!$A$2:$D992, 2, FALSE), "Normal", VLOOKUP(B79, 'Localizações'!$A$2:$D992, 3, FALSE), "Hoenn", VLOOKUP(B79, 'Localizações'!$A$2:$D992, 4, FALSE), ""), "") -> https://imgur.com/a/l3lliRe | E79: 1120
A80: 4000 | B80: Aggron | C80: Hoenn | D80: =IF(B80<>"", SWITCH(C80, "Wild", VLOOKUP(B80, 'Localizações'!$A$2:$D992, 2, FALSE), "Normal", VLOOKUP(B80, 'Localizações'!$A$2:$D992, 3, FALSE), "Hoenn", VLOOKUP(B80, 'Localizações'!$A$2:$D992, 4, FALSE), ""), "") -> https://imgur.com/a/cJndpSb | E80: 1120
A81: 4000 | B81: Sharpedo | C81: Hoenn | D81: =IF(B81<>"", SWITCH(C81, "Wild", VLOOKUP(B81, 'Localizações'!$A$2:$D992, 2, FALSE), "Normal", VLOOKUP(B81, 'Localizações'!$A$2:$D992, 3, FALSE), "Hoenn", VLOOKUP(B81, 'Localizações'!$A$2:$D992, 4, FALSE), ""), "") -> https://imgur.com/a/xEQLyNo | E81: 1400
A82: 4000 | B82: Armaldo | C82: Hoenn | D82: =IF(B82<>"", SWITCH(C82, "Wild", VLOOKUP(B82, 'Localizações'!$A$2:$D992, 2, FALSE), "Normal", VLOOKUP(B82, 'Localizações'!$A$2:$D992, 3, FALSE), "Hoenn", VLOOKUP(B82, 'Localizações'!$A$2:$D992, 4, FALSE), ""), "") -> https://imgur.com/a/xG6MiHI | E82: 1400
A83: 4000 | B83: Altaria | C83: Hoenn | D83: =IF(B83<>"", SWITCH(C83, "Wild", VLOOKUP(B83, 'Localizações'!$A$2:$D992, 2, FALSE), "Normal", VLOOKUP(B83, 'Localizações'!$A$2:$D992, 3, FALSE), "Hoenn", VLOOKUP(B83, 'Localizações'!$A$2:$D992, 4, FALSE), ""), "") -> https://imgur.com/a/4BU3DIw | E83: 1200
A84: 4000 | B84: Swellow | C84: Hoenn | D84: =IF(B84<>"", SWITCH(C84, "Wild", VLOOKUP(B84, 'Localizações'!$A$2:$D992, 2, FALSE), "Normal", VLOOKUP(B84, 'Localizações'!$A$2:$D992, 3, FALSE), "Hoenn", VLOOKUP(B84, 'Localizações'!$A$2:$D992, 4, FALSE), ""), "") -> https://imgur.com/a/zWjp1is | E84: 1300
A85: 4000 | B85: Huntail | C85: Hoenn | D85: =IF(B85<>"", SWITCH(C85, "Wild", VLOOKUP(B85, 'Localizações'!$A$2:$D992, 2, FALSE), "Normal", VLOOKUP(B85, 'Localizações'!$A$2:$D992, 3, FALSE), "Hoenn", VLOOKUP(B85, 'Localizações'!$A$2:$D992, 4, FALSE), ""), "") -> https://imgur.com/a/xi7IxsL | E85: 1400
A86: 4000 | B86: Breloom | C86: Hoenn | D86: =IF(B86<>"", SWITCH(C86, "Wild", VLOOKUP(B86, 'Localizações'!$A$2:$D992, 2, FALSE), "Normal", VLOOKUP(B86, 'Localizações'!$A$2:$D992, 3, FALSE), "Hoenn", VLOOKUP(B86, 'Localizações'!$A$2:$D992, 4, FALSE), ""), "") -> https://imgur.com/a/xkbItkt | E86: 1140
A87: 4000 | B87: Claydol | C87: Hoenn | D87: =IF(B87<>"", SWITCH(C87, "Wild", VLOOKUP(B87, 'Localizações'!$A$2:$D992, 2, FALSE), "Normal", VLOOKUP(B87, 'Localizações'!$A$2:$D992, 3, FALSE), "Hoenn", VLOOKUP(B87, 'Localizações'!$A$2:$D992, 4, FALSE), ""), "") -> https://imgur.com/a/FaZB45d | E87: 1400
A88: 4000 | B88: Hariyama | C88: Hoenn | D88: =IF(B88<>"", SWITCH(C88, "Wild", VLOOKUP(B88, 'Localizações'!$A$2:$D992, 2, FALSE), "Normal", VLOOKUP(B88, 'Localizações'!$A$2:$D992, 3, FALSE), "Hoenn", VLOOKUP(B88, 'Localizações'!$A$2:$D992, 4, FALSE), ""), "") -> https://imgur.com/a/ywTJuVx | E88: 1100
A89: 4000 | B89: Cradily | C89: Hoenn | D89: =IF(B89<>"", SWITCH(C89, "Wild", VLOOKUP(B89, 'Localizações'!$A$2:$D992, 2, FALSE), "Normal", VLOOKUP(B89, 'Localizações'!$A$2:$D992, 3, FALSE), "Hoenn", VLOOKUP(B89, 'Localizações'!$A$2:$D992, 4, FALSE), ""), "") -> https://imgur.com/a/zziX3N4 | E89: 1050
A90: 4000 | B90: Roselia | C90: Hoenn | D90: =IF(B90<>"", SWITCH(C90, "Wild", VLOOKUP(B90, 'Localizações'!$A$2:$D992, 2, FALSE), "Normal", VLOOKUP(B90, 'Localizações'!$A$2:$D992, 3, FALSE), "Hoenn", VLOOKUP(B90, 'Localizações'!$A$2:$D992, 4, FALSE), ""), "") -> https://imgur.com/a/Dv4T5af | E90: 1600
A91: 4000 | B91: Pelipper | C91: Hoenn | D91: =IF(B91<>"", SWITCH(C91, "Wild", VLOOKUP(B91, 'Localizações'!$A$2:$D992, 2, FALSE), "Normal", VLOOKUP(B91, 'Localizações'!$A$2:$D992, 3, FALSE), "Hoenn", VLOOKUP(B91, 'Localizações'!$A$2:$D992, 4, FALSE), ""), "") -> https://imgur.com/a/9ny4RTg | E91: 1170
A92: 4000 | B92: Dustox | C92: Hoenn | D92: =IF(B92<>"", SWITCH(C92, "Wild", VLOOKUP(B92, 'Localizações'!$A$2:$D992, 2, FALSE), "Normal", VLOOKUP(B92, 'Localizações'!$A$2:$D992, 3, FALSE), "Hoenn", VLOOKUP(B92, 'Localizações'!$A$2:$D992, 4, FALSE), ""), "") -> https://imgur.com/a/aa8JVeg | E92: 1250
A93: 4000 | B93: Solrock | C93: Hoenn | D93: =IF(B93<>"", SWITCH(C93, "Wild", VLOOKUP(B93, 'Localizações'!$A$2:$D992, 2, FALSE), "Normal", VLOOKUP(B93, 'Localizações'!$A$2:$D992, 3, FALSE), "Hoenn", VLOOKUP(B93, 'Localizações'!$A$2:$D992, 4, FALSE), ""), "") -> https://imgur.com/a/eWSLlta | E93: 1500
A94: =IF(B94<>"", SWITCH(C94, "Wild", 10000, "Normal", "?", "Hoenn", 4000, ""), "") -> 4000 | B94: Clamperl | C94: Hoenn | D94: =IF(B94<>"", SWITCH(C94, "Wild", VLOOKUP(B94, 'Localizações'!$A$2:$D992, 2, FALSE), "Normal", VLOOKUP(B94, 'Localizações'!$A$2:$D992, 3, FALSE), "Hoenn", VLOOKUP(B94, 'Localizações'!$A$2:$D992, 4, FALSE), ""), "") -> https://imgur.com/a/3by4nDT | E94: 1350
A95: =IF(B95<>"", SWITCH(C95, "Wild", 10000, "Normal", "?", "Hoenn", 4000, ""), "") -> 4000 | B95: Banette | C95: Hoenn | D95: =IF(B95<>"", SWITCH(C95, "Wild", VLOOKUP(B95, 'Localizações'!$A$2:$D992, 2, FALSE), "Normal", VLOOKUP(B95, 'Localizações'!$A$2:$D992, 3, FALSE), "Hoenn", VLOOKUP(B95, 'Localizações'!$A$2:$D992, 4, FALSE), ""), "") -> https://imgur.com/a/JL6EoDR | E95: 900
A96: =IF(B96<>"", SWITCH(C96, "Wild", 10000, "Normal", "?", "Hoenn", 4000, ""), "") -> 4000 | B96: Camerupt | C96: Hoenn | D96: =IF(B96<>"", SWITCH(C96, "Wild", VLOOKUP(B96, 'Localizações'!$A$2:$D992, 2, FALSE), "Normal", VLOOKUP(B96, 'Localizações'!$A$2:$D992, 3, FALSE), "Hoenn", VLOOKUP(B96, 'Localizações'!$A$2:$D992, 4, FALSE), ""), "") -> https://imgur.com/a/a8pfzjH | E96: 1250
A97: 4000 | B97: Castform Fire | C97: Hoenn | D97: https://imgur.com/a/Ts9I3R9 | E97: 1150
A98: =IF(B98<>"", SWITCH(C98, "Wild", 10000, "Normal", "?", "Hoenn", 4000, ""), "") -> 4000 | B98: Castform Ice | C98: Hoenn | D98: https://imgur.com/a/Ts9I3R9 | E98: 1300
A99: =IF(B99<>"", SWITCH(C99, "Wild", 10000, "Normal", "?", "Hoenn", 4000, ""), "") -> 4000 | B99: Castform Electric | C99: Hoenn | D99: https://imgur.com/a/Ts9I3R9 | E99: 1090
A100: =IF(B100<>"", SWITCH(C100, "Wild", 10000, "Normal", "?", "Hoenn", 4000, ""), "") -> 4000 | B100: Kecleon | C100: Hoenn | D100: =IF(B100<>"", SWITCH(C100, "Wild", VLOOKUP(B100, 'Localizações'!$A$2:$D992, 2, FALSE), "Normal", VLOOKUP(B100, 'Localizações'!$A$2:$D992, 3, FALSE), "Hoenn", VLOOKUP(B100, 'Localizações'!$A$2:$D992, 4, FALSE), ""), "") -> https://imgur.com/a/8sxx7sN | E100: 1070
...

Sheet Localizações
A1: =IFERROR(__xludf.DUMMYFUNCTION("IMPORTRANGE(""https://docs.google.com/spreadsheets/d/1ID3qu1P4Zey82OSLntg4O0xoZlY1hGK58tte0D_Cv_s/edit?pli=1&gid=305783725#gid=305783725"",""Locations!A1:D1002"")"),"Pokémon") -> Pokémon | B1: =IFERROR(__xludf.DUMMYFUNCTION("""COMPUTED_VALUE"""),"Wildscape (Lvl 150+)") -> Wildscape (Lvl 150+) | C1: =IFERROR(__xludf.DUMMYFUNCTION("""COMPUTED_VALUE"""),"Normal") -> Normal | D1: =IFERROR(__xludf.DUMMYFUNCTION("""COMPUTED_VALUE"""),"Hoenn (Lvl 250+)") -> Hoenn (Lvl 250+)
A2: =IFERROR(__xludf.DUMMYFUNCTION("""COMPUTED_VALUE"""),"Bulbasaur") -> Bulbasaur | B2: =IFERROR(__xludf.DUMMYFUNCTION("""COMPUTED_VALUE"""),"-") -> - | C2: =IFERROR(__xludf.DUMMYFUNCTION("""COMPUTED_VALUE"""),"https://imgur.com/a/jcpzOgr") -> https://imgur.com/a/jcpzOgr | D2: =IFERROR(__xludf.DUMMYFUNCTION("""COMPUTED_VALUE"""),"-") -> - | E2: Como usar - Aperte Ctrl+F - Pesquise o nome do Pokémon que quer caçar Ilhas Laranja: https://imgur.com/a/FV42d75 Hoenn: https://imgur.com/a/Uwf1wBW
A3: =IFERROR(__xludf.DUMMYFUNCTION("""COMPUTED_VALUE"""),"Ivysaur") -> Ivysaur | B3: =IFERROR(__xludf.DUMMYFUNCTION("""COMPUTED_VALUE"""),"-") -> - | C3: =IFERROR(__xludf.DUMMYFUNCTION("""COMPUTED_VALUE"""),"https://imgur.com/a/XEfXuD8") -> https://imgur.com/a/XEfXuD8 | D3: =IFERROR(__xludf.DUMMYFUNCTION("""COMPUTED_VALUE"""),"-") -> -
A4: =IFERROR(__xludf.DUMMYFUNCTION("""COMPUTED_VALUE"""),"Venusaur") -> Venusaur | B4: =IFERROR(__xludf.DUMMYFUNCTION("""COMPUTED_VALUE"""),"https://imgur.com/a/QZY9tMI") -> https://imgur.com/a/QZY9tMI | C4: =IFERROR(__xludf.DUMMYFUNCTION("""COMPUTED_VALUE"""),"https://imgur.com/a/zRcrSLP") -> https://imgur.com/a/zRcrSLP | D4: =IFERROR(__xludf.DUMMYFUNCTION("""COMPUTED_VALUE"""),"-") -> -
A5: =IFERROR(__xludf.DUMMYFUNCTION("""COMPUTED_VALUE"""),"Charmander") -> Charmander | B5: =IFERROR(__xludf.DUMMYFUNCTION("""COMPUTED_VALUE"""),"-") -> - | C5: =IFERROR(__xludf.DUMMYFUNCTION("""COMPUTED_VALUE"""),"https://imgur.com/a/8vGvdYp") -> https://imgur.com/a/8vGvdYp | D5: =IFERROR(__xludf.DUMMYFUNCTION("""COMPUTED_VALUE"""),"-") -> -
A6: =IFERROR(__xludf.DUMMYFUNCTION("""COMPUTED_VALUE"""),"Charmelion") -> Charmelion | B6: =IFERROR(__xludf.DUMMYFUNCTION("""COMPUTED_VALUE"""),"-") -> - | C6: =IFERROR(__xludf.DUMMYFUNCTION("""COMPUTED_VALUE"""),"https://imgur.com/a/5ZdzM08") -> https://imgur.com/a/5ZdzM08 | D6: =IFERROR(__xludf.DUMMYFUNCTION("""COMPUTED_VALUE"""),"-") -> -
A7: =IFERROR(__xludf.DUMMYFUNCTION("""COMPUTED_VALUE"""),"Charizard") -> Charizard | B7: =IFERROR(__xludf.DUMMYFUNCTION("""COMPUTED_VALUE"""),"https://imgur.com/a/thSWZiw") -> https://imgur.com/a/thSWZiw | C7: =IFERROR(__xludf.DUMMYFUNCTION("""COMPUTED_VALUE"""),"https://imgur.com/a/ksXMwHN") -> https://imgur.com/a/ksXMwHN | D7: =IFERROR(__xludf.DUMMYFUNCTION("""COMPUTED_VALUE"""),"-") -> -
A8: =IFERROR(__xludf.DUMMYFUNCTION("""COMPUTED_VALUE"""),"Squirtle") -> Squirtle | B8: =IFERROR(__xludf.DUMMYFUNCTION("""COMPUTED_VALUE"""),"-") -> - | C8: =IFERROR(__xludf.DUMMYFUNCTION("""COMPUTED_VALUE"""),"https://imgur.com/a/8ZPHQzh") -> https://imgur.com/a/8ZPHQzh | D8: =IFERROR(__xludf.DUMMYFUNCTION("""COMPUTED_VALUE"""),"-") -> -
A9: =IFERROR(__xludf.DUMMYFUNCTION("""COMPUTED_VALUE"""),"Wartortle") -> Wartortle | B9: =IFERROR(__xludf.DUMMYFUNCTION("""COMPUTED_VALUE"""),"-") -> - | C9: =IFERROR(__xludf.DUMMYFUNCTION("""COMPUTED_VALUE"""),"https://imgur.com/a/wXrfm6F") -> https://imgur.com/a/wXrfm6F | D9: =IFERROR(__xludf.DUMMYFUNCTION("""COMPUTED_VALUE"""),"-") -> -
A10: =IFERROR(__xludf.DUMMYFUNCTION("""COMPUTED_VALUE"""),"Blastoise") -> Blastoise | B10: =IFERROR(__xludf.DUMMYFUNCTION("""COMPUTED_VALUE"""),"https://imgur.com/a/H98mIzg") -> https://imgur.com/a/H98mIzg | C10: =IFERROR(__xludf.DUMMYFUNCTION("""COMPUTED_VALUE"""),"https://imgur.com/a/o6O5mnt") -> https://imgur.com/a/o6O5mnt | D10: =IFERROR(__xludf.DUMMYFUNCTION("""COMPUTED_VALUE"""),"-") -> -
A11: =IFERROR(__xludf.DUMMYFUNCTION("""COMPUTED_VALUE"""),"Caterpie") -> Caterpie | B11: =IFERROR(__xludf.DUMMYFUNCTION("""COMPUTED_VALUE"""),"-") -> - | C11: =IFERROR(__xludf.DUMMYFUNCTION("""COMPUTED_VALUE"""),"https://imgur.com/a/FRZPc0L") -> https://imgur.com/a/FRZPc0L | D11: =IFERROR(__xludf.DUMMYFUNCTION("""COMPUTED_VALUE"""),"-") -> -
A12: =IFERROR(__xludf.DUMMYFUNCTION("""COMPUTED_VALUE"""),"Metapod") -> Metapod | B12: =IFERROR(__xludf.DUMMYFUNCTION("""COMPUTED_VALUE"""),"-") -> - | C12: =IFERROR(__xludf.DUMMYFUNCTION("""COMPUTED_VALUE"""),"https://imgur.com/a/Md3zxUt") -> https://imgur.com/a/Md3zxUt | D12: =IFERROR(__xludf.DUMMYFUNCTION("""COMPUTED_VALUE"""),"-") -> -
A13: =IFERROR(__xludf.DUMMYFUNCTION("""COMPUTED_VALUE"""),"Butterfree") -> Butterfree | B13: =IFERROR(__xludf.DUMMYFUNCTION("""COMPUTED_VALUE"""),"-") -> - | C13: =IFERROR(__xludf.DUMMYFUNCTION("""COMPUTED_VALUE"""),"https://imgur.com/a/IAhK3th") -> https://imgur.com/a/IAhK3th | D13: =IFERROR(__xludf.DUMMYFUNCTION("""COMPUTED_VALUE"""),"-") -> -
A14: =IFERROR(__xludf.DUMMYFUNCTION("""COMPUTED_VALUE"""),"Weedle") -> Weedle | B14: =IFERROR(__xludf.DUMMYFUNCTION("""COMPUTED_VALUE"""),"-") -> - | C14: =IFERROR(__xludf.DUMMYFUNCTION("""COMPUTED_VALUE"""),"https://imgur.com/a/3UGhQN6") -> https://imgur.com/a/3UGhQN6 | D14: =IFERROR(__xludf.DUMMYFUNCTION("""COMPUTED_VALUE"""),"-") -> -
A15: =IFERROR(__xludf.DUMMYFUNCTION("""COMPUTED_VALUE"""),"Kakuna") -> Kakuna | B15: =IFERROR(__xludf.DUMMYFUNCTION("""COMPUTED_VALUE"""),"-") -> - | C15: =IFERROR(__xludf.DUMMYFUNCTION("""COMPUTED_VALUE"""),"https://imgur.com/a/u3FmFya") -> https://imgur.com/a/u3FmFya | D15: =IFERROR(__xludf.DUMMYFUNCTION("""COMPUTED_VALUE"""),"-") -> -
A16: =IFERROR(__xludf.DUMMYFUNCTION("""COMPUTED_VALUE"""),"Beedrill") -> Beedrill | B16: =IFERROR(__xludf.DUMMYFUNCTION("""COMPUTED_VALUE"""),"-") -> - | C16: =IFERROR(__xludf.DUMMYFUNCTION("""COMPUTED_VALUE"""),"https://imgur.com/a/1F8OZPT") -> https://imgur.com/a/1F8OZPT | D16: =IFERROR(__xludf.DUMMYFUNCTION("""COMPUTED_VALUE"""),"-") -> -
A17: =IFERROR(__xludf.DUMMYFUNCTION("""COMPUTED_VALUE"""),"Pidgey") -> Pidgey | B17: =IFERROR(__xludf.DUMMYFUNCTION("""COMPUTED_VALUE"""),"-") -> - | C17: =IFERROR(__xludf.DUMMYFUNCTION("""COMPUTED_VALUE"""),"https://imgur.com/a/ANHSsgY") -> https://imgur.com/a/ANHSsgY | D17: =IFERROR(__xludf.DUMMYFUNCTION("""COMPUTED_VALUE"""),"-") -> -
A18: =IFERROR(__xludf.DUMMYFUNCTION("""COMPUTED_VALUE"""),"Pidgeotto") -> Pidgeotto | B18: =IFERROR(__xludf.DUMMYFUNCTION("""COMPUTED_VALUE"""),"-") -> - | C18: =IFERROR(__xludf.DUMMYFUNCTION("""COMPUTED_VALUE"""),"https://imgur.com/a/yq5WqUg") -> https://imgur.com/a/yq5WqUg | D18: =IFERROR(__xludf.DUMMYFUNCTION("""COMPUTED_VALUE"""),"-") -> -
A19: =IFERROR(__xludf.DUMMYFUNCTION("""COMPUTED_VALUE"""),"Pidgeot") -> Pidgeot | B19: =IFERROR(__xludf.DUMMYFUNCTION("""COMPUTED_VALUE"""),"https://imgur.com/a/mZdWvFw") -> https://imgur.com/a/mZdWvFw | C19: =IFERROR(__xludf.DUMMYFUNCTION("""COMPUTED_VALUE"""),"https://imgur.com/a/SmDawr1") -> https://imgur.com/a/SmDawr1 | D19: =IFERROR(__xludf.DUMMYFUNCTION("""COMPUTED_VALUE"""),"-") -> -
A20: =IFERROR(__xludf.DUMMYFUNCTION("""COMPUTED_VALUE"""),"Rattata") -> Rattata | B20: =IFERROR(__xludf.DUMMYFUNCTION("""COMPUTED_VALUE"""),"-") -> - | C20: =IFERROR(__xludf.DUMMYFUNCTION("""COMPUTED_VALUE"""),"https://imgur.com/a/ZyszZOZ") -> https://imgur.com/a/ZyszZOZ | D20: =IFERROR(__xludf.DUMMYFUNCTION("""COMPUTED_VALUE"""),"-") -> -
A21: =IFERROR(__xludf.DUMMYFUNCTION("""COMPUTED_VALUE"""),"Raticate") -> Raticate | B21: =IFERROR(__xludf.DUMMYFUNCTION("""COMPUTED_VALUE"""),"-") -> - | C21: =IFERROR(__xludf.DUMMYFUNCTION("""COMPUTED_VALUE"""),"https://imgur.com/a/ZyszZOZ") -> https://imgur.com/a/ZyszZOZ | D21: =IFERROR(__xludf.DUMMYFUNCTION("""COMPUTED_VALUE"""),"-") -> -
A22: =IFERROR(__xludf.DUMMYFUNCTION("""COMPUTED_VALUE"""),"Spearow") -> Spearow | B22: =IFERROR(__xludf.DUMMYFUNCTION("""COMPUTED_VALUE"""),"-") -> - | C22: =IFERROR(__xludf.DUMMYFUNCTION("""COMPUTED_VALUE"""),"https://imgur.com/a/ANHSsgY") -> https://imgur.com/a/ANHSsgY | D22: =IFERROR(__xludf.DUMMYFUNCTION("""COMPUTED_VALUE"""),"-") -> -
A23: =IFERROR(__xludf.DUMMYFUNCTION("""COMPUTED_VALUE"""),"Fearow") -> Fearow | B23: =IFERROR(__xludf.DUMMYFUNCTION("""COMPUTED_VALUE"""),"-") -> - | C23: =IFERROR(__xludf.DUMMYFUNCTION("""COMPUTED_VALUE"""),"https://imgur.com/a/NVXqWOp") -> https://imgur.com/a/NVXqWOp | D23: =IFERROR(__xludf.DUMMYFUNCTION("""COMPUTED_VALUE"""),"-") -> -
A24: =IFERROR(__xludf.DUMMYFUNCTION("""COMPUTED_VALUE"""),"Ekans") -> Ekans | B24: =IFERROR(__xludf.DUMMYFUNCTION("""COMPUTED_VALUE"""),"-") -> - | C24: =IFERROR(__xludf.DUMMYFUNCTION("""COMPUTED_VALUE"""),"https://imgur.com/a/X7pm0Qb") -> https://imgur.com/a/X7pm0Qb | D24: =IFERROR(__xludf.DUMMYFUNCTION("""COMPUTED_VALUE"""),"-") -> -
A25: =IFERROR(__xludf.DUMMYFUNCTION("""COMPUTED_VALUE"""),"Arbok") -> Arbok | B25: =IFERROR(__xludf.DUMMYFUNCTION("""COMPUTED_VALUE"""),"-") -> - | C25: =IFERROR(__xludf.DUMMYFUNCTION("""COMPUTED_VALUE"""),"https://imgur.com/a/urtC1Gz") -> https://imgur.com/a/urtC1Gz | D25: =IFERROR(__xludf.DUMMYFUNCTION("""COMPUTED_VALUE"""),"-") -> -
A26: =IFERROR(__xludf.DUMMYFUNCTION("""COMPUTED_VALUE"""),"Pikachu") -> Pikachu | B26: =IFERROR(__xludf.DUMMYFUNCTION("""COMPUTED_VALUE"""),"-") -> - | C26: =IFERROR(__xludf.DUMMYFUNCTION("""COMPUTED_VALUE"""),"https://imgur.com/a/eMjPulX") -> https://imgur.com/a/eMjPulX | D26: =IFERROR(__xludf.DUMMYFUNCTION("""COMPUTED_VALUE"""),"-") -> -
A27: =IFERROR(__xludf.DUMMYFUNCTION("""COMPUTED_VALUE"""),"Raichu") -> Raichu | B27: =IFERROR(__xludf.DUMMYFUNCTION("""COMPUTED_VALUE"""),"https://imgur.com/a/clP3jSD") -> https://imgur.com/a/clP3jSD | C27: =IFERROR(__xludf.DUMMYFUNCTION("""COMPUTED_VALUE"""),"https://imgur.com/a/tVt9b2v") -> https://imgur.com/a/tVt9b2v | D27: =IFERROR(__xludf.DUMMYFUNCTION("""COMPUTED_VALUE"""),"-") -> -
A28: =IFERROR(__xludf.DUMMYFUNCTION("""COMPUTED_VALUE"""),"Sandshrew") -> Sandshrew | B28: =IFERROR(__xludf.DUMMYFUNCTION("""COMPUTED_VALUE"""),"-") -> - | C28: =IFERROR(__xludf.DUMMYFUNCTION("""COMPUTED_VALUE"""),"https://imgur.com/a/hqHxs3c") -> https://imgur.com/a/hqHxs3c | D28: =IFERROR(__xludf.DUMMYFUNCTION("""COMPUTED_VALUE"""),"-") -> -
A29: =IFERROR(__xludf.DUMMYFUNCTION("""COMPUTED_VALUE"""),"Sandslash") -> Sandslash | B29: =IFERROR(__xludf.DUMMYFUNCTION("""COMPUTED_VALUE"""),"https://imgur.com/a/d4z4t8M") -> https://imgur.com/a/d4z4t8M | C29: =IFERROR(__xludf.DUMMYFUNCTION("""COMPUTED_VALUE"""),"https://imgur.com/a/jyNtIqk") -> https://imgur.com/a/jyNtIqk | D29: =IFERROR(__xludf.DUMMYFUNCTION("""COMPUTED_VALUE"""),"-") -> -
A30: =IFERROR(__xludf.DUMMYFUNCTION("""COMPUTED_VALUE"""),"Nidoran female") -> Nidoran female | B30: =IFERROR(__xludf.DUMMYFUNCTION("""COMPUTED_VALUE"""),"-") -> - | C30: =IFERROR(__xludf.DUMMYFUNCTION("""COMPUTED_VALUE"""),"https://imgur.com/a/fZJqgPy") -> https://imgur.com/a/fZJqgPy | D30: =IFERROR(__xludf.DUMMYFUNCTION("""COMPUTED_VALUE"""),"-") -> -
A31: =IFERROR(__xludf.DUMMYFUNCTION("""COMPUTED_VALUE"""),"Nidorina") -> Nidorina | B31: =IFERROR(__xludf.DUMMYFUNCTION("""COMPUTED_VALUE"""),"-") -> - | C31: =IFERROR(__xludf.DUMMYFUNCTION("""COMPUTED_VALUE"""),"https://imgur.com/a/x0itz9y") -> https://imgur.com/a/x0itz9y | D31: =IFERROR(__xludf.DUMMYFUNCTION("""COMPUTED_VALUE"""),"-") -> -
A32: =IFERROR(__xludf.DUMMYFUNCTION("""COMPUTED_VALUE"""),"Nidoqueen") -> Nidoqueen | B32: =IFERROR(__xludf.DUMMYFUNCTION("""COMPUTED_VALUE"""),"https://imgur.com/a/lnONjUq") -> https://imgur.com/a/lnONjUq | C32: =IFERROR(__xludf.DUMMYFUNCTION("""COMPUTED_VALUE"""),"https://imgur.com/a/UiIeSQX") -> https://imgur.com/a/UiIeSQX | D32: =IFERROR(__xludf.DUMMYFUNCTION("""COMPUTED_VALUE"""),"-") -> -
A33: =IFERROR(__xludf.DUMMYFUNCTION("""COMPUTED_VALUE"""),"Nidoran Male") -> Nidoran Male | B33: =IFERROR(__xludf.DUMMYFUNCTION("""COMPUTED_VALUE"""),"-") -> - | C33: =IFERROR(__xludf.DUMMYFUNCTION("""COMPUTED_VALUE"""),"https://imgur.com/a/fZJqgPy") -> https://imgur.com/a/fZJqgPy | D33: =IFERROR(__xludf.DUMMYFUNCTION("""COMPUTED_VALUE"""),"-") -> -
A34: =IFERROR(__xludf.DUMMYFUNCTION("""COMPUTED_VALUE"""),"Nidorino") -> Nidorino | B34: =IFERROR(__xludf.DUMMYFUNCTION("""COMPUTED_VALUE"""),"-") -> - | C34: =IFERROR(__xludf.DUMMYFUNCTION("""COMPUTED_VALUE"""),"https://imgur.com/a/x0itz9y") -> https://imgur.com/a/x0itz9y | D34: =IFERROR(__xludf.DUMMYFUNCTION("""COMPUTED_VALUE"""),"-") -> -
A35: =IFERROR(__xludf.DUMMYFUNCTION("""COMPUTED_VALUE"""),"Nidoking") -> Nidoking | B35: =IFERROR(__xludf.DUMMYFUNCTION("""COMPUTED_VALUE"""),"https://imgur.com/a/HWxtEs3") -> https://imgur.com/a/HWxtEs3 | C35: =IFERROR(__xludf.DUMMYFUNCTION("""COMPUTED_VALUE"""),"https://imgur.com/a/6fIH7lZ") -> https://imgur.com/a/6fIH7lZ | D35: =IFERROR(__xludf.DUMMYFUNCTION("""COMPUTED_VALUE"""),"-") -> -
A36: =IFERROR(__xludf.DUMMYFUNCTION("""COMPUTED_VALUE"""),"Clefairy") -> Clefairy | B36: =IFERROR(__xludf.DUMMYFUNCTION("""COMPUTED_VALUE"""),"-") -> - | C36: =IFERROR(__xludf.DUMMYFUNCTION("""COMPUTED_VALUE"""),"https://imgur.com/a/HipDvE8") -> https://imgur.com/a/HipDvE8 | D36: =IFERROR(__xludf.DUMMYFUNCTION("""COMPUTED_VALUE"""),"-") -> -
A37: =IFERROR(__xludf.DUMMYFUNCTION("""COMPUTED_VALUE"""),"Clefable") -> Clefable | B37: =IFERROR(__xludf.DUMMYFUNCTION("""COMPUTED_VALUE"""),"https://imgur.com/a/sXQlso1") -> https://imgur.com/a/sXQlso1 | C37: =IFERROR(__xludf.DUMMYFUNCTION("""COMPUTED_VALUE"""),"Escada na DG de Floette em Pewter") -> Escada na DG de Floette em Pewter | D37: =IFERROR(__xludf.DUMMYFUNCTION("""COMPUTED_VALUE"""),"-") -> -
A38: =IFERROR(__xludf.DUMMYFUNCTION("""COMPUTED_VALUE"""),"Vulpix") -> Vulpix | B38: =IFERROR(__xludf.DUMMYFUNCTION("""COMPUTED_VALUE"""),"-") -> - | C38: =IFERROR(__xludf.DUMMYFUNCTION("""COMPUTED_VALUE"""),"https://imgur.com/a/G4NlFHG") -> https://imgur.com/a/G4NlFHG | D38: =IFERROR(__xludf.DUMMYFUNCTION("""COMPUTED_VALUE"""),"-") -> -
A39: =IFERROR(__xludf.DUMMYFUNCTION("""COMPUTED_VALUE"""),"Ninetales") -> Ninetales | B39: =IFERROR(__xludf.DUMMYFUNCTION("""COMPUTED_VALUE"""),"https://imgur.com/a/2uMZqFZ") -> https://imgur.com/a/2uMZqFZ | C39: =IFERROR(__xludf.DUMMYFUNCTION("""COMPUTED_VALUE"""),"https://imgur.com/a/Rh21XkV") -> https://imgur.com/a/Rh21XkV | D39: =IFERROR(__xludf.DUMMYFUNCTION("""COMPUTED_VALUE"""),"-") -> -
A40: =IFERROR(__xludf.DUMMYFUNCTION("""COMPUTED_VALUE"""),"Jigglypuff") -> Jigglypuff | B40: =IFERROR(__xludf.DUMMYFUNCTION("""COMPUTED_VALUE"""),"-") -> - | C40: =IFERROR(__xludf.DUMMYFUNCTION("""COMPUTED_VALUE"""),"https://imgur.com/a/HipDvE8") -> https://imgur.com/a/HipDvE8 | D40: =IFERROR(__xludf.DUMMYFUNCTION("""COMPUTED_VALUE"""),"-") -> -
A41: =IFERROR(__xludf.DUMMYFUNCTION("""COMPUTED_VALUE"""),"Wigglytuff") -> Wigglytuff | B41: =IFERROR(__xludf.DUMMYFUNCTION("""COMPUTED_VALUE"""),"https://imgur.com/a/FuZNCOC") -> https://imgur.com/a/FuZNCOC | C41: =IFERROR(__xludf.DUMMYFUNCTION("""COMPUTED_VALUE"""),"Escada na DG de Folette em Pewter") -> Escada na DG de Folette em Pewter | D41: =IFERROR(__xludf.DUMMYFUNCTION("""COMPUTED_VALUE"""),"-") -> -
A42: =IFERROR(__xludf.DUMMYFUNCTION("""COMPUTED_VALUE"""),"Zubat") -> Zubat | B42: =IFERROR(__xludf.DUMMYFUNCTION("""COMPUTED_VALUE"""),"-") -> - | C42: =IFERROR(__xludf.DUMMYFUNCTION("""COMPUTED_VALUE"""),"https://imgur.com/a/RlR6LYU") -> https://imgur.com/a/RlR6LYU | D42: =IFERROR(__xludf.DUMMYFUNCTION("""COMPUTED_VALUE"""),"-") -> -
A43: =IFERROR(__xludf.DUMMYFUNCTION("""COMPUTED_VALUE"""),"Golbat") -> Golbat | B43: =IFERROR(__xludf.DUMMYFUNCTION("""COMPUTED_VALUE"""),"-") -> - | C43: =IFERROR(__xludf.DUMMYFUNCTION("""COMPUTED_VALUE"""),"https://imgur.com/a/uvfPxaO") -> https://imgur.com/a/uvfPxaO | D43: =IFERROR(__xludf.DUMMYFUNCTION("""COMPUTED_VALUE"""),"-") -> -
A44: =IFERROR(__xludf.DUMMYFUNCTION("""COMPUTED_VALUE"""),"Oddish") -> Oddish | B44: =IFERROR(__xludf.DUMMYFUNCTION("""COMPUTED_VALUE"""),"-") -> - | C44: =IFERROR(__xludf.DUMMYFUNCTION("""COMPUTED_VALUE"""),"https://imgur.com/a/2SuUURl") -> https://imgur.com/a/2SuUURl | D44: =IFERROR(__xludf.DUMMYFUNCTION("""COMPUTED_VALUE"""),"-") -> -
A45: =IFERROR(__xludf.DUMMYFUNCTION("""COMPUTED_VALUE"""),"Gloom") -> Gloom | B45: =IFERROR(__xludf.DUMMYFUNCTION("""COMPUTED_VALUE"""),"-") -> - | C45: =IFERROR(__xludf.DUMMYFUNCTION("""COMPUTED_VALUE"""),"https://imgur.com/a/TaH2l6m") -> https://imgur.com/a/TaH2l6m | D45: =IFERROR(__xludf.DUMMYFUNCTION("""COMPUTED_VALUE"""),"-") -> -
A46: =IFERROR(__xludf.DUMMYFUNCTION("""COMPUTED_VALUE"""),"Vileplume") -> Vileplume | B46: =IFERROR(__xludf.DUMMYFUNCTION("""COMPUTED_VALUE"""),"-") -> - | C46: =IFERROR(__xludf.DUMMYFUNCTION("""COMPUTED_VALUE"""),"https://imgur.com/a/iOsQeVF") -> https://imgur.com/a/iOsQeVF | D46: =IFERROR(__xludf.DUMMYFUNCTION("""COMPUTED_VALUE"""),"-") -> -
A47: =IFERROR(__xludf.DUMMYFUNCTION("""COMPUTED_VALUE"""),"Paras") -> Paras | B47: =IFERROR(__xludf.DUMMYFUNCTION("""COMPUTED_VALUE"""),"-") -> - | C47: =IFERROR(__xludf.DUMMYFUNCTION("""COMPUTED_VALUE"""),"https://imgur.com/a/tv3nErv") -> https://imgur.com/a/tv3nErv | D47: =IFERROR(__xludf.DUMMYFUNCTION("""COMPUTED_VALUE"""),"-") -> -
A48: =IFERROR(__xludf.DUMMYFUNCTION("""COMPUTED_VALUE"""),"Parasect") -> Parasect | B48: =IFERROR(__xludf.DUMMYFUNCTION("""COMPUTED_VALUE"""),"-") -> - | C48: =IFERROR(__xludf.DUMMYFUNCTION("""COMPUTED_VALUE"""),"https://imgur.com/a/tv3nErv") -> https://imgur.com/a/tv3nErv | D48: =IFERROR(__xludf.DUMMYFUNCTION("""COMPUTED_VALUE"""),"-") -> -
A49: =IFERROR(__xludf.DUMMYFUNCTION("""COMPUTED_VALUE"""),"Venonat") -> Venonat | B49: =IFERROR(__xludf.DUMMYFUNCTION("""COMPUTED_VALUE"""),"-") -> - | C49: =IFERROR(__xludf.DUMMYFUNCTION("""COMPUTED_VALUE"""),"https://imgur.com/a/X5fPhhu") -> https://imgur.com/a/X5fPhhu | D49: =IFERROR(__xludf.DUMMYFUNCTION("""COMPUTED_VALUE"""),"-") -> -
A50: =IFERROR(__xludf.DUMMYFUNCTION("""COMPUTED_VALUE"""),"Venomoth") -> Venomoth | B50: =IFERROR(__xludf.DUMMYFUNCTION("""COMPUTED_VALUE"""),"https://imgur.com/a/pfHx2qk") -> https://imgur.com/a/pfHx2qk | C50: =IFERROR(__xludf.DUMMYFUNCTION("""COMPUTED_VALUE"""),"https://imgur.com/a/09DbkdU") -> https://imgur.com/a/09DbkdU | D50: =IFERROR(__xludf.DUMMYFUNCTION("""COMPUTED_VALUE"""),"-") -> -
A51: =IFERROR(__xludf.DUMMYFUNCTION("""COMPUTED_VALUE"""),"Diglett") -> Diglett | B51: =IFERROR(__xludf.DUMMYFUNCTION("""COMPUTED_VALUE"""),"-") -> - | C51: =IFERROR(__xludf.DUMMYFUNCTION("""COMPUTED_VALUE"""),"https://imgur.com/a/oqtqJb4") -> https://imgur.com/a/oqtqJb4 | D51: =IFERROR(__xludf.DUMMYFUNCTION("""COMPUTED_VALUE"""),"-") -> -
A52: =IFERROR(__xludf.DUMMYFUNCTION("""COMPUTED_VALUE"""),"Dugtrio") -> Dugtrio | B52: =IFERROR(__xludf.DUMMYFUNCTION("""COMPUTED_VALUE"""),"-") -> - | C52: =IFERROR(__xludf.DUMMYFUNCTION("""COMPUTED_VALUE"""),"https://imgur.com/a/qAQiMyS") -> https://imgur.com/a/qAQiMyS | D52: =IFERROR(__xludf.DUMMYFUNCTION("""COMPUTED_VALUE"""),"-") -> -
A53: =IFERROR(__xludf.DUMMYFUNCTION("""COMPUTED_VALUE"""),"Meowth") -> Meowth | B53: =IFERROR(__xludf.DUMMYFUNCTION("""COMPUTED_VALUE"""),"-") -> - | C53: =IFERROR(__xludf.DUMMYFUNCTION("""COMPUTED_VALUE"""),"https://imgur.com/a/ZaKbHhf") -> https://imgur.com/a/ZaKbHhf | D53: =IFERROR(__xludf.DUMMYFUNCTION("""COMPUTED_VALUE"""),"-") -> -
A54: =IFERROR(__xludf.DUMMYFUNCTION("""COMPUTED_VALUE"""),"Persian") -> Persian | B54: =IFERROR(__xludf.DUMMYFUNCTION("""COMPUTED_VALUE"""),"https://imgur.com/a/B7jUmCO") -> https://imgur.com/a/B7jUmCO | C54: =IFERROR(__xludf.DUMMYFUNCTION("""COMPUTED_VALUE"""),"https://imgur.com/a/pCa1RXB") -> https://imgur.com/a/pCa1RXB | D54: =IFERROR(__xludf.DUMMYFUNCTION("""COMPUTED_VALUE"""),"-") -> -
A55: =IFERROR(__xludf.DUMMYFUNCTION("""COMPUTED_VALUE"""),"Psyduck") -> Psyduck | B55: =IFERROR(__xludf.DUMMYFUNCTION("""COMPUTED_VALUE"""),"-") -> - | C55: =IFERROR(__xludf.DUMMYFUNCTION("""COMPUTED_VALUE"""),"https://imgur.com/a/ndO8iRQ") -> https://imgur.com/a/ndO8iRQ | D55: =IFERROR(__xludf.DUMMYFUNCTION("""COMPUTED_VALUE"""),"-") -> -
A56: =IFERROR(__xludf.DUMMYFUNCTION("""COMPUTED_VALUE"""),"Golduck") -> Golduck | B56: =IFERROR(__xludf.DUMMYFUNCTION("""COMPUTED_VALUE"""),"-") -> - | C56: =IFERROR(__xludf.DUMMYFUNCTION("""COMPUTED_VALUE"""),"https://youtu.be/jTEe_aB8h-A") -> https://youtu.be/jTEe_aB8h-A | D56: =IFERROR(__xludf.DUMMYFUNCTION("""COMPUTED_VALUE"""),"-") -> -
A57: =IFERROR(__xludf.DUMMYFUNCTION("""COMPUTED_VALUE"""),"Mankey") -> Mankey | B57: =IFERROR(__xludf.DUMMYFUNCTION("""COMPUTED_VALUE"""),"-") -> - | C57: =IFERROR(__xludf.DUMMYFUNCTION("""COMPUTED_VALUE"""),"https://imgur.com/a/4E7gOtq") -> https://imgur.com/a/4E7gOtq | D57: =IFERROR(__xludf.DUMMYFUNCTION("""COMPUTED_VALUE"""),"-") -> -
A58: =IFERROR(__xludf.DUMMYFUNCTION("""COMPUTED_VALUE"""),"Primeape") -> Primeape | B58: =IFERROR(__xludf.DUMMYFUNCTION("""COMPUTED_VALUE"""),"-") -> - | C58: =IFERROR(__xludf.DUMMYFUNCTION("""COMPUTED_VALUE"""),"https://imgur.com/a/4E7gOtq") -> https://imgur.com/a/4E7gOtq | D58: =IFERROR(__xludf.DUMMYFUNCTION("""COMPUTED_VALUE"""),"-") -> -
A59: =IFERROR(__xludf.DUMMYFUNCTION("""COMPUTED_VALUE"""),"Growlithe") -> Growlithe | B59: =IFERROR(__xludf.DUMMYFUNCTION("""COMPUTED_VALUE"""),"-") -> - | C59: =IFERROR(__xludf.DUMMYFUNCTION("""COMPUTED_VALUE"""),"https://imgur.com/a/yAYRe4r") -> https://imgur.com/a/yAYRe4r | D59: =IFERROR(__xludf.DUMMYFUNCTION("""COMPUTED_VALUE"""),"-") -> -
A60: =IFERROR(__xludf.DUMMYFUNCTION("""COMPUTED_VALUE"""),"Arcanine") -> Arcanine | B60: =IFERROR(__xludf.DUMMYFUNCTION("""COMPUTED_VALUE"""),"https://imgur.com/a/NnkwV5t") -> https://imgur.com/a/NnkwV5t | C60: =IFERROR(__xludf.DUMMYFUNCTION("""COMPUTED_VALUE"""),"https://imgur.com/a/InCkrp9") -> https://imgur.com/a/InCkrp9 | D60: =IFERROR(__xludf.DUMMYFUNCTION("""COMPUTED_VALUE"""),"-") -> -
A61: =IFERROR(__xludf.DUMMYFUNCTION("""COMPUTED_VALUE"""),"Poliwag") -> Poliwag | B61: =IFERROR(__xludf.DUMMYFUNCTION("""COMPUTED_VALUE"""),"-") -> - | C61: =IFERROR(__xludf.DUMMYFUNCTION("""COMPUTED_VALUE"""),"https://imgur.com/a/LmUUKug") -> https://imgur.com/a/LmUUKug | D61: =IFERROR(__xludf.DUMMYFUNCTION("""COMPUTED_VALUE"""),"-") -> -
A62: =IFERROR(__xludf.DUMMYFUNCTION("""COMPUTED_VALUE"""),"Poliwhirl") -> Poliwhirl | B62: =IFERROR(__xludf.DUMMYFUNCTION("""COMPUTED_VALUE"""),"-") -> - | C62: =IFERROR(__xludf.DUMMYFUNCTION("""COMPUTED_VALUE"""),"https://imgur.com/a/4pP85lz") -> https://imgur.com/a/4pP85lz | D62: =IFERROR(__xludf.DUMMYFUNCTION("""COMPUTED_VALUE"""),"-") -> -
A63: =IFERROR(__xludf.DUMMYFUNCTION("""COMPUTED_VALUE"""),"Poliwrath") -> Poliwrath | B63: =IFERROR(__xludf.DUMMYFUNCTION("""COMPUTED_VALUE"""),"https://imgur.com/a/c9ewG6a") -> https://imgur.com/a/c9ewG6a | C63: =IFERROR(__xludf.DUMMYFUNCTION("""COMPUTED_VALUE"""),"https://imgur.com/a/IyWzoPx") -> https://imgur.com/a/IyWzoPx | D63: =IFERROR(__xludf.DUMMYFUNCTION("""COMPUTED_VALUE"""),"-") -> -
A64: =IFERROR(__xludf.DUMMYFUNCTION("""COMPUTED_VALUE"""),"Abra") -> Abra | B64: =IFERROR(__xludf.DUMMYFUNCTION("""COMPUTED_VALUE"""),"-") -> - | C64: =IFERROR(__xludf.DUMMYFUNCTION("""COMPUTED_VALUE"""),"https://imgur.com/a/ekO6c8T") -> https://imgur.com/a/ekO6c8T | D64: =IFERROR(__xludf.DUMMYFUNCTION("""COMPUTED_VALUE"""),"-") -> -
A65: =IFERROR(__xludf.DUMMYFUNCTION("""COMPUTED_VALUE"""),"Kadabra") -> Kadabra | B65: =IFERROR(__xludf.DUMMYFUNCTION("""COMPUTED_VALUE"""),"-") -> - | C65: =IFERROR(__xludf.DUMMYFUNCTION("""COMPUTED_VALUE"""),"https://imgur.com/a/G7qjSsO") -> https://imgur.com/a/G7qjSsO | D65: =IFERROR(__xludf.DUMMYFUNCTION("""COMPUTED_VALUE"""),"-") -> -
A66: =IFERROR(__xludf.DUMMYFUNCTION("""COMPUTED_VALUE"""),"Alakazam") -> Alakazam | B66: =IFERROR(__xludf.DUMMYFUNCTION("""COMPUTED_VALUE"""),"https://imgur.com/a/OEmy8zV") -> https://imgur.com/a/OEmy8zV | C66: =IFERROR(__xludf.DUMMYFUNCTION("""COMPUTED_VALUE"""),"https://imgur.com/a/n2TjM6f") -> https://imgur.com/a/n2TjM6f | D66: =IFERROR(__xludf.DUMMYFUNCTION("""COMPUTED_VALUE"""),"https://imgur.com/a/wFcUcVR") -> https://imgur.com/a/wFcUcVR
A67: =IFERROR(__xludf.DUMMYFUNCTION("""COMPUTED_VALUE"""),"Machop") -> Machop | B67: =IFERROR(__xludf.DUMMYFUNCTION("""COMPUTED_VALUE"""),"-") -> - | C67: =IFERROR(__xludf.DUMMYFUNCTION("""COMPUTED_VALUE"""),"https://imgur.com/a/C6BDrQk") -> https://imgur.com/a/C6BDrQk | D67: =IFERROR(__xludf.DUMMYFUNCTION("""COMPUTED_VALUE"""),"-") -> -
A68: =IFERROR(__xludf.DUMMYFUNCTION("""COMPUTED_VALUE"""),"Machoke") -> Machoke | B68: =IFERROR(__xludf.DUMMYFUNCTION("""COMPUTED_VALUE"""),"-") -> - | C68: =IFERROR(__xludf.DUMMYFUNCTION("""COMPUTED_VALUE"""),"https://imgur.com/a/C6BDrQk") -> https://imgur.com/a/C6BDrQk | D68: =IFERROR(__xludf.DUMMYFUNCTION("""COMPUTED_VALUE"""),"-") -> -
A69: =IFERROR(__xludf.DUMMYFUNCTION("""COMPUTED_VALUE"""),"Machamp") -> Machamp | B69: =IFERROR(__xludf.DUMMYFUNCTION("""COMPUTED_VALUE"""),"https://imgur.com/a/yB63tms") -> https://imgur.com/a/yB63tms | C69: =IFERROR(__xludf.DUMMYFUNCTION("""COMPUTED_VALUE"""),"Norte de Lavender, último andar") -> Norte de Lavender, último andar | D69: =IFERROR(__xludf.DUMMYFUNCTION("""COMPUTED_VALUE"""),"-") -> -
A70: =IFERROR(__xludf.DUMMYFUNCTION("""COMPUTED_VALUE"""),"Bellsprout") -> Bellsprout | B70: =IFERROR(__xludf.DUMMYFUNCTION("""COMPUTED_VALUE"""),"-") -> - | C70: =IFERROR(__xludf.DUMMYFUNCTION("""COMPUTED_VALUE"""),"https://imgur.com/a/MnFL6no") -> https://imgur.com/a/MnFL6no | D70: =IFERROR(__xludf.DUMMYFUNCTION("""COMPUTED_VALUE"""),"-") -> -
A71: =IFERROR(__xludf.DUMMYFUNCTION("""COMPUTED_VALUE"""),"Weepinbell") -> Weepinbell | B71: =IFERROR(__xludf.DUMMYFUNCTION("""COMPUTED_VALUE"""),"-") -> - | C71: =IFERROR(__xludf.DUMMYFUNCTION("""COMPUTED_VALUE"""),"https://imgur.com/a/Xw7aLDs") -> https://imgur.com/a/Xw7aLDs | D71: =IFERROR(__xludf.DUMMYFUNCTION("""COMPUTED_VALUE"""),"-") -> -
A72: =IFERROR(__xludf.DUMMYFUNCTION("""COMPUTED_VALUE"""),"Victreebel") -> Victreebel | B72: =IFERROR(__xludf.DUMMYFUNCTION("""COMPUTED_VALUE"""),"-") -> - | C72: =IFERROR(__xludf.DUMMYFUNCTION("""COMPUTED_VALUE"""),"https://imgur.com/a/oL0tt9a") -> https://imgur.com/a/oL0tt9a | D72: =IFERROR(__xludf.DUMMYFUNCTION("""COMPUTED_VALUE"""),"-") -> -
A73: =IFERROR(__xludf.DUMMYFUNCTION("""COMPUTED_VALUE"""),"Tentacool") -> Tentacool | B73: =IFERROR(__xludf.DUMMYFUNCTION("""COMPUTED_VALUE"""),"-") -> - | C73: =IFERROR(__xludf.DUMMYFUNCTION("""COMPUTED_VALUE"""),"https://imgur.com/a/UadRpGw") -> https://imgur.com/a/UadRpGw | D73: =IFERROR(__xludf.DUMMYFUNCTION("""COMPUTED_VALUE"""),"-") -> -
A74: =IFERROR(__xludf.DUMMYFUNCTION("""COMPUTED_VALUE"""),"Tentacruel") -> Tentacruel | B74: =IFERROR(__xludf.DUMMYFUNCTION("""COMPUTED_VALUE"""),"https://imgur.com/a/1MIh0TT") -> https://imgur.com/a/1MIh0TT | C74: =IFERROR(__xludf.DUMMYFUNCTION("""COMPUTED_VALUE"""),"https://imgur.com/a/1MIh0TT") -> https://imgur.com/a/1MIh0TT | D74: =IFERROR(__xludf.DUMMYFUNCTION("""COMPUTED_VALUE"""),"-") -> -
A75: =IFERROR(__xludf.DUMMYFUNCTION("""COMPUTED_VALUE"""),"Geodude") -> Geodude | B75: =IFERROR(__xludf.DUMMYFUNCTION("""COMPUTED_VALUE"""),"-") -> - | C75: =IFERROR(__xludf.DUMMYFUNCTION("""COMPUTED_VALUE"""),"https://imgur.com/a/IhJ17iJ") -> https://imgur.com/a/IhJ17iJ | D75: =IFERROR(__xludf.DUMMYFUNCTION("""COMPUTED_VALUE"""),"-") -> -
A76: =IFERROR(__xludf.DUMMYFUNCTION("""COMPUTED_VALUE"""),"Graveler") -> Graveler | B76: =IFERROR(__xludf.DUMMYFUNCTION("""COMPUTED_VALUE"""),"-") -> - | C76: =IFERROR(__xludf.DUMMYFUNCTION("""COMPUTED_VALUE"""),"https://imgur.com/a/SHzJxH4") -> https://imgur.com/a/SHzJxH4 | D76: =IFERROR(__xludf.DUMMYFUNCTION("""COMPUTED_VALUE"""),"-") -> -
A77: =IFERROR(__xludf.DUMMYFUNCTION("""COMPUTED_VALUE"""),"Golem") -> Golem | B77: =IFERROR(__xludf.DUMMYFUNCTION("""COMPUTED_VALUE"""),"https://imgur.com/a/rg5qYI4") -> https://imgur.com/a/rg5qYI4 | C77: =IFERROR(__xludf.DUMMYFUNCTION("""COMPUTED_VALUE"""),"https://imgur.com/a/1JOCaQq") -> https://imgur.com/a/1JOCaQq | D77: =IFERROR(__xludf.DUMMYFUNCTION("""COMPUTED_VALUE"""),"-") -> -
A78: =IFERROR(__xludf.DUMMYFUNCTION("""COMPUTED_VALUE"""),"Ponyta") -> Ponyta | B78: =IFERROR(__xludf.DUMMYFUNCTION("""COMPUTED_VALUE"""),"-") -> - | C78: =IFERROR(__xludf.DUMMYFUNCTION("""COMPUTED_VALUE"""),"https://imgur.com/a/Wj6MnzA") -> https://imgur.com/a/Wj6MnzA | D78: =IFERROR(__xludf.DUMMYFUNCTION("""COMPUTED_VALUE"""),"-") -> -
A79: =IFERROR(__xludf.DUMMYFUNCTION("""COMPUTED_VALUE"""),"Rapidash") -> Rapidash | B79: =IFERROR(__xludf.DUMMYFUNCTION("""COMPUTED_VALUE"""),"https://imgur.com/a/lwqRvJB") -> https://imgur.com/a/lwqRvJB | C79: =IFERROR(__xludf.DUMMYFUNCTION("""COMPUTED_VALUE"""),"https://imgur.com/a/wtXPt06") -> https://imgur.com/a/wtXPt06 | D79: =IFERROR(__xludf.DUMMYFUNCTION("""COMPUTED_VALUE"""),"-") -> -
A80: =IFERROR(__xludf.DUMMYFUNCTION("""COMPUTED_VALUE"""),"Slowpoke") -> Slowpoke | B80: =IFERROR(__xludf.DUMMYFUNCTION("""COMPUTED_VALUE"""),"-") -> - | C80: =IFERROR(__xludf.DUMMYFUNCTION("""COMPUTED_VALUE"""),"Poço direita de Azalea") -> Poço direita de Azalea | D80: =IFERROR(__xludf.DUMMYFUNCTION("""COMPUTED_VALUE"""),"-") -> -
A81: =IFERROR(__xludf.DUMMYFUNCTION("""COMPUTED_VALUE"""),"Slowbro") -> Slowbro | B81: =IFERROR(__xludf.DUMMYFUNCTION("""COMPUTED_VALUE"""),"-") -> - | C81: =IFERROR(__xludf.DUMMYFUNCTION("""COMPUTED_VALUE"""),"Poço direita de Azalea") -> Poço direita de Azalea | D81: =IFERROR(__xludf.DUMMYFUNCTION("""COMPUTED_VALUE"""),"-") -> -
A82: =IFERROR(__xludf.DUMMYFUNCTION("""COMPUTED_VALUE"""),"Magnemite") -> Magnemite | B82: =IFERROR(__xludf.DUMMYFUNCTION("""COMPUTED_VALUE"""),"-") -> - | C82: =IFERROR(__xludf.DUMMYFUNCTION("""COMPUTED_VALUE"""),"https://imgur.com/a/ZNQjOvj") -> https://imgur.com/a/ZNQjOvj | D82: =IFERROR(__xludf.DUMMYFUNCTION("""COMPUTED_VALUE"""),"-") -> -
A83: =IFERROR(__xludf.DUMMYFUNCTION("""COMPUTED_VALUE"""),"Magneton") -> Magneton | B83: =IFERROR(__xludf.DUMMYFUNCTION("""COMPUTED_VALUE"""),"https://imgur.com/a/fbJrvin") -> https://imgur.com/a/fbJrvin | C83: =IFERROR(__xludf.DUMMYFUNCTION("""COMPUTED_VALUE"""),"https://imgur.com/a/ZNQjOvj") -> https://imgur.com/a/ZNQjOvj | D83: =IFERROR(__xludf.DUMMYFUNCTION("""COMPUTED_VALUE"""),"-") -> -
A84: =IFERROR(__xludf.DUMMYFUNCTION("""COMPUTED_VALUE"""),"Farfetch'd") -> Farfetch'd | B84: =IFERROR(__xludf.DUMMYFUNCTION("""COMPUTED_VALUE"""),"https://imgur.com/a/mZdWvFw") -> https://imgur.com/a/mZdWvFw | C84: =IFERROR(__xludf.DUMMYFUNCTION("""COMPUTED_VALUE"""),"Direita de Fuchsia") -> Direita de Fuchsia | D84: =IFERROR(__xludf.DUMMYFUNCTION("""COMPUTED_VALUE"""),"-") -> -
A85: =IFERROR(__xludf.DUMMYFUNCTION("""COMPUTED_VALUE"""),"Doduo") -> Doduo | B85: =IFERROR(__xludf.DUMMYFUNCTION("""COMPUTED_VALUE"""),"-") -> - | C85: =IFERROR(__xludf.DUMMYFUNCTION("""COMPUTED_VALUE"""),"Esquerda de Viridian") -> Esquerda de Viridian | D85: =IFERROR(__xludf.DUMMYFUNCTION("""COMPUTED_VALUE"""),"-") -> -
A86: =IFERROR(__xludf.DUMMYFUNCTION("""COMPUTED_VALUE"""),"Dodrio") -> Dodrio | B86: =IFERROR(__xludf.DUMMYFUNCTION("""COMPUTED_VALUE"""),"https://imgur.com/a/mZdWvFw") -> https://imgur.com/a/mZdWvFw | C86: =IFERROR(__xludf.DUMMYFUNCTION("""COMPUTED_VALUE"""),"https://imgur.com/a/8rw5VI3") -> https://imgur.com/a/8rw5VI3 | D86: =IFERROR(__xludf.DUMMYFUNCTION("""COMPUTED_VALUE"""),"-") -> -
A87: =IFERROR(__xludf.DUMMYFUNCTION("""COMPUTED_VALUE"""),"Seel") -> Seel | B87: =IFERROR(__xludf.DUMMYFUNCTION("""COMPUTED_VALUE"""),"-") -> - | C87: =IFERROR(__xludf.DUMMYFUNCTION("""COMPUTED_VALUE"""),"https://imgur.com/a/0FU7pxA") -> https://imgur.com/a/0FU7pxA | D87: =IFERROR(__xludf.DUMMYFUNCTION("""COMPUTED_VALUE"""),"-") -> -
A88: =IFERROR(__xludf.DUMMYFUNCTION("""COMPUTED_VALUE"""),"Dewgong") -> Dewgong | B88: =IFERROR(__xludf.DUMMYFUNCTION("""COMPUTED_VALUE"""),"https://imgur.com/a/AWD6nTs") -> https://imgur.com/a/AWD6nTs | C88: =IFERROR(__xludf.DUMMYFUNCTION("""COMPUTED_VALUE"""),"https://imgur.com/a/6S3V66E") -> https://imgur.com/a/6S3V66E | D88: =IFERROR(__xludf.DUMMYFUNCTION("""COMPUTED_VALUE"""),"-") -> -
A89: =IFERROR(__xludf.DUMMYFUNCTION("""COMPUTED_VALUE"""),"Grimer") -> Grimer | B89: =IFERROR(__xludf.DUMMYFUNCTION("""COMPUTED_VALUE"""),"-") -> - | C89: =IFERROR(__xludf.DUMMYFUNCTION("""COMPUTED_VALUE"""),"https://imgur.com/a/vgGrrfT") -> https://imgur.com/a/vgGrrfT | D89: =IFERROR(__xludf.DUMMYFUNCTION("""COMPUTED_VALUE"""),"-") -> -
A90: =IFERROR(__xludf.DUMMYFUNCTION("""COMPUTED_VALUE"""),"Muk") -> Muk | B90: =IFERROR(__xludf.DUMMYFUNCTION("""COMPUTED_VALUE"""),"https://imgur.com/a/vgGrrfT") -> https://imgur.com/a/vgGrrfT | C90: =IFERROR(__xludf.DUMMYFUNCTION("""COMPUTED_VALUE"""),"https://imgur.com/a/vgGrrfT") -> https://imgur.com/a/vgGrrfT | D90: =IFERROR(__xludf.DUMMYFUNCTION("""COMPUTED_VALUE"""),"-") -> -
A91: =IFERROR(__xludf.DUMMYFUNCTION("""COMPUTED_VALUE"""),"Shellder") -> Shellder | B91: =IFERROR(__xludf.DUMMYFUNCTION("""COMPUTED_VALUE"""),"-") -> - | C91: =IFERROR(__xludf.DUMMYFUNCTION("""COMPUTED_VALUE"""),"https://imgur.com/a/mHLB6sh") -> https://imgur.com/a/mHLB6sh | D91: =IFERROR(__xludf.DUMMYFUNCTION("""COMPUTED_VALUE"""),"-") -> -
A92: =IFERROR(__xludf.DUMMYFUNCTION("""COMPUTED_VALUE"""),"Cloyster") -> Cloyster | B92: =IFERROR(__xludf.DUMMYFUNCTION("""COMPUTED_VALUE"""),"https://imgur.com/a/JxKX8lv") -> https://imgur.com/a/JxKX8lv | C92: =IFERROR(__xludf.DUMMYFUNCTION("""COMPUTED_VALUE"""),"Ilha de gelo sudeste de Kanto") -> Ilha de gelo sudeste de Kanto | D92: =IFERROR(__xludf.DUMMYFUNCTION("""COMPUTED_VALUE"""),"-") -> -
A93: =IFERROR(__xludf.DUMMYFUNCTION("""COMPUTED_VALUE"""),"Gastly") -> Gastly | B93: =IFERROR(__xludf.DUMMYFUNCTION("""COMPUTED_VALUE"""),"-") -> - | C93: =IFERROR(__xludf.DUMMYFUNCTION("""COMPUTED_VALUE"""),"https://imgur.com/a/9zmYETV") -> https://imgur.com/a/9zmYETV | D93: =IFERROR(__xludf.DUMMYFUNCTION("""COMPUTED_VALUE"""),"-") -> -
A94: =IFERROR(__xludf.DUMMYFUNCTION("""COMPUTED_VALUE"""),"Haunter") -> Haunter | B94: =IFERROR(__xludf.DUMMYFUNCTION("""COMPUTED_VALUE"""),"-") -> - | C94: =IFERROR(__xludf.DUMMYFUNCTION("""COMPUTED_VALUE"""),"https://imgur.com/a/WeJwwK9") -> https://imgur.com/a/WeJwwK9 | D94: =IFERROR(__xludf.DUMMYFUNCTION("""COMPUTED_VALUE"""),"-") -> -
A95: =IFERROR(__xludf.DUMMYFUNCTION("""COMPUTED_VALUE"""),"Gengar") -> Gengar | B95: =IFERROR(__xludf.DUMMYFUNCTION("""COMPUTED_VALUE"""),"https://imgur.com/a/8auiFkj") -> https://imgur.com/a/8auiFkj | C95: =IFERROR(__xludf.DUMMYFUNCTION("""COMPUTED_VALUE"""),"Não tem") -> Não tem | D95: =IFERROR(__xludf.DUMMYFUNCTION("""COMPUTED_VALUE"""),"https://imgur.com/a/wFcUcVR") -> https://imgur.com/a/wFcUcVR
A96: =IFERROR(__xludf.DUMMYFUNCTION("""COMPUTED_VALUE"""),"Onix") -> Onix | B96: =IFERROR(__xludf.DUMMYFUNCTION("""COMPUTED_VALUE"""),"-") -> - | C96: =IFERROR(__xludf.DUMMYFUNCTION("""COMPUTED_VALUE"""),"https://imgur.com/a/XRtE7Ns") -> https://imgur.com/a/XRtE7Ns | D96: =IFERROR(__xludf.DUMMYFUNCTION("""COMPUTED_VALUE"""),"-") -> -
A97: =IFERROR(__xludf.DUMMYFUNCTION("""COMPUTED_VALUE"""),"Drowzee") -> Drowzee | B97: =IFERROR(__xludf.DUMMYFUNCTION("""COMPUTED_VALUE"""),"-") -> - | C97: =IFERROR(__xludf.DUMMYFUNCTION("""COMPUTED_VALUE"""),"https://imgur.com/a/H8LgV6N") -> https://imgur.com/a/H8LgV6N | D97: =IFERROR(__xludf.DUMMYFUNCTION("""COMPUTED_VALUE"""),"-") -> -
A98: =IFERROR(__xludf.DUMMYFUNCTION("""COMPUTED_VALUE"""),"Hypno") -> Hypno | B98: =IFERROR(__xludf.DUMMYFUNCTION("""COMPUTED_VALUE"""),"-") -> - | C98: =IFERROR(__xludf.DUMMYFUNCTION("""COMPUTED_VALUE"""),"https://imgur.com/a/c500gBU") -> https://imgur.com/a/c500gBU | D98: =IFERROR(__xludf.DUMMYFUNCTION("""COMPUTED_VALUE"""),"-") -> -
A99: =IFERROR(__xludf.DUMMYFUNCTION("""COMPUTED_VALUE"""),"Krabby") -> Krabby | B99: =IFERROR(__xludf.DUMMYFUNCTION("""COMPUTED_VALUE"""),"-") -> - | C99: =IFERROR(__xludf.DUMMYFUNCTION("""COMPUTED_VALUE"""),"https://imgur.com/a/9CsLe4f") -> https://imgur.com/a/9CsLe4f | D99: =IFERROR(__xludf.DUMMYFUNCTION("""COMPUTED_VALUE"""),"-") -> -
A100: =IFERROR(__xludf.DUMMYFUNCTION("""COMPUTED_VALUE"""),"Kingler") -> Kingler | B100: =IFERROR(__xludf.DUMMYFUNCTION("""COMPUTED_VALUE"""),"-") -> - | C100: =IFERROR(__xludf.DUMMYFUNCTION("""COMPUTED_VALUE"""),"https://imgur.com/a/RJTlGC2") -> https://imgur.com/a/RJTlGC2 | D100: =IFERROR(__xludf.DUMMYFUNCTION("""COMPUTED_VALUE"""),"-") -> -
...

Sheet Search
A1: ITEM | C1: ="Pokemons que dropam '" & A2 & "'" -> Pokemons que dropam 'bottle of poison' | D1: Como usar - Pesquise o Item na célula A2 (clique no dropdown e digite o nome) - Os pokemons aparecerão na coluna C - Por uma limitação do Google, se tiver muita gente (90+ pessoas) usando a planilha, o campo de pesquisa não pode ser editado. Se isso acontecer, use essa planilha: Copy of Pokedex pública - Pokemon alliance (By Mts Vitor)
A2: bottle of poison | C2: =IFERROR(__xludf.DUMMYFUNCTION("FILTER(Drops!A:A, (Drops!B:B=A2) + (Drops!C:C=A2) + (Drops!D:D=A2) + (Drops!E:E=A2) + (Drops!F:F=A2) + (Drops!G:G=A2) + (Drops!H:H=A2) + (Drops!I:I=A2) + (Drops!J:J=A2) + (Drops!K:K=A2))"),"Bulbasaur") -> Bulbasaur
C3: =IFERROR(__xludf.DUMMYFUNCTION("""COMPUTED_VALUE"""),"Shiny Bulbasaur") -> Shiny Bulbasaur
C4: =IFERROR(__xludf.DUMMYFUNCTION("""COMPUTED_VALUE"""),"Ivysaur") -> Ivysaur
C5: =IFERROR(__xludf.DUMMYFUNCTION("""COMPUTED_VALUE"""),"Shiny Ivysaur") -> Shiny Ivysaur
C6: =IFERROR(__xludf.DUMMYFUNCTION("""COMPUTED_VALUE"""),"Venusaur") -> Venusaur
C7: =IFERROR(__xludf.DUMMYFUNCTION("""COMPUTED_VALUE"""),"Shiny Venusaur") -> Shiny Venusaur
C8: =IFERROR(__xludf.DUMMYFUNCTION("""COMPUTED_VALUE"""),"Weedle") -> Weedle
C9: =IFERROR(__xludf.DUMMYFUNCTION("""COMPUTED_VALUE"""),"Shiny Weedle") -> Shiny Weedle
C10: =IFERROR(__xludf.DUMMYFUNCTION("""COMPUTED_VALUE"""),"Kakuna") -> Kakuna
C11: =IFERROR(__xludf.DUMMYFUNCTION("""COMPUTED_VALUE"""),"Shiny Kakuna") -> Shiny Kakuna
C12: =IFERROR(__xludf.DUMMYFUNCTION("""COMPUTED_VALUE"""),"Beedrill") -> Beedrill
C13: =IFERROR(__xludf.DUMMYFUNCTION("""COMPUTED_VALUE"""),"Shiny Beedrill") -> Shiny Beedrill
C14: =IFERROR(__xludf.DUMMYFUNCTION("""COMPUTED_VALUE"""),"Ekans") -> Ekans
C15: =IFERROR(__xludf.DUMMYFUNCTION("""COMPUTED_VALUE"""),"Shiny Ekans") -> Shiny Ekans
C16: =IFERROR(__xludf.DUMMYFUNCTION("""COMPUTED_VALUE"""),"Arbok") -> Arbok
C17: =IFERROR(__xludf.DUMMYFUNCTION("""COMPUTED_VALUE"""),"Shiny Arbok") -> Shiny Arbok
C18: =IFERROR(__xludf.DUMMYFUNCTION("""COMPUTED_VALUE"""),"Nidoran female") -> Nidoran female
C19: =IFERROR(__xludf.DUMMYFUNCTION("""COMPUTED_VALUE"""),"Shiny Nidoran female") -> Shiny Nidoran female
C20: =IFERROR(__xludf.DUMMYFUNCTION("""COMPUTED_VALUE"""),"Nidorina") -> Nidorina
C21: =IFERROR(__xludf.DUMMYFUNCTION("""COMPUTED_VALUE"""),"Shiny Nidorina") -> Shiny Nidorina
C22: =IFERROR(__xludf.DUMMYFUNCTION("""COMPUTED_VALUE"""),"Nidoqueen") -> Nidoqueen
C23: =IFERROR(__xludf.DUMMYFUNCTION("""COMPUTED_VALUE"""),"Shiny Nidoqueen") -> Shiny Nidoqueen
C24: =IFERROR(__xludf.DUMMYFUNCTION("""COMPUTED_VALUE"""),"Nidoran Male") -> Nidoran Male
C25: =IFERROR(__xludf.DUMMYFUNCTION("""COMPUTED_VALUE"""),"Shiny Nidoran Male") -> Shiny Nidoran Male
C26: =IFERROR(__xludf.DUMMYFUNCTION("""COMPUTED_VALUE"""),"Nidorino") -> Nidorino
C27: =IFERROR(__xludf.DUMMYFUNCTION("""COMPUTED_VALUE"""),"Shiny Nidorino") -> Shiny Nidorino
C28: =IFERROR(__xludf.DUMMYFUNCTION("""COMPUTED_VALUE"""),"Nidoking") -> Nidoking
C29: =IFERROR(__xludf.DUMMYFUNCTION("""COMPUTED_VALUE"""),"Shiny Nidoking") -> Shiny Nidoking
C30: =IFERROR(__xludf.DUMMYFUNCTION("""COMPUTED_VALUE"""),"Zubat") -> Zubat
C31: =IFERROR(__xludf.DUMMYFUNCTION("""COMPUTED_VALUE"""),"Shiny Zubat") -> Shiny Zubat
C32: =IFERROR(__xludf.DUMMYFUNCTION("""COMPUTED_VALUE"""),"Golbat") -> Golbat
C33: =IFERROR(__xludf.DUMMYFUNCTION("""COMPUTED_VALUE"""),"Shiny Golbat") -> Shiny Golbat
C34: =IFERROR(__xludf.DUMMYFUNCTION("""COMPUTED_VALUE"""),"Oddish") -> Oddish
C35: =IFERROR(__xludf.DUMMYFUNCTION("""COMPUTED_VALUE"""),"Shiny Oddish") -> Shiny Oddish
C36: =IFERROR(__xludf.DUMMYFUNCTION("""COMPUTED_VALUE"""),"Gloom") -> Gloom
C37: =IFERROR(__xludf.DUMMYFUNCTION("""COMPUTED_VALUE"""),"Shiny Gloom") -> Shiny Gloom
C38: =IFERROR(__xludf.DUMMYFUNCTION("""COMPUTED_VALUE"""),"Vileplume") -> Vileplume
C39: =IFERROR(__xludf.DUMMYFUNCTION("""COMPUTED_VALUE"""),"Shiny Vileplume") -> Shiny Vileplume
C40: =IFERROR(__xludf.DUMMYFUNCTION("""COMPUTED_VALUE"""),"Venonat") -> Venonat
C41: =IFERROR(__xludf.DUMMYFUNCTION("""COMPUTED_VALUE"""),"Shiny Venonat") -> Shiny Venonat
C42: =IFERROR(__xludf.DUMMYFUNCTION("""COMPUTED_VALUE"""),"Venomoth") -> Venomoth
C43: =IFERROR(__xludf.DUMMYFUNCTION("""COMPUTED_VALUE"""),"Shiny Venomoth") -> Shiny Venomoth
C44: =IFERROR(__xludf.DUMMYFUNCTION("""COMPUTED_VALUE"""),"Bellsprout") -> Bellsprout
C45: =IFERROR(__xludf.DUMMYFUNCTION("""COMPUTED_VALUE"""),"Shiny Bellsprout") -> Shiny Bellsprout
C46: =IFERROR(__xludf.DUMMYFUNCTION("""COMPUTED_VALUE"""),"Weepinbell") -> Weepinbell
C47: =IFERROR(__xludf.DUMMYFUNCTION("""COMPUTED_VALUE"""),"Shiny Weepinbell") -> Shiny Weepinbell
C48: =IFERROR(__xludf.DUMMYFUNCTION("""COMPUTED_VALUE"""),"Victreebel") -> Victreebel
C49: =IFERROR(__xludf.DUMMYFUNCTION("""COMPUTED_VALUE"""),"Shiny Victreebel") -> Shiny Victreebel
C50: =IFERROR(__xludf.DUMMYFUNCTION("""COMPUTED_VALUE"""),"Tentacool") -> Tentacool
C51: =IFERROR(__xludf.DUMMYFUNCTION("""COMPUTED_VALUE"""),"Shiny Tentacool") -> Shiny Tentacool
C52: =IFERROR(__xludf.DUMMYFUNCTION("""COMPUTED_VALUE"""),"Tentacruel") -> Tentacruel
C53: =IFERROR(__xludf.DUMMYFUNCTION("""COMPUTED_VALUE"""),"Shiny Tentacruel") -> Shiny Tentacruel
C54: =IFERROR(__xludf.DUMMYFUNCTION("""COMPUTED_VALUE"""),"Grimer") -> Grimer
C55: =IFERROR(__xludf.DUMMYFUNCTION("""COMPUTED_VALUE"""),"Shiny Grimer") -> Shiny Grimer
C56: =IFERROR(__xludf.DUMMYFUNCTION("""COMPUTED_VALUE"""),"Muk") -> Muk
C57: =IFERROR(__xludf.DUMMYFUNCTION("""COMPUTED_VALUE"""),"Shiny Muk") -> Shiny Muk
C58: =IFERROR(__xludf.DUMMYFUNCTION("""COMPUTED_VALUE"""),"Gastly") -> Gastly
C59: =IFERROR(__xludf.DUMMYFUNCTION("""COMPUTED_VALUE"""),"Shiny Gastly") -> Shiny Gastly
C60: =IFERROR(__xludf.DUMMYFUNCTION("""COMPUTED_VALUE"""),"Haunter") -> Haunter
C61: =IFERROR(__xludf.DUMMYFUNCTION("""COMPUTED_VALUE"""),"Shiny Haunter") -> Shiny Haunter
C62: =IFERROR(__xludf.DUMMYFUNCTION("""COMPUTED_VALUE"""),"Gengar") -> Gengar
C63: =IFERROR(__xludf.DUMMYFUNCTION("""COMPUTED_VALUE"""),"Shiny Gengar") -> Shiny Gengar
C64: =IFERROR(__xludf.DUMMYFUNCTION("""COMPUTED_VALUE"""),"Koffing") -> Koffing
C65: =IFERROR(__xludf.DUMMYFUNCTION("""COMPUTED_VALUE"""),"Shiny Koffing") -> Shiny Koffing
C66: =IFERROR(__xludf.DUMMYFUNCTION("""COMPUTED_VALUE"""),"Weezing") -> Weezing
C67: =IFERROR(__xludf.DUMMYFUNCTION("""COMPUTED_VALUE"""),"Shiny Weezing") -> Shiny Weezing
C68: =IFERROR(__xludf.DUMMYFUNCTION("""COMPUTED_VALUE"""),"Spinarak") -> Spinarak
C69: =IFERROR(__xludf.DUMMYFUNCTION("""COMPUTED_VALUE"""),"Shiny Spinarak") -> Shiny Spinarak
C70: =IFERROR(__xludf.DUMMYFUNCTION("""COMPUTED_VALUE"""),"Ariados") -> Ariados
C71: =IFERROR(__xludf.DUMMYFUNCTION("""COMPUTED_VALUE"""),"Crobat") -> Crobat
C72: =IFERROR(__xludf.DUMMYFUNCTION("""COMPUTED_VALUE"""),"Shiny Crobat") -> Shiny Crobat
C73: =IFERROR(__xludf.DUMMYFUNCTION("""COMPUTED_VALUE"""),"Qwilfish") -> Qwilfish
C74: =IFERROR(__xludf.DUMMYFUNCTION("""COMPUTED_VALUE"""),"Shiny Qwilfish") -> Shiny Qwilfish
C75: =IFERROR(__xludf.DUMMYFUNCTION("""COMPUTED_VALUE"""),"Toxicroak") -> Toxicroak
C76: =IFERROR(__xludf.DUMMYFUNCTION("""COMPUTED_VALUE"""),"Shiny Toxicroak") -> Shiny Toxicroak
C77: =IFERROR(__xludf.DUMMYFUNCTION("""COMPUTED_VALUE"""),"Scolipede") -> Scolipede
C78: =IFERROR(__xludf.DUMMYFUNCTION("""COMPUTED_VALUE"""),"Mega Scolipede") -> Mega Scolipede
C79: =IFERROR(__xludf.DUMMYFUNCTION("""COMPUTED_VALUE"""),"Trubbish") -> Trubbish
C80: =IFERROR(__xludf.DUMMYFUNCTION("""COMPUTED_VALUE"""),"Shiny Trubbish") -> Shiny Trubbish

Sheet PokeTalents
A1: a | D1: Quantidade | E1: Tipo | F1: # | H1: Buff
A2: fighter hawk | B2: Machop | C2: =IF(A2<>"",A2&" ("&B2&")", "") -> fighter hawk (Machop) | D2: 25 | E2: Character | F2: 1 | G2: =IF(E2<>"", E2 & " #" & F2, "") -> Character #1 | H2: Gives all your Pokemon 1% critical chance. | I2: 1 - Gives all your Pokemon 1% critical chance.
A3: rock fist | B3: Geodude | C3: =IF(A3<>"",A3&" ("&B3&")", "") -> rock fist (Geodude) | D3: 25 | E3: Character | F3: 1 | G3: =IF(E3<>"", E3 & " #" & F3, "") -> Character #1 | H3: Gives all your Pokemon 1% critical chance. | I3: 1 - Gives all your Pokemon 1% critical chance.
A4: bear claw | B4: Ursaring | C4: =IF(A4<>"",A4&" ("&B4&")", "") -> bear claw (Ursaring) | D4: 1500 | E4: Character | F4: 2 | G4: =IF(E4<>"", E4 & " #" & F4, "") -> Character #2 | H4: Accelerates the regeneration of 1 second cooldown of the spells of Pokemon stored in the bag (Pokemon that remain inside the Poke Balls). | I4: 2 - Accelerates the regeneration of 1 second cooldown of the spells of Pokemon stored in the bag (Pokemon that remain inside the Poke Balls).
A5: cow tail | B5: Miltank | C5: =IF(A5<>"",A5&" ("&B5&")", "") -> cow tail (Miltank) | D5: 1100 | E5: Character | F5: 2 | G5: =IF(E5<>"", E5 & " #" & F5, "") -> Character #2 | H5: Accelerates the regeneration of 1 second cooldown of the spells of Pokemon stored in the bag (Pokemon that remain inside the Poke Balls). | I5: 2 - Accelerates the regeneration of 1 second cooldown of the spells of Pokemon stored in the bag (Pokemon that remain inside the Poke Balls).
A6: earth badge | B6: Viridian Gym | C6: =IF(A6<>"",A6&" ("&B6&")", "") -> earth badge (Viridian Gym) | D6: 1 | E6: Character | F6: 2 | G6: =IF(E6<>"", E6 & " #" & F6, "") -> Character #2 | H6: Accelerates the regeneration of 1 second cooldown of the spells of Pokemon stored in the bag (Pokemon that remain inside the Poke Balls). | I6: 2 - Accelerates the regeneration of 1 second cooldown of the spells of Pokemon stored in the bag (Pokemon that remain inside the Poke Balls).
A7: heart stone | C7: =IF(A7<>"",A7&" ("&B7&")", "") -> heart stone () | D7: 1000 | E7: Character | F7: 2 | G7: =IF(E7<>"", E7 & " #" & F7, "") -> Character #2 | H7: Accelerates the regeneration of 1 second cooldown of the spells of Pokemon stored in the bag (Pokemon that remain inside the Poke Balls). | I7: 2 - Accelerates the regeneration of 1 second cooldown of the spells of Pokemon stored in the bag (Pokemon that remain inside the Poke Balls).
A8: pink wings | B8: Clefable | C8: =IF(A8<>"",A8&" ("&B8&")", "") -> pink wings (Clefable) | D8: 450 | E8: Character | F8: 2 | G8: =IF(E8<>"", E8 & " #" & F8, "") -> Character #2 | H8: Accelerates the regeneration of 1 second cooldown of the spells of Pokemon stored in the bag (Pokemon that remain inside the Poke Balls). | I8: 2 - Accelerates the regeneration of 1 second cooldown of the spells of Pokemon stored in the bag (Pokemon that remain inside the Poke Balls).
A9: snorlax paw | B9: Snorlax | C9: =IF(A9<>"",A9&" ("&B9&")", "") -> snorlax paw (Snorlax) | D9: 1500 | E9: Character | F9: 2 | G9: =IF(E9<>"", E9 & " #" & F9, "") -> Character #2 | H9: Accelerates the regeneration of 1 second cooldown of the spells of Pokemon stored in the bag (Pokemon that remain inside the Poke Balls). | I9: 2 - Accelerates the regeneration of 1 second cooldown of the spells of Pokemon stored in the bag (Pokemon that remain inside the Poke Balls).
A10: wigglytuff ear | B10: Wigglytuff | C10: =IF(A10<>"",A10&" ("&B10&")", "") -> wigglytuff ear (Wigglytuff) | D10: 450 | E10: Character | F10: 2 | G10: =IF(E10<>"", E10 & " #" & F10, "") -> Character #2 | H10: Accelerates the regeneration of 1 second cooldown of the spells of Pokemon stored in the bag (Pokemon that remain inside the Poke Balls). | I10: 2 - Accelerates the regeneration of 1 second cooldown of the spells of Pokemon stored in the bag (Pokemon that remain inside the Poke Balls).
C11: =IF(A11<>"",A11&" ("&B11&")", "") | G11: =IF(E11<>"", E11 & " #" & F11, "")
C12: =IF(A12<>"",A12&" ("&B12&")", "") | G12: =IF(E12<>"", E12 & " #" & F12, "")
A13: volcano badge | B13: Cinnabar Gym | C13: =IF(A13<>"",A13&" ("&B13&")", "") -> volcano badge (Cinnabar Gym) | D13: 1 | E13: Character | F13: 3 | G13: =IF(E13<>"", E13 & " #" & F13, "") -> Character #3 | H13: Accelerates the regeneration of 1 second cooldown of the spells of Pokemon stored in the bag (Pokemon that remain inside the Poke Balls). | I13: 3 - Accelerates the regeneration of 1 second cooldown of the spells of Pokemon stored in the bag (Pokemon that remain inside the Poke Balls).
A14: fire wing | B14: Charizard | C14: =IF(A14<>"",A14&" ("&B14&")", "") -> fire wing (Charizard) | D14: 1500 | E14: Character | F14: 3 | G14: =IF(E14<>"", E14 & " #" & F14, "") -> Character #3 | H14: Accelerates the regeneration of 1 second cooldown of the spells of Pokemon stored in the bag (Pokemon that remain inside the Poke Balls). | I14: 3 - Accelerates the regeneration of 1 second cooldown of the spells of Pokemon stored in the bag (Pokemon that remain inside the Poke Balls).
A15: magma foot | B15: Magmar | C15: =IF(A15<>"",A15&" ("&B15&")", "") -> magma foot (Magmar) | D15: 1500 | E15: Character | F15: 3 | G15: =IF(E15<>"", E15 & " #" & F15, "") -> Character #3 | H15: Accelerates the regeneration of 1 second cooldown of the spells of Pokemon stored in the bag (Pokemon that remain inside the Poke Balls). | I15: 3 - Accelerates the regeneration of 1 second cooldown of the spells of Pokemon stored in the bag (Pokemon that remain inside the Poke Balls).
A16: giant piece of fur | B16: Arcanine | C16: =IF(A16<>"",A16&" ("&B16&")", "") -> giant piece of fur (Arcanine) | D16: 1100 | E16: Character | F16: 3 | G16: =IF(E16<>"", E16 & " #" & F16, "") -> Character #3 | H16: Accelerates the regeneration of 1 second cooldown of the spells of Pokemon stored in the bag (Pokemon that remain inside the Poke Balls). | I16: 3 - Accelerates the regeneration of 1 second cooldown of the spells of Pokemon stored in the bag (Pokemon that remain inside the Poke Balls).
A17: magma shell | B17: Magcargo | C17: =IF(A17<>"",A17&" ("&B17&")", "") -> magma shell (Magcargo) | D17: 900 | E17: Character | F17: 3 | G17: =IF(E17<>"", E17 & " #" & F17, "") -> Character #3 | H17: Accelerates the regeneration of 1 second cooldown of the spells of Pokemon stored in the bag (Pokemon that remain inside the Poke Balls). | I17: 3 - Accelerates the regeneration of 1 second cooldown of the spells of Pokemon stored in the bag (Pokemon that remain inside the Poke Balls).
A18: fire stone | B18: Verificar aba de drops | C18: =IF(A18<>"",A18&" ("&B18&")", "") -> fire stone (Verificar aba de drops) | D18: 1000 | E18: Character | F18: 3 | G18: =IF(E18<>"", E18 & " #" & F18, "") -> Character #3 | H18: Accelerates the regeneration of 1 second cooldown of the spells of Pokemon stored in the bag (Pokemon that remain inside the Poke Balls). | I18: 3 - Accelerates the regeneration of 1 second cooldown of the spells of Pokemon stored in the bag (Pokemon that remain inside the Poke Balls).
C19: =IF(A19<>"",A19&" ("&B19&")", "") | G19: =IF(E19<>"", E19 & " #" & F19, "")
A20: boulder badge | B20: Pewter Gym | C20: =IF(A20<>"",A20&" ("&B20&")", "") -> boulder badge (Pewter Gym) | D20: 1 | E20: Character | F20: 4 | G20: =IF(E20<>"", E20 & " #" & F20, "") -> Character #4 | H20: Accelerates the regeneration of 1 second cooldown of the spells of Pokemon stored in the bag (Pokemon that remain inside the Poke Balls). | I20: 4 - Accelerates the regeneration of 1 second cooldown of the spells of Pokemon stored in the bag (Pokemon that remain inside the Poke Balls).
A21: stone rocks | B21: Golem | C21: =IF(A21<>"",A21&" ("&B21&")", "") -> stone rocks (Golem) | D21: 1500 | E21: Character | F21: 4 | G21: =IF(E21<>"", E21 & " #" & F21, "") -> Character #4 | H21: Accelerates the regeneration of 1 second cooldown of the spells of Pokemon stored in the bag (Pokemon that remain inside the Poke Balls). | I21: 4 - Accelerates the regeneration of 1 second cooldown of the spells of Pokemon stored in the bag (Pokemon that remain inside the Poke Balls).
A22: horn drill | B22: Rhydon | C22: =IF(A22<>"",A22&" ("&B22&")", "") -> horn drill (Rhydon) | D22: 1500 | E22: Character | F22: 4 | G22: =IF(E22<>"", E22 & " #" & F22, "") -> Character #4 | H22: Accelerates the regeneration of 1 second cooldown of the spells of Pokemon stored in the bag (Pokemon that remain inside the Poke Balls). | I22: 4 - Accelerates the regeneration of 1 second cooldown of the spells of Pokemon stored in the bag (Pokemon that remain inside the Poke Balls).
A23: bone | B23: Marowak | C23: =IF(A23<>"",A23&" ("&B23&")", "") -> bone (Marowak) | D23: 1100 | E23: Character | F23: 4 | G23: =IF(E23<>"", E23 & " #" & F23, "") -> Character #4 | H23: Accelerates the regeneration of 1 second cooldown of the spells of Pokemon stored in the bag (Pokemon that remain inside the Poke Balls). | I23: 4 - Accelerates the regeneration of 1 second cooldown of the spells of Pokemon stored in the bag (Pokemon that remain inside the Poke Balls).
A24: steelix tail | B24: Steelix | C24: =IF(A24<>"",A24&" ("&B24&")", "") -> steelix tail (Steelix) | D24: 900 | E24: Character | F24: 4 | G24: =IF(E24<>"", E24 & " #" & F24, "") -> Character #4 | H24: Accelerates the regeneration of 1 second cooldown of the spells of Pokemon stored in the bag (Pokemon that remain inside the Poke Balls). | I24: 4 - Accelerates the regeneration of 1 second cooldown of the spells of Pokemon stored in the bag (Pokemon that remain inside the Poke Balls).
A25: rock stone | B25: Verificar aba de drops | C25: =IF(A25<>"",A25&" ("&B25&")", "") -> rock stone (Verificar aba de drops) | D25: 500 | E25: Character | F25: 4 | G25: =IF(E25<>"", E25 & " #" & F25, "") -> Character #4 | H25: Accelerates the regeneration of 1 second cooldown of the spells of Pokemon stored in the bag (Pokemon that remain inside the Poke Balls). | I25: 4 - Accelerates the regeneration of 1 second cooldown of the spells of Pokemon stored in the bag (Pokemon that remain inside the Poke Balls).
A26: earth stone | B26: Verificar aba de drops | C26: =IF(A26<>"",A26&" ("&B26&")", "") -> earth stone (Verificar aba de drops) | D26: 500 | E26: Character | F26: 4 | G26: =IF(E26<>"", E26 & " #" & F26, "") -> Character #4 | H26: Accelerates the regeneration of 1 second cooldown of the spells of Pokemon stored in the bag (Pokemon that remain inside the Poke Balls). | I26: 4 - Accelerates the regeneration of 1 second cooldown of the spells of Pokemon stored in the bag (Pokemon that remain inside the Poke Balls).
C27: =IF(A27<>"",A27&" ("&B27&")", "") | G27: =IF(E27<>"", E27 & " #" & F27, "")
A28: cascade badge | B28: Cerulean Gym | C28: =IF(A28<>"",A28&" ("&B28&")", "") -> cascade badge (Cerulean Gym) | D28: 1 | E28: Character | F28: 5 | G28: =IF(E28<>"", E28 & " #" & F28, "") -> Character #5 | H28: Accelerates the regeneration of 1 second cooldown of the spells of Pokemon stored in the bag (Pokemon that remain inside the Poke Balls). | I28: 5 - Accelerates the regeneration of 1 second cooldown of the spells of Pokemon stored in the bag (Pokemon that remain inside the Poke Balls).
A29: lapras fin | B29: Lapras | C29: =IF(A29<>"",A29&" ("&B29&")", "") -> lapras fin (Lapras) | D29: 900 | E29: Character | F29: 5 | G29: =IF(E29<>"", E29 & " #" & F29, "") -> Character #5 | H29: Accelerates the regeneration of 1 second cooldown of the spells of Pokemon stored in the bag (Pokemon that remain inside the Poke Balls). | I29: 5 - Accelerates the regeneration of 1 second cooldown of the spells of Pokemon stored in the bag (Pokemon that remain inside the Poke Balls).
A30: gyarados tail | B30: Gyarados | C30: =IF(A30<>"",A30&" ("&B30&")", "") -> gyarados tail (Gyarados) | D30: 1500 | E30: Character | F30: 5 | G30: =IF(E30<>"", E30 & " #" & F30, "") -> Character #5 | H30: Accelerates the regeneration of 1 second cooldown of the spells of Pokemon stored in the bag (Pokemon that remain inside the Poke Balls). | I30: 5 - Accelerates the regeneration of 1 second cooldown of the spells of Pokemon stored in the bag (Pokemon that remain inside the Poke Balls).
A31: aquatic tail | B31: Vaporeon | C31: =IF(A31<>"",A31&" ("&B31&")", "") -> aquatic tail (Vaporeon) | D31: 1100 | E31: Character | F31: 5 | G31: =IF(E31<>"", E31 & " #" & F31, "") -> Character #5 | H31: Accelerates the regeneration of 1 second cooldown of the spells of Pokemon stored in the bag (Pokemon that remain inside the Poke Balls). | I31: 5 - Accelerates the regeneration of 1 second cooldown of the spells of Pokemon stored in the bag (Pokemon that remain inside the Poke Balls).
A32: water cannon | B32: Blastoise | C32: =IF(A32<>"",A32&" ("&B32&")", "") -> water cannon (Blastoise) | D32: 1500 | E32: Character | F32: 5 | G32: =IF(E32<>"", E32 & " #" & F32, "") -> Character #5 | H32: Accelerates the regeneration of 1 second cooldown of the spells of Pokemon stored in the bag (Pokemon that remain inside the Poke Balls). | I32: 5 - Accelerates the regeneration of 1 second cooldown of the spells of Pokemon stored in the bag (Pokemon that remain inside the Poke Balls).
A33: water stone | B33: Verificar aba de drops | C33: =IF(A33<>"",A33&" ("&B33&")", "") -> water stone (Verificar aba de drops) | D33: 500 | E33: Character | F33: 5 | G33: =IF(E33<>"", E33 & " #" & F33, "") -> Character #5 | H33: Accelerates the regeneration of 1 second cooldown of the spells of Pokemon stored in the bag (Pokemon that remain inside the Poke Balls). | I33: 5 - Accelerates the regeneration of 1 second cooldown of the spells of Pokemon stored in the bag (Pokemon that remain inside the Poke Balls).
A34: ice stone | B34: Verificar aba de drops | C34: =IF(A34<>"",A34&" ("&B34&")", "") -> ice stone (Verificar aba de drops) | D34: 500 | E34: Character | F34: 5 | G34: =IF(E34<>"", E34 & " #" & F34, "") -> Character #5 | H34: Accelerates the regeneration of 1 second cooldown of the spells of Pokemon stored in the bag (Pokemon that remain inside the Poke Balls). | I34: 5 - Accelerates the regeneration of 1 second cooldown of the spells of Pokemon stored in the bag (Pokemon that remain inside the Poke Balls).
C35: =IF(A35<>"",A35&" ("&B35&")", "") | G35: =IF(E35<>"", E35 & " #" & F35, "")
A36: thunder badge | B36: Vermilion Gym | C36: =IF(A36<>"",A36&" ("&B36&")", "") -> thunder badge (Vermilion Gym) | D36: 1 | E36: Character | F36: 6 | G36: =IF(E36<>"", E36 & " #" & F36, "") -> Character #6 | H36: Accelerates the regeneration of 1 second cooldown of the spells of Pokemon stored in the bag (Pokemon that remain inside the Poke Balls). | I36: 6 - Accelerates the regeneration of 1 second cooldown of the spells of Pokemon stored in the bag (Pokemon that remain inside the Poke Balls).
A37: electric sheep tail | B37: Ampharos | C37: =IF(A37<>"",A37&" ("&B37&")", "") -> electric sheep tail (Ampharos) | D37: 1100 | E37: Character | F37: 6 | G37: =IF(E37<>"", E37 & " #" & F37, "") -> Character #6 | H37: Accelerates the regeneration of 1 second cooldown of the spells of Pokemon stored in the bag (Pokemon that remain inside the Poke Balls). | I37: 6 - Accelerates the regeneration of 1 second cooldown of the spells of Pokemon stored in the bag (Pokemon that remain inside the Poke Balls).
A38: electric tail | B38: Electabuzz | C38: =IF(A38<>"",A38&" ("&B38&")", "") -> electric tail (Electabuzz) | D38: 1500 | E38: Character | F38: 6 | G38: =IF(E38<>"", E38 & " #" & F38, "") -> Character #6 | H38: Accelerates the regeneration of 1 second cooldown of the spells of Pokemon stored in the bag (Pokemon that remain inside the Poke Balls). | I38: 6 - Accelerates the regeneration of 1 second cooldown of the spells of Pokemon stored in the bag (Pokemon that remain inside the Poke Balls).
A39: electric ear | B39: Raichu | C39: =IF(A39<>"",A39&" ("&B39&")", "") -> electric ear (Raichu) | D39: 1500 | E39: Character | F39: 6 | G39: =IF(E39<>"", E39 & " #" & F39, "") -> Character #6 | H39: Accelerates the regeneration of 1 second cooldown of the spells of Pokemon stored in the bag (Pokemon that remain inside the Poke Balls). | I39: 6 - Accelerates the regeneration of 1 second cooldown of the spells of Pokemon stored in the bag (Pokemon that remain inside the Poke Balls).
A40: electric collar | B40: Jolteon | C40: =IF(A40<>"",A40&" ("&B40&")", "") -> electric collar (Jolteon) | D40: 900 | E40: Character | F40: 6 | G40: =IF(E40<>"", E40 & " #" & F40, "") -> Character #6 | H40: Accelerates the regeneration of 1 second cooldown of the spells of Pokemon stored in the bag (Pokemon that remain inside the Poke Balls). | I40: 6 - Accelerates the regeneration of 1 second cooldown of the spells of Pokemon stored in the bag (Pokemon that remain inside the Poke Balls).
A41: thunder stone | B41: Verificar aba de drops | C41: =IF(A41<>"",A41&" ("&B41&")", "") -> thunder stone (Verificar aba de drops) | D41: 1000 | E41: Character | F41: 6 | G41: =IF(E41<>"", E41 & " #" & F41, "") -> Character #6 | H41: Accelerates the regeneration of 1 second cooldown of the spells of Pokemon stored in the bag (Pokemon that remain inside the Poke Balls). | I41: 6 - Accelerates the regeneration of 1 second cooldown of the spells of Pokemon stored in the bag (Pokemon that remain inside the Poke Balls).
C42: =IF(A42<>"",A42&" ("&B42&")", "") | G42: =IF(E42<>"", E42 & " #" & F42, "")
A43: rainbow badge | B43: Celadon Gym | C43: =IF(A43<>"",A43&" ("&B43&")", "") -> rainbow badge (Celadon Gym) | D43: 1 | E43: Character | F43: 7 | G43: =IF(E43<>"", E43 & " #" & F43, "") -> Character #7 | H43: Accelerates the regeneration of 1 second cooldown of the spells of Pokemon stored in the bag (Pokemon that remain inside the Poke Balls). | I43: 7 - Accelerates the regeneration of 1 second cooldown of the spells of Pokemon stored in the bag (Pokemon that remain inside the Poke Balls).
A44: red petal | B44: Venusaur | C44: =IF(A44<>"",A44&" ("&B44&")", "") -> red petal (Venusaur) | D44: 1500 | E44: Character | F44: 7 | G44: =IF(E44<>"", E44 & " #" & F44, "") -> Character #7 | H44: Accelerates the regeneration of 1 second cooldown of the spells of Pokemon stored in the bag (Pokemon that remain inside the Poke Balls). | I44: 7 - Accelerates the regeneration of 1 second cooldown of the spells of Pokemon stored in the bag (Pokemon that remain inside the Poke Balls).
A45: big petal | B45: Meganium | C45: =IF(A45<>"",A45&" ("&B45&")", "") -> big petal (Meganium) | D45: 1500 | E45: Character | F45: 7 | G45: =IF(E45<>"", E45 & " #" & F45, "") -> Character #7 | H45: Accelerates the regeneration of 1 second cooldown of the spells of Pokemon stored in the bag (Pokemon that remain inside the Poke Balls). | I45: 7 - Accelerates the regeneration of 1 second cooldown of the spells of Pokemon stored in the bag (Pokemon that remain inside the Poke Balls).
A46: coconut leaves | B46: Exeggutor | C46: =IF(A46<>"",A46&" ("&B46&")", "") -> coconut leaves (Exeggutor) | D46: 1100 | E46: Character | F46: 7 | G46: =IF(E46<>"", E46 & " #" & F46, "") -> Character #7 | H46: Accelerates the regeneration of 1 second cooldown of the spells of Pokemon stored in the bag (Pokemon that remain inside the Poke Balls). | I46: 7 - Accelerates the regeneration of 1 second cooldown of the spells of Pokemon stored in the bag (Pokemon that remain inside the Poke Balls).
A47: vine hair | B47: Tangela | C47: =IF(A47<>"",A47&" ("&B47&")", "") -> vine hair (Tangela) | D47: 900 | E47: Character | F47: 7 | G47: =IF(E47<>"", E47 & " #" & F47, "") -> Character #7 | H47: Accelerates the regeneration of 1 second cooldown of the spells of Pokemon stored in the bag (Pokemon that remain inside the Poke Balls). | I47: 7 - Accelerates the regeneration of 1 second cooldown of the spells of Pokemon stored in the bag (Pokemon that remain inside the Poke Balls).
A48: leaf stone | B48: Verificar aba de drops | C48: =IF(A48<>"",A48&" ("&B48&")", "") -> leaf stone (Verificar aba de drops) | D48: 500 | E48: Character | F48: 7 | G48: =IF(E48<>"", E48 & " #" & F48, "") -> Character #7 | H48: Accelerates the regeneration of 1 second cooldown of the spells of Pokemon stored in the bag (Pokemon that remain inside the Poke Balls). | I48: 7 - Accelerates the regeneration of 1 second cooldown of the spells of Pokemon stored in the bag (Pokemon that remain inside the Poke Balls).
A49: cocoon stone | B49: Verificar aba de drops | C49: =IF(A49<>"",A49&" ("&B49&")", "") -> cocoon stone (Verificar aba de drops) | D49: 500 | E49: Character | F49: 7 | G49: =IF(E49<>"", E49 & " #" & F49, "") -> Character #7 | H49: Accelerates the regeneration of 1 second cooldown of the spells of Pokemon stored in the bag (Pokemon that remain inside the Poke Balls). | I49: 7 - Accelerates the regeneration of 1 second cooldown of the spells of Pokemon stored in the bag (Pokemon that remain inside the Poke Balls).
C50: =IF(A50<>"",A50&" ("&B50&")", "") | G50: =IF(E50<>"", E50 & " #" & F50, "")
A51: soul badge | B51: Fuchsia Gym | C51: =IF(A51<>"",A51&" ("&B51&")", "") -> soul badge (Fuchsia Gym) | D51: 1 | E51: Character | F51: 8 | G51: =IF(E51<>"", E51 & " #" & F51, "") -> Character #8 | H51: Accelerates the regeneration of 1 second cooldown of the spells of Pokemon stored in the bag (Pokemon that remain inside the Poke Balls). | I51: 8 - Accelerates the regeneration of 1 second cooldown of the spells of Pokemon stored in the bag (Pokemon that remain inside the Poke Balls).
A52: queen ear | B52: Nidoqueen | C52: =IF(A52<>"",A52&" ("&B52&")", "") -> queen ear (Nidoqueen) | D52: 1500 | E52: Character | F52: 8 | G52: =IF(E52<>"", E52 & " #" & F52, "") -> Character #8 | H52: Accelerates the regeneration of 1 second cooldown of the spells of Pokemon stored in the bag (Pokemon that remain inside the Poke Balls). | I52: 8 - Accelerates the regeneration of 1 second cooldown of the spells of Pokemon stored in the bag (Pokemon that remain inside the Poke Balls).
A53: king ear | B53: Nidoking | C53: =IF(A53<>"",A53&" ("&B53&")", "") -> king ear (Nidoking) | D53: 1500 | E53: Character | F53: 8 | G53: =IF(E53<>"", E53 & " #" & F53, "") -> Character #8 | H53: Accelerates the regeneration of 1 second cooldown of the spells of Pokemon stored in the bag (Pokemon that remain inside the Poke Balls). | I53: 8 - Accelerates the regeneration of 1 second cooldown of the spells of Pokemon stored in the bag (Pokemon that remain inside the Poke Balls).
A54: giant bat wing | B54: Crobat | C54: =IF(A54<>"",A54&" ("&B54&")", "") -> giant bat wing (Crobat) | D54: 1100 | E54: Character | F54: 8 | G54: =IF(E54<>"", E54 & " #" & F54, "") -> Character #8 | H54: Accelerates the regeneration of 1 second cooldown of the spells of Pokemon stored in the bag (Pokemon that remain inside the Poke Balls). | I54: 8 - Accelerates the regeneration of 1 second cooldown of the spells of Pokemon stored in the bag (Pokemon that remain inside the Poke Balls).
A55: stinky hand | B55: Muk | C55: =IF(A55<>"",A55&" ("&B55&")", "") -> stinky hand (Muk) | D55: 900 | E55: Character | F55: 8 | G55: =IF(E55<>"", E55 & " #" & F55, "") -> Character #8 | H55: Accelerates the regeneration of 1 second cooldown of the spells of Pokemon stored in the bag (Pokemon that remain inside the Poke Balls). | I55: 8 - Accelerates the regeneration of 1 second cooldown of the spells of Pokemon stored in the bag (Pokemon that remain inside the Poke Balls).
A56: venom stone | B56: Verificar aba de drops | C56: =IF(A56<>"",A56&" ("&B56&")", "") -> venom stone (Verificar aba de drops) | D56: 1000 | E56: Character | F56: 8 | G56: =IF(E56<>"", E56 & " #" & F56, "") -> Character #8 | H56: Accelerates the regeneration of 1 second cooldown of the spells of Pokemon stored in the bag (Pokemon that remain inside the Poke Balls). | I56: 8 - Accelerates the regeneration of 1 second cooldown of the spells of Pokemon stored in the bag (Pokemon that remain inside the Poke Balls).
C57: =IF(A57<>"",A57&" ("&B57&")", "") | G57: =IF(E57<>"", E57 & " #" & F57, "")
A58: marsh badge | B58: Saffron Gym | C58: =IF(A58<>"",A58&" ("&B58&")", "") -> marsh badge (Saffron Gym) | D58: 1 | E58: Character | F58: 9 | G58: =IF(E58<>"", E58 & " #" & F58, "") -> Character #9 | H58: Accelerates the regeneration of 1 second cooldown of the spells of Pokemon stored in the bag (Pokemon that remain inside the Poke Balls). | I58: 9 - Accelerates the regeneration of 1 second cooldown of the spells of Pokemon stored in the bag (Pokemon that remain inside the Poke Balls).
A59: psychic moustache | B59: Alakazam | C59: =IF(A59<>"",A59&" ("&B59&")", "") -> psychic moustache (Alakazam) | D59: 1500 | E59: Character | F59: 9 | G59: =IF(E59<>"", E59 & " #" & F59, "") -> Character #9 | H59: Accelerates the regeneration of 1 second cooldown of the spells of Pokemon stored in the bag (Pokemon that remain inside the Poke Balls). | I59: 9 - Accelerates the regeneration of 1 second cooldown of the spells of Pokemon stored in the bag (Pokemon that remain inside the Poke Balls).
A60: two-eyed black tail | B60: Wobbuffet | C60: =IF(A60<>"",A60&" ("&B60&")", "") -> two-eyed black tail (Wobbuffet) | D60: 1500 | E60: Character | F60: 9 | G60: =IF(E60<>"", E60 & " #" & F60, "") -> Character #9 | H60: Accelerates the regeneration of 1 second cooldown of the spells of Pokemon stored in the bag (Pokemon that remain inside the Poke Balls). | I60: 9 - Accelerates the regeneration of 1 second cooldown of the spells of Pokemon stored in the bag (Pokemon that remain inside the Poke Balls).
A61: xatu wing | B61: Xatu | C61: =IF(A61<>"",A61&" ("&B61&")", "") -> xatu wing (Xatu) | D61: 1100 | E61: Character | F61: 9 | G61: =IF(E61<>"", E61 & " #" & F61, "") -> Character #9 | H61: Accelerates the regeneration of 1 second cooldown of the spells of Pokemon stored in the bag (Pokemon that remain inside the Poke Balls). | I61: 9 - Accelerates the regeneration of 1 second cooldown of the spells of Pokemon stored in the bag (Pokemon that remain inside the Poke Balls).
A62: giraffe antenna | B62: Girafarig | C62: =IF(A62<>"",A62&" ("&B62&")", "") -> giraffe antenna (Girafarig) | D62: 900 | E62: Character | F62: 9 | G62: =IF(E62<>"", E62 & " #" & F62, "") -> Character #9 | H62: Accelerates the regeneration of 1 second cooldown of the spells of Pokemon stored in the bag (Pokemon that remain inside the Poke Balls). | I62: 9 - Accelerates the regeneration of 1 second cooldown of the spells of Pokemon stored in the bag (Pokemon that remain inside the Poke Balls).
A63: enigma stone | B63: Verificar aba de drops | C63: =IF(A63<>"",A63&" ("&B63&")", "") -> enigma stone (Verificar aba de drops) | D63: 1000 | E63: Character | F63: 9 | G63: =IF(E63<>"", E63 & " #" & F63, "") -> Character #9 | H63: Accelerates the regeneration of 1 second cooldown of the spells of Pokemon stored in the bag (Pokemon that remain inside the Poke Balls). | I63: 9 - Accelerates the regeneration of 1 second cooldown of the spells of Pokemon stored in the bag (Pokemon that remain inside the Poke Balls).
C64: =IF(A64<>"",A64&" ("&B64&")", "") | G64: =IF(E64<>"", E64 & " #" & F64, "")
A65: electric screws | B65: Magnemite | C65: =IF(A65<>"",A65&" ("&B65&")", "") -> electric screws (Magnemite) | D65: 25 | E65: Character | F65: 10 | G65: =IF(E65<>"", E65 & " #" & F65, "") -> Character #10 | H65: Gives all your Pokemon 10% critical chance. | I65: 10 - Gives all your Pokemon 10% critical chance.
A66: remains of voltorb | B66: Voltorb | C66: =IF(A66<>"",A66&" ("&B66&")", "") -> remains of voltorb (Voltorb) | D66: 25 | E66: Character | F66: 10 | G66: =IF(E66<>"", E66 & " #" & F66, "") -> Character #10 | H66: Gives all your Pokemon 10% critical chance. | I66: 10 - Gives all your Pokemon 10% critical chance.
C67: =IF(A67<>"",A67&" ("&B67&")", "") | G67: =IF(E67<>"", E67 & " #" & F67, "")
A68: blue wings | B68: Shiny Clefable | C68: =IF(A68<>"",A68&" ("&B68&")", "") -> blue wings (Shiny Clefable) | D68: 1 | E68: Character | F68: 11 | G68: =IF(E68<>"", E68 & " #" & F68, "") -> Character #11 | H68: Your character will have an increase of 500 hitpoints in their maximum health. | I68: 11 - Your character will have an increase of 500 hitpoints in their maximum health.
A69: big cute ear | B69: Shiny Wigglytuff | C69: =IF(A69<>"",A69&" ("&B69&")", "") -> big cute ear (Shiny Wigglytuff) | D69: 1 | E69: Character | F69: 11 | G69: =IF(E69<>"", E69 & " #" & F69, "") -> Character #11 | H69: Your character will have an increase of 500 hitpoints in their maximum health. | I69: 11 - Your character will have an increase of 500 hitpoints in their maximum health.
C70: =IF(A70<>"",A70&" ("&B70&")", "") | G70: =IF(E70<>"", E70 & " #" & F70, "")
A71: wigglytuff ear | B71: Wigglytuff | C71: =IF(A71<>"",A71&" ("&B71&")", "") -> wigglytuff ear (Wigglytuff) | D71: 250 | E71: Character | F71: 12 | G71: =IF(E71<>"", E71 & " #" & F71, "") -> Character #12 | H71: Your character will have an increase of 300 hitpoints in their maximum health. | I71: 12 - Your character will have an increase of 300 hitpoints in their maximum health.
A72: pink wings | B72: Clefable | C72: =IF(A72<>"",A72&" ("&B72&")", "") -> pink wings (Clefable) | D72: 250 | E72: Character | F72: 12 | G72: =IF(E72<>"", E72 & " #" & F72, "") -> Character #12 | H72: Your character will have an increase of 300 hitpoints in their maximum health. | I72: 12 - Your character will have an increase of 300 hitpoints in their maximum health.
C73: =IF(A73<>"",A73&" ("&B73&")", "") | G73: =IF(E73<>"", E73 & " #" & F73, "")
A74: snorlax paw | B74: Snorlax | C74: =IF(A74<>"",A74&" ("&B74&")", "") -> snorlax paw (Snorlax) | D74: 400 | E74: Character | F74: 13 | G74: =IF(E74<>"", E74 & " #" & F74, "") -> Character #13 | H74: Your character will have an increase of 300 hitpoints in their maximum health. | I74: 13 - Your character will have an increase of 300 hitpoints in their maximum health.
A75: bear claw | B75: Ursaring | C75: =IF(A75<>"",A75&" ("&B75&")", "") -> bear claw (Ursaring) | D75: 400 | E75: Character | F75: 13 | G75: =IF(E75<>"", E75 & " #" & F75, "") -> Character #13 | H75: Your character will have an increase of 300 hitpoints in their maximum health. | I75: 13 - Your character will have an increase of 300 hitpoints in their maximum health.
C76: =IF(A76<>"",A76&" ("&B76&")", "") | G76: =IF(E76<>"", E76 & " #" & F76, "")
A77: magikarp fin | B77: Magikarp | C77: =IF(A77<>"",A77&" ("&B77&")", "") -> magikarp fin (Magikarp) | D77: 10 | E77: Character | F77: 14 | G77: =IF(E77<>"", E77 & " #" & F77, "") -> Character #14 | H77: Your character will have an increase of 300 hitpoints in their maximum health. | I77: 14 - Your character will have an increase of 300 hitpoints in their maximum health.
A78: mouse tail | B78: Ratata | C78: =IF(A78<>"",A78&" ("&B78&")", "") -> mouse tail (Ratata) | D78: 30 | E78: Character | F78: 14 | G78: =IF(E78<>"", E78 & " #" & F78, "") -> Character #14 | H78: Your character will have an increase of 300 hitpoints in their maximum health. | I78: 14 - Your character will have an increase of 300 hitpoints in their maximum health.
C79: =IF(A79<>"",A79&" ("&B79&")", "") | G79: =IF(E79<>"", E79 & " #" & F79, "")
A80: fire hair | B80: Ponyta | C80: =IF(A80<>"",A80&" ("&B80&")", "") -> fire hair (Ponyta) | D80: 80 | E80: Character | F80: 15 | G80: =IF(E80<>"", E80 & " #" & F80, "") -> Character #15 | H80: Give to player more 20 speed. | I80: 15 - Give to player more 20 speed.
A81: blue hair | B81: Shiny Ponyta | C81: =IF(A81<>"",A81&" ("&B81&")", "") -> blue hair (Shiny Ponyta) | D81: 1 | E81: Character | F81: 15 | G81: =IF(E81<>"", E81 & " #" & F81, "") -> Character #15 | H81: Give to player more 20 speed. | I81: 15 - Give to player more 20 speed.
C82: =IF(A82<>"",A82&" ("&B82&")", "") | G82: =IF(E82<>"", E82 & " #" & F82, "")
A83: fire hoof | B83: Rapidash | C83: =IF(A83<>"",A83&" ("&B83&")", "") -> fire hoof (Rapidash) | D83: 100 | E83: Character | F83: 16 | G83: =IF(E83<>"", E83 & " #" & F83, "") -> Character #16 | H83: Give to player more 20 speed. | I83: 16 - Give to player more 20 speed.
A84: giant piece of fur | B84: Arcanine | C84: =IF(A84<>"",A84&" ("&B84&")", "") -> giant piece of fur (Arcanine) | D84: 100 | E84: Character | F84: 16 | G84: =IF(E84<>"", E84 & " #" & F84, "") -> Character #16 | H84: Give to player more 20 speed. | I84: 16 - Give to player more 20 speed.
C85: =IF(A85<>"",A85&" ("&B85&")", "") | G85: =IF(E85<>"", E85 & " #" & F85, "")
A86: yellow bird crest | B86: Shiny Pidgey | C86: =IF(A86<>"",A86&" ("&B86&")", "") -> yellow bird crest (Shiny Pidgey) | D86: 1 | E86: Character | F86: 17 | G86: =IF(E86<>"", E86 & " #" & F86, "") -> Character #17 | H86: Give to player more 20 speed. | I86: 17 - Give to player more 20 speed.
A87: carmine wing | B87: Shiny Spearow | C87: =IF(A87<>"",A87&" ("&B87&")", "") -> carmine wing (Shiny Spearow) | D87: 1 | E87: Character | F87: 17 | G87: =IF(E87<>"", E87 & " #" & F87, "") -> Character #17 | H87: Give to player more 20 speed. | I87: 17 - Give to player more 20 speed.
C88: =IF(A88<>"",A88&" ("&B88&")", "") | G88: =IF(E88<>"", E88 & " #" & F88, "")
A89: bird wing | B89: Spearow | C89: =IF(A89<>"",A89&" ("&B89&")", "") -> bird wing (Spearow) | D89: 5 | E89: Character | F89: 18 | G89: =IF(E89<>"", E89 & " #" & F89, "") -> Character #18 | H89: Give to player more 20 speed. | I89: 18 - Give to player more 20 speed.
A90: bird crest | B90: Pidgey | C90: =IF(A90<>"",A90&" ("&B90&")", "") -> bird crest (Pidgey) | D90: 5 | E90: Character | F90: 18 | G90: =IF(E90<>"", E90 & " #" & F90, "") -> Character #18 | H90: Give to player more 20 speed. | I90: 18 - Give to player more 20 speed.
C91: =IF(A91<>"",A91&" ("&B91&")", "") | G91: =IF(E91<>"", E91 & " #" & F91, "")
A92: mythic water orb | B92: Verificar aba de drops | C92: =IF(A92<>"",A92&" ("&B92&")", "") -> mythic water orb (Verificar aba de drops) | D92: 3 | E92: Pokemon | F92: 1 | G92: =IF(E92<>"", E92 & " #" & F92, "") -> Pokemon #1 | H92: Reduces speed impariment caused by being underwater by 40% | I92: 1 - Reduces speed impariment caused by being underwater by 40%
A93: giant ruby | B93: Tentacruel | C93: =IF(A93<>"",A93&" ("&B93&")", "") -> giant ruby (Tentacruel) | D93: 600 | E93: Pokemon | F93: 1 | G93: =IF(E93<>"", E93 & " #" & F93, "") -> Pokemon #1 | H93: Reduces speed impariment caused by being underwater by 40% | I93: 1 - Reduces speed impariment caused by being underwater by 40%
A94: gyarados tail | B94: Gyarados | C94: =IF(A94<>"",A94&" ("&B94&")", "") -> gyarados tail (Gyarados) | D94: 1000 | E94: Pokemon | F94: 1 | G94: =IF(E94<>"", E94 & " #" & F94, "") -> Pokemon #1 | H94: Reduces speed impariment caused by being underwater by 40% | I94: 1 - Reduces speed impariment caused by being underwater by 40%
A95: big fist gloves | B95: Poliwrath | C95: =IF(A95<>"",A95&" ("&B95&")", "") -> big fist gloves (Poliwrath) | D95: 600 | E95: Pokemon | F95: 1 | G95: =IF(E95<>"", E95 & " #" & F95, "") -> Pokemon #1 | H95: Reduces speed impariment caused by being underwater by 40% | I95: 1 - Reduces speed impariment caused by being underwater by 40%
A96: aquatic tail | B96: Vaporeon | C96: =IF(A96<>"",A96&" ("&B96&")", "") -> aquatic tail (Vaporeon) | D96: 600 | E96: Pokemon | F96: 1 | G96: =IF(E96<>"", E96 & " #" & F96, "") -> Pokemon #1 | H96: Reduces speed impariment caused by being underwater by 40% | I96: 1 - Reduces speed impariment caused by being underwater by 40%
A97: duck paw | B97: Golduck | C97: =IF(A97<>"",A97&" ("&B97&")", "") -> duck paw (Golduck) | D97: 500 | E97: Pokemon | F97: 1 | G97: =IF(E97<>"", E97 & " #" & F97, "") -> Pokemon #1 | H97: Reduces speed impariment caused by being underwater by 40% | I97: 1 - Reduces speed impariment caused by being underwater by 40%
A98: water stone | B98: Verificar aba de drops | C98: =IF(A98<>"",A98&" ("&B98&")", "") -> water stone (Verificar aba de drops) | D98: 1000 | E98: Pokemon | F98: 1 | G98: =IF(E98<>"", E98 & " #" & F98, "") -> Pokemon #1 | H98: Reduces speed impariment caused by being underwater by 40% | I98: 1 - Reduces speed impariment caused by being underwater by 40%
A99: crystal stone | B99: Verificar aba de drops | C99: =IF(A99<>"",A99&" ("&B99&")", "") -> crystal stone (Verificar aba de drops) | D99: 500 | E99: Pokemon | F99: 1 | G99: =IF(E99<>"", E99 & " #" & F99, "") -> Pokemon #1 | H99: Reduces speed impariment caused by being underwater by 40% | I99: 1 - Reduces speed impariment caused by being underwater by 40%
C100: =IF(A100<>"",A100&" ("&B100&")", "") | G100: =IF(E100<>"", E100 & " #" & F100, "")
...

Sheet Star
A1: Star atual | B1: 0 | D1: Custo total DD💎 | E1: {=IF( INDIRECT("Star!B1")=0, SUM(MAP(SEQUENCE(1,INDIRECT("Star!B2")-0,0,1),LAMBDA(current_star_level,(INDEX('Star Level'!B3:K8,MATCH(INDIRECT("B3"),'Star Level'!A3:A8,0),(current_star_level*2)+1))*(2^(INDIRECT("Star!B2")-(current_star_level+1)))))), (2^(INDIRECT("Star!B2")-INDIRECT("Star!B1"))-1) * SUM(MAP(SEQUENCE(1,INDIRECT("Star!B1")-0,0,1),LAMBDA(current_star_level,(INDEX('Star Level'!B3:K8,MATCH(INDIRECT("B3"),'Star Level'!A3:A8,0),(current_star_level*2)+1))*(2^(INDIRECT("Star!B1")-(current_star_level+1)))))) + SUM(MAP(SEQUENCE(1,INDIRECT("Star!B2")-INDIRECT("Star!B1"),INDIRECT("Star!B1"),1),LAMBDA(current_star_level,(INDEX('Star Level'!B3:K8,MATCH(INDIRECT("B3"),'Star Level'!A3:A8,0),(current_star_level*2)+1))*(2^(INDIRECT("Star!B2")-(current_star_level+1))))) ))} -> 48
A2: Star objetivo | B2: 2 | D2: Custo total KK💸 | E2: {=IF( INDIRECT("Star!B1")=0, SUM( MAP( SEQUENCE(1,INDIRECT("Star!B2"),0,1), LAMBDA(current_star_level, INDEX('Star Level'!$B$3:$K$8, MATCH(INDIRECT("B3"),'Star Level'!$A$3:$A$8,0), (current_star_level*2)+2 ) * (2^(INDIRECT("Star!B2")-(current_star_level+1))) ) ) ), (2^(INDIRECT("Star!B2")-INDIRECT("Star!B1"))-1) * SUM( MAP( SEQUENCE(1,INDIRECT("Star!B1"),0,1), LAMBDA(current_star_level, INDEX('Star Level'!$B$3:$K$8, MATCH(INDIRECT("B3"),'Star Level'!$A$3:$A$8,0), (current_star_level*2)+2 ) * (2^(INDIRECT("Star!B1")-(current_star_level+1))) ) ) ) + SUM( MAP( SEQUENCE(1,INDIRECT("Star!B2")-INDIRECT("Star!B1"),INDIRECT("Star!B1"),1), LAMBDA(current_star_level, INDEX('Star Level'!$B$3:$K$8, MATCH(INDIRECT("B3"),'Star Level'!$A$3:$A$8,0), (current_star_level*2)+2 ) * (2^(INDIRECT("Star!B2")-(current_star_level+1))) ) ) ) )} -> 12
A3: Tier | B3: T1 | D3: Pokes necessarios | E3: {=POWER(2, INDIRECT("Star!B2")) - POWER(2, INDIRECT("Star!B1"))} -> 3
A4: Valores são considerando a opção de 100% de sucesso; Star aumenta o DANO DE ATAQUE: - Tier 3: 2% por nível de estrela. - Tier 2: 4% por nível de estrela. - Tier 1: 6% por nível de estrela. - Super Rare: 8% por nível de estrela. - Ultra Rare: 10% por nível de estrela. - Legendary: 15% por nível de estrela.

Sheet Brokes
B1: Max Broke | D1: OBS 1. Premier/Alliance balls contam sempre como a primeira bola jogada. 2. Premier/Alliance balls contam para a contagem de brokes totais. 3. O max é um valor não oficial descoberto pela comunidade, e pode mudar a qualquer momento. 4. As brokes são pra shinys. Pokémon normal não tem max. 5. Chegar na máxima não garante o catch. A chance só fica muito mais alta. 6. Rates: PB = 4x UB = 4x AB = 5x Elemental = 5x 7. O sistema de mérito considera o total de brokes. Os rates não têm nada a ver com ele
A2: Mythic | B2: ?
A3: Legendary | B3: 22535
A4: Ultra Rare | B4: 9400
A5: Super Rare | B5: 3500
A6: T1 | B6: 1280
A7: T2 | B7: ~900
A8: T3 | B8: ~700
A9: T4 | B9: ~600
A10: T5 | B10: ~400
A11: T6 | B11: ~200

Sheet Tier List
A1: Pokémon | B1: Tier | C1: Moveset | D1: Tier | E1: {="Pokemons Tier " & INDIRECT("D2") & " com moveset " & INDIRECT("D4")} -> Pokemons Tier T1 com moveset Steel | F1: ? | G1: {=unique(C2:C1011)} -> Grass | H1: Ultra Rare | I1: =IFERROR(__xludf.DUMMYFUNCTION("Query($A$2:$B1011, ""SELECT A WHERE B = '""&H1&""'"")"),"Shiny Sceptile") -> Shiny Sceptile | K1: T1 | L1: =IFERROR(__xludf.DUMMYFUNCTION("Query($A$2:$B1011, ""SELECT A WHERE B = '""&K1&""'"")"),"Shiny Venusaur") -> Shiny Venusaur | N1: Super Rare | O1: =IFERROR(__xludf.DUMMYFUNCTION("SORT(Query($A$2:$B1011, ""SELECT A WHERE B = '""&N1&""'""))"),"Shiny Aggron") -> Shiny Aggron | Q1: Legendary | R1: =IFERROR(__xludf.DUMMYFUNCTION("Query($A$2:$B1011, ""SELECT A WHERE B = '""&Q1&""'"")"),"Shiny Alakazam") -> Shiny Alakazam
A2: Bulbasaur | B2: T6 | C2: Grass | D2: T1 | E2: =IFERROR(__xludf.DUMMYFUNCTION("IFERROR(FILTER($A$2:$A1011, $B$2:$B1011 = INDIRECT(""D2""), C2:C1011 = INDIRECT(""D4"")), ""Nenhum Pokémon encontrado"")"),"Shiny Mawile") -> Shiny Mawile | F2: T7 | G2: Fire | I2: =IFERROR(__xludf.DUMMYFUNCTION("""COMPUTED_VALUE"""),"Shiny Blaziken") -> Shiny Blaziken | L2: =IFERROR(__xludf.DUMMYFUNCTION("""COMPUTED_VALUE"""),"Shiny Charizard") -> Shiny Charizard | O2: =IFERROR(__xludf.DUMMYFUNCTION("""COMPUTED_VALUE"""),"Shiny Altaria") -> Shiny Altaria | R2: =IFERROR(__xludf.DUMMYFUNCTION("""COMPUTED_VALUE"""),"Shiny Gengar") -> Shiny Gengar
A3: Shiny Bulbasaur | B3: T5 | C3: Grass | D3: Moveset | E3: =IFERROR(__xludf.DUMMYFUNCTION("""COMPUTED_VALUE"""),"Shiny Metang") -> Shiny Metang | F3: T6 | G3: Water | I3: =IFERROR(__xludf.DUMMYFUNCTION("""COMPUTED_VALUE"""),"Shiny Swampert") -> Shiny Swampert | L3: =IFERROR(__xludf.DUMMYFUNCTION("""COMPUTED_VALUE"""),"Shiny Blastoise") -> Shiny Blastoise | O3: =IFERROR(__xludf.DUMMYFUNCTION("""COMPUTED_VALUE"""),"Shiny Arcanine") -> Shiny Arcanine | R3: =IFERROR(__xludf.DUMMYFUNCTION("""COMPUTED_VALUE"""),"Shiny Electabuzz") -> Shiny Electabuzz
A4: Ivysaur | B4: T5 | C4: Grass | D4: Steel | F4: T5 | G4: Bug | I4: =IFERROR(__xludf.DUMMYFUNCTION("""COMPUTED_VALUE"""),"Shiny Mightyena") -> Shiny Mightyena | L4: =IFERROR(__xludf.DUMMYFUNCTION("""COMPUTED_VALUE"""),"Shiny Pidgeot") -> Shiny Pidgeot | O4: =IFERROR(__xludf.DUMMYFUNCTION("""COMPUTED_VALUE"""),"Shiny Armaldo") -> Shiny Armaldo | R4: =IFERROR(__xludf.DUMMYFUNCTION("""COMPUTED_VALUE"""),"Shiny Magmar") -> Shiny Magmar
A5: Shiny Ivysaur | B5: T4 | C5: Grass | F5: T4 | G5: Flying | I5: =IFERROR(__xludf.DUMMYFUNCTION("""COMPUTED_VALUE"""),"Shiny Gardevoir") -> Shiny Gardevoir | L5: =IFERROR(__xludf.DUMMYFUNCTION("""COMPUTED_VALUE"""),"Shiny Raichu") -> Shiny Raichu | O5: =IFERROR(__xludf.DUMMYFUNCTION("""COMPUTED_VALUE"""),"Shiny Dusknoir") -> Shiny Dusknoir | R5: =IFERROR(__xludf.DUMMYFUNCTION("""COMPUTED_VALUE"""),"Shiny Gyarados") -> Shiny Gyarados
A6: Venusaur | B6: T3 | C6: Grass | F6: T3 | G6: Normal | I6: =IFERROR(__xludf.DUMMYFUNCTION("""COMPUTED_VALUE"""),"Shiny Exploud") -> Shiny Exploud | L6: =IFERROR(__xludf.DUMMYFUNCTION("""COMPUTED_VALUE"""),"Shiny Nidoqueen") -> Shiny Nidoqueen | O6: =IFERROR(__xludf.DUMMYFUNCTION("""COMPUTED_VALUE"""),"Shiny Florges") -> Shiny Florges | R6: =IFERROR(__xludf.DUMMYFUNCTION("""COMPUTED_VALUE"""),"Shiny Snorlax") -> Shiny Snorlax
A7: Shiny Venusaur | B7: T1 | C7: Grass | F7: T2 | G7: Poison | I7: =IFERROR(__xludf.DUMMYFUNCTION("""COMPUTED_VALUE"""),"Shiny Manectric") -> Shiny Manectric | L7: =IFERROR(__xludf.DUMMYFUNCTION("""COMPUTED_VALUE"""),"Shiny Nidoking") -> Shiny Nidoking | O7: =IFERROR(__xludf.DUMMYFUNCTION("""COMPUTED_VALUE"""),"Shiny Gliscor") -> Shiny Gliscor | R7: =IFERROR(__xludf.DUMMYFUNCTION("""COMPUTED_VALUE"""),"Shiny Dragonair") -> Shiny Dragonair
A8: Charmander | B8: T6 | C8: Fire | F8: T1 | G8: Electric | I8: =IFERROR(__xludf.DUMMYFUNCTION("""COMPUTED_VALUE"""),"Shiny Swalot") -> Shiny Swalot | L8: =IFERROR(__xludf.DUMMYFUNCTION("""COMPUTED_VALUE"""),"Mega Clefable") -> Mega Clefable | O8: =IFERROR(__xludf.DUMMYFUNCTION("""COMPUTED_VALUE"""),"Shiny Gogoat") -> Shiny Gogoat | R8: =IFERROR(__xludf.DUMMYFUNCTION("""COMPUTED_VALUE"""),"Shiny Scizor") -> Shiny Scizor
A9: Shiny Charmander | B9: T5 | C9: Fire | F9: Super Rare | G9: Ground | I9: =IFERROR(__xludf.DUMMYFUNCTION("""COMPUTED_VALUE"""),"Shiny Torkoal") -> Shiny Torkoal | L9: =IFERROR(__xludf.DUMMYFUNCTION("""COMPUTED_VALUE"""),"Shiny Ninetales") -> Shiny Ninetales | O9: =IFERROR(__xludf.DUMMYFUNCTION("""COMPUTED_VALUE"""),"Shiny Houndoom") -> Shiny Houndoom | R9: =IFERROR(__xludf.DUMMYFUNCTION("""COMPUTED_VALUE"""),"Mega Houndoom") -> Mega Houndoom
A10: Charmeleon | B10: T5 | C10: Fire | F10: Ultra Rare | G10: Fairy | I10: =IFERROR(__xludf.DUMMYFUNCTION("""COMPUTED_VALUE"""),"Shiny Milotic") -> Shiny Milotic | L10: =IFERROR(__xludf.DUMMYFUNCTION("""COMPUTED_VALUE"""),"Shiny Poliwrath") -> Shiny Poliwrath | O10: =IFERROR(__xludf.DUMMYFUNCTION("""COMPUTED_VALUE"""),"Shiny Hydreigon") -> Shiny Hydreigon | R10: =IFERROR(__xludf.DUMMYFUNCTION("""COMPUTED_VALUE"""),"Shiny Flygon") -> Shiny Flygon
A11: Shiny Charmeleon | B11: T4 | C11: Fire | F11: Legendary | G11: Dark | I11: =IFERROR(__xludf.DUMMYFUNCTION("""COMPUTED_VALUE"""),"Shiny Tropius") -> Shiny Tropius | L11: =IFERROR(__xludf.DUMMYFUNCTION("""COMPUTED_VALUE"""),"Shiny Tentacruel") -> Shiny Tentacruel | O11: =IFERROR(__xludf.DUMMYFUNCTION("""COMPUTED_VALUE"""),"Shiny Infernape") -> Shiny Infernape | R11: =IFERROR(__xludf.DUMMYFUNCTION("""COMPUTED_VALUE"""),"Shiny Absol") -> Shiny Absol
A12: Charizard | B12: T3 | C12: Fire | F12: Mythic | G12: Psychic | I12: =IFERROR(__xludf.DUMMYFUNCTION("""COMPUTED_VALUE"""),"Shiny Glalie") -> Shiny Glalie | L12: =IFERROR(__xludf.DUMMYFUNCTION("""COMPUTED_VALUE"""),"Shiny Golem") -> Shiny Golem | O12: =IFERROR(__xludf.DUMMYFUNCTION("""COMPUTED_VALUE"""),"Shiny Kangaskhan") -> Shiny Kangaskhan | R12: =IFERROR(__xludf.DUMMYFUNCTION("""COMPUTED_VALUE"""),"Shiny Lucario") -> Shiny Lucario
A13: Shiny Charizard | B13: T1 | C13: Fire | G13: Fighting | I13: =IFERROR(__xludf.DUMMYFUNCTION("""COMPUTED_VALUE"""),"Shiny Salamence") -> Shiny Salamence | L13: =IFERROR(__xludf.DUMMYFUNCTION("""COMPUTED_VALUE"""),"Shiny Rapidash") -> Shiny Rapidash | O13: =IFERROR(__xludf.DUMMYFUNCTION("""COMPUTED_VALUE"""),"Shiny Kingdra") -> Shiny Kingdra | R13: =IFERROR(__xludf.DUMMYFUNCTION("""COMPUTED_VALUE"""),"Mega Abomasnow") -> Mega Abomasnow
A14: Squirtle | B14: T6 | C14: Water | G14: Rock | I14: =IFERROR(__xludf.DUMMYFUNCTION("""COMPUTED_VALUE"""),"Shiny Metagross") -> Shiny Metagross | L14: =IFERROR(__xludf.DUMMYFUNCTION("""COMPUTED_VALUE"""),"Shiny Farfetch'd") -> Shiny Farfetch'd | O14: =IFERROR(__xludf.DUMMYFUNCTION("""COMPUTED_VALUE"""),"Shiny Luxray") -> Shiny Luxray | R14: =IFERROR(__xludf.DUMMYFUNCTION("""COMPUTED_VALUE"""),"Shiny Rhyperior") -> Shiny Rhyperior
A15: Shiny Squirtle | B15: T5 | C15: Water | G15: Steel | I15: =IFERROR(__xludf.DUMMYFUNCTION("""COMPUTED_VALUE"""),"Shiny Rampardos") -> Shiny Rampardos | L15: =IFERROR(__xludf.DUMMYFUNCTION("""COMPUTED_VALUE"""),"Shiny Dodrio") -> Shiny Dodrio | O15: =IFERROR(__xludf.DUMMYFUNCTION("""COMPUTED_VALUE"""),"Shiny Machamp") -> Shiny Machamp | R15: =IFERROR(__xludf.DUMMYFUNCTION("""COMPUTED_VALUE"""),"Shiny Leafeon") -> Shiny Leafeon
A16: Wartortle | B16: T5 | C16: Water | G16: Ice | L16: =IFERROR(__xludf.DUMMYFUNCTION("""COMPUTED_VALUE"""),"Shiny Muk") -> Shiny Muk | O16: =IFERROR(__xludf.DUMMYFUNCTION("""COMPUTED_VALUE"""),"Shiny Mimikyu") -> Shiny Mimikyu | R16: =IFERROR(__xludf.DUMMYFUNCTION("""COMPUTED_VALUE"""),"Shiny Glaceon") -> Shiny Glaceon
A17: Shiny Wartortle | B17: T4 | C17: Water | G17: Ghost | L17: =IFERROR(__xludf.DUMMYFUNCTION("""COMPUTED_VALUE"""),"Shiny Marowak") -> Shiny Marowak | O17: =IFERROR(__xludf.DUMMYFUNCTION("""COMPUTED_VALUE"""),"Shiny Misdreavus") -> Shiny Misdreavus | R17: =IFERROR(__xludf.DUMMYFUNCTION("""COMPUTED_VALUE"""),"Shiny Garbodor") -> Shiny Garbodor
A18: Blastoise | B18: T3 | C18: Water | G18: ? | L18: =IFERROR(__xludf.DUMMYFUNCTION("""COMPUTED_VALUE"""),"Shiny Hitmonlee") -> Shiny Hitmonlee | O18: =IFERROR(__xludf.DUMMYFUNCTION("""COMPUTED_VALUE"""),"Shiny Mr. Mime") -> Shiny Mr. Mime | R18: =IFERROR(__xludf.DUMMYFUNCTION("""COMPUTED_VALUE"""),"Shiny Sylveon") -> Shiny Sylveon
A19: Shiny Blastoise | B19: T1 | C19: Water | G19: Dragon | L19: =IFERROR(__xludf.DUMMYFUNCTION("""COMPUTED_VALUE"""),"Shiny Hitmonchan") -> Shiny Hitmonchan | O19: =IFERROR(__xludf.DUMMYFUNCTION("""COMPUTED_VALUE"""),"Shiny Pachirisu") -> Shiny Pachirisu
A20: Caterpie | B20: T7 | C20: Bug | L20: =IFERROR(__xludf.DUMMYFUNCTION("""COMPUTED_VALUE"""),"Shiny Jynx") -> Shiny Jynx | O20: =IFERROR(__xludf.DUMMYFUNCTION("""COMPUTED_VALUE"""),"Shiny Pinsir") -> Shiny Pinsir
A21: Shiny Caterpie | B21: T6 | C21: Bug | L21: =IFERROR(__xludf.DUMMYFUNCTION("""COMPUTED_VALUE"""),"Shiny Lapras") -> Shiny Lapras | O21: =IFERROR(__xludf.DUMMYFUNCTION("""COMPUTED_VALUE"""),"Shiny Pupitar") -> Shiny Pupitar
A22: Metapod | B22: T6 | C22: Bug | L22: =IFERROR(__xludf.DUMMYFUNCTION("""COMPUTED_VALUE"""),"Shiny Vaporeon") -> Shiny Vaporeon | O22: =IFERROR(__xludf.DUMMYFUNCTION("""COMPUTED_VALUE"""),"Shiny Scyther") -> Shiny Scyther
A23: Shiny Metapod | B23: T5 | C23: Bug | L23: =IFERROR(__xludf.DUMMYFUNCTION("""COMPUTED_VALUE"""),"Shiny Jolteon") -> Shiny Jolteon | O23: =IFERROR(__xludf.DUMMYFUNCTION("""COMPUTED_VALUE"""),"Shiny Seviper") -> Shiny Seviper
A24: Butterfree | B24: T5 | C24: Flying | L24: =IFERROR(__xludf.DUMMYFUNCTION("""COMPUTED_VALUE"""),"Shiny Flareon") -> Shiny Flareon | O24: =IFERROR(__xludf.DUMMYFUNCTION("""COMPUTED_VALUE"""),"Shiny Sharpedo") -> Shiny Sharpedo
A25: Shiny Butterfree | B25: T4 | C25: Flying | L25: =IFERROR(__xludf.DUMMYFUNCTION("""COMPUTED_VALUE"""),"Shiny Omastar") -> Shiny Omastar | O25: =IFERROR(__xludf.DUMMYFUNCTION("""COMPUTED_VALUE"""),"Shiny Skarmory") -> Shiny Skarmory
A26: Weedle | B26: T7 | C26: Bug | L26: =IFERROR(__xludf.DUMMYFUNCTION("""COMPUTED_VALUE"""),"Shiny Kabutops") -> Shiny Kabutops | O26: =IFERROR(__xludf.DUMMYFUNCTION("""COMPUTED_VALUE"""),"Shiny Swellow") -> Shiny Swellow
A27: Shiny Weedle | B27: T6 | C27: Bug | L27: =IFERROR(__xludf.DUMMYFUNCTION("""COMPUTED_VALUE"""),"Aerodactyl") -> Aerodactyl | O27: =IFERROR(__xludf.DUMMYFUNCTION("""COMPUTED_VALUE"""),"Shiny Tangrowth") -> Shiny Tangrowth
A28: Kakuna | B28: T6 | C28: Bug | L28: =IFERROR(__xludf.DUMMYFUNCTION("""COMPUTED_VALUE"""),"Shiny Meganium") -> Shiny Meganium | O28: =IFERROR(__xludf.DUMMYFUNCTION("""COMPUTED_VALUE"""),"Shiny Tauros") -> Shiny Tauros
A29: Shiny Kakuna | B29: T5 | C29: Bug | L29: =IFERROR(__xludf.DUMMYFUNCTION("""COMPUTED_VALUE"""),"Shiny Typhlosion") -> Shiny Typhlosion | O29: =IFERROR(__xludf.DUMMYFUNCTION("""COMPUTED_VALUE"""),"Shiny Torterra") -> Shiny Torterra
A30: Beedrill | B30: T5 | C30: Bug | L30: =IFERROR(__xludf.DUMMYFUNCTION("""COMPUTED_VALUE"""),"Shiny Feraligatr") -> Shiny Feraligatr | O30: =IFERROR(__xludf.DUMMYFUNCTION("""COMPUTED_VALUE"""),"Shiny Toxicroak") -> Shiny Toxicroak
A31: Shiny Beedrill | B31: T4 | C31: Bug | L31: =IFERROR(__xludf.DUMMYFUNCTION("""COMPUTED_VALUE"""),"Shiny Ampharos") -> Shiny Ampharos | O31: =IFERROR(__xludf.DUMMYFUNCTION("""COMPUTED_VALUE"""),"Shiny Walrein") -> Shiny Walrein
A32: Pidgey | B32: T7 | C32: Flying | L32: =IFERROR(__xludf.DUMMYFUNCTION("""COMPUTED_VALUE"""),"Shiny Sudowoodo") -> Shiny Sudowoodo | O32: =IFERROR(__xludf.DUMMYFUNCTION("""COMPUTED_VALUE"""),"Shiny Wobbuffet") -> Shiny Wobbuffet
A33: Shiny Pidgey | B33: T6 | C33: Flying | L33: =IFERROR(__xludf.DUMMYFUNCTION("""COMPUTED_VALUE"""),"Shiny Politoed") -> Shiny Politoed
A34: Pidgeotto | B34: T5 | C34: Flying | L34: =IFERROR(__xludf.DUMMYFUNCTION("""COMPUTED_VALUE"""),"Shiny Espeon") -> Shiny Espeon
A35: Shiny Pidgeotto | B35: T4 | C35: Flying | L35: =IFERROR(__xludf.DUMMYFUNCTION("""COMPUTED_VALUE"""),"Shiny Umbreon") -> Shiny Umbreon
A36: Pidgeot | B36: T3 | C36: Flying | L36: =IFERROR(__xludf.DUMMYFUNCTION("""COMPUTED_VALUE"""),"Shiny Slowking") -> Shiny Slowking
A37: Shiny Pidgeot | B37: T1 | C37: Flying | L37: =IFERROR(__xludf.DUMMYFUNCTION("""COMPUTED_VALUE"""),"Shiny Steelix") -> Shiny Steelix
A38: Rattata | B38: T7 | C38: Normal | L38: =IFERROR(__xludf.DUMMYFUNCTION("""COMPUTED_VALUE"""),"Shiny Ursaring") -> Shiny Ursaring
A39: Shiny Rattata | B39: T6 | C39: Normal | L39: =IFERROR(__xludf.DUMMYFUNCTION("""COMPUTED_VALUE"""),"Shiny Magcargo") -> Shiny Magcargo
A40: Raticate | B40: T5 | C40: Normal | L40: =IFERROR(__xludf.DUMMYFUNCTION("""COMPUTED_VALUE"""),"Shiny Mantine") -> Shiny Mantine
A41: Shiny Raticate | B41: T4 | C41: Normal | L41: =IFERROR(__xludf.DUMMYFUNCTION("""COMPUTED_VALUE"""),"Shiny Smeargle") -> Shiny Smeargle
A42: Spearow | B42: T7 | C42: Flying | L42: =IFERROR(__xludf.DUMMYFUNCTION("""COMPUTED_VALUE"""),"Shiny Hitmontop") -> Shiny Hitmontop
A43: Shiny Spearow | B43: T6 | C43: Flying | L43: =IFERROR(__xludf.DUMMYFUNCTION("""COMPUTED_VALUE"""),"Shiny Miltank") -> Shiny Miltank
A44: Fearow | B44: T5 | C44: Flying | L44: =IFERROR(__xludf.DUMMYFUNCTION("""COMPUTED_VALUE"""),"Shiny Blissey") -> Shiny Blissey
A45: Shiny Fearow | B45: T3 | C45: Flying | L45: =IFERROR(__xludf.DUMMYFUNCTION("""COMPUTED_VALUE"""),"Shiny Beautifly") -> Shiny Beautifly
A46: Ekans | B46: T6 | C46: Poison | L46: =IFERROR(__xludf.DUMMYFUNCTION("""COMPUTED_VALUE"""),"Shiny Dustox") -> Shiny Dustox
A47: Shiny Ekans | B47: T5 | C47: Poison | L47: =IFERROR(__xludf.DUMMYFUNCTION("""COMPUTED_VALUE"""),"Shiny Ludicolo") -> Shiny Ludicolo
A48: Arbok | B48: T4 | C48: Poison | L48: =IFERROR(__xludf.DUMMYFUNCTION("""COMPUTED_VALUE"""),"Shiny Shiftry") -> Shiny Shiftry
A49: Shiny Arbok | B49: T3 | C49: Poison | L49: =IFERROR(__xludf.DUMMYFUNCTION("""COMPUTED_VALUE"""),"Shiny Pelipper") -> Shiny Pelipper
A50: Pikachu | B50: T5 | C50: Electric | L50: =IFERROR(__xludf.DUMMYFUNCTION("""COMPUTED_VALUE"""),"Shiny Masquerain") -> Shiny Masquerain
A51: Shiny Pikachu | B51: T4 | C51: Electric | L51: =IFERROR(__xludf.DUMMYFUNCTION("""COMPUTED_VALUE"""),"Shiny Breloom") -> Shiny Breloom
A52: Raichu | B52: T3 | C52: Electric | L52: =IFERROR(__xludf.DUMMYFUNCTION("""COMPUTED_VALUE"""),"Shiny Ninjask") -> Shiny Ninjask
A53: Shiny Raichu | B53: T1 | C53: Electric | L53: =IFERROR(__xludf.DUMMYFUNCTION("""COMPUTED_VALUE"""),"Shiny Shedinja") -> Shiny Shedinja
A54: Sandshrew | B54: T6 | C54: Ground | L54: =IFERROR(__xludf.DUMMYFUNCTION("""COMPUTED_VALUE"""),"Shiny Hariyama") -> Shiny Hariyama
A55: Shiny Sandshrew | B55: T5 | C55: Ground | L55: =IFERROR(__xludf.DUMMYFUNCTION("""COMPUTED_VALUE"""),"Shiny Delcatty") -> Shiny Delcatty
A56: Sandslash | B56: T4 | C56: Ground | L56: =IFERROR(__xludf.DUMMYFUNCTION("""COMPUTED_VALUE"""),"Shiny Sableye") -> Shiny Sableye
A57: Shiny Sandslash | B57: T3 | C57: Ground | L57: =IFERROR(__xludf.DUMMYFUNCTION("""COMPUTED_VALUE"""),"Shiny Mawile") -> Shiny Mawile
A58: Nidoran female | B58: T6 | C58: Poison | L58: =IFERROR(__xludf.DUMMYFUNCTION("""COMPUTED_VALUE"""),"Shiny Medicham") -> Shiny Medicham
A59: Shiny Nidoran female | B59: T5 | C59: Poison | L59: =IFERROR(__xludf.DUMMYFUNCTION("""COMPUTED_VALUE"""),"Shiny Roselia") -> Shiny Roselia
A60: Nidorina | B60: T5 | C60: Ground | L60: =IFERROR(__xludf.DUMMYFUNCTION("""COMPUTED_VALUE"""),"Shiny Wailord") -> Shiny Wailord
A61: Shiny Nidorina | B61: T4 | C61: Ground | L61: =IFERROR(__xludf.DUMMYFUNCTION("""COMPUTED_VALUE"""),"Shiny Camerupt") -> Shiny Camerupt
A62: Nidoqueen | B62: T3 | C62: Ground | L62: =IFERROR(__xludf.DUMMYFUNCTION("""COMPUTED_VALUE"""),"Shiny Grumpig") -> Shiny Grumpig
A63: Shiny Nidoqueen | B63: T1 | C63: Ground | L63: =IFERROR(__xludf.DUMMYFUNCTION("""COMPUTED_VALUE"""),"Shiny Cacturne") -> Shiny Cacturne
A64: Nidoran Male | B64: T6 | C64: Poison | L64: =IFERROR(__xludf.DUMMYFUNCTION("""COMPUTED_VALUE"""),"Shiny Zangoose") -> Shiny Zangoose
A65: Shiny Nidoran Male | B65: T5 | C65: Poison | L65: =IFERROR(__xludf.DUMMYFUNCTION("""COMPUTED_VALUE"""),"Shiny Lunatone") -> Shiny Lunatone
A66: Nidorino | B66: T5 | C66: Poison | L66: =IFERROR(__xludf.DUMMYFUNCTION("""COMPUTED_VALUE"""),"Shiny Solrock") -> Shiny Solrock
A67: Shiny Nidorino | B67: T4 | C67: Poison | L67: =IFERROR(__xludf.DUMMYFUNCTION("""COMPUTED_VALUE"""),"Shiny Whiscash") -> Shiny Whiscash
A68: Nidoking | B68: T3 | C68: Poison | L68: =IFERROR(__xludf.DUMMYFUNCTION("""COMPUTED_VALUE"""),"Shiny Crawdaunt") -> Shiny Crawdaunt
A69: Shiny Nidoking | B69: T1 | C69: Poison | L69: =IFERROR(__xludf.DUMMYFUNCTION("""COMPUTED_VALUE"""),"Shiny Claydol") -> Shiny Claydol
A70: Clefairy | B70: T6 | C70: Fairy | L70: =IFERROR(__xludf.DUMMYFUNCTION("""COMPUTED_VALUE"""),"Shiny Cradily") -> Shiny Cradily
A71: Shiny Clefairy | B71: T5 | C71: Fairy | L71: =IFERROR(__xludf.DUMMYFUNCTION("""COMPUTED_VALUE"""),"Shiny Kecleon") -> Shiny Kecleon
A72: Clefable | B72: T4 | C72: Fairy | L72: =IFERROR(__xludf.DUMMYFUNCTION("""COMPUTED_VALUE"""),"Shiny Banette") -> Shiny Banette
A73: Shiny Clefable | B73: T3 | C73: Fairy | L73: =IFERROR(__xludf.DUMMYFUNCTION("""COMPUTED_VALUE"""),"Shiny Dusclops") -> Shiny Dusclops
A74: Mega Clefable | B74: T1 | C74: Fairy | L74: =IFERROR(__xludf.DUMMYFUNCTION("""COMPUTED_VALUE"""),"Shiny Chimecho") -> Shiny Chimecho
A75: Vulpix | B75: T6 | C75: Fire | L75: =IFERROR(__xludf.DUMMYFUNCTION("""COMPUTED_VALUE"""),"Shiny Huntail") -> Shiny Huntail
A76: Shiny Vulpix | B76: T5 | C76: Fire | L76: =IFERROR(__xludf.DUMMYFUNCTION("""COMPUTED_VALUE"""),"Shiny Gorebyss") -> Shiny Gorebyss
A77: Ninetales | B77: T3 | C77: Fire | L77: =IFERROR(__xludf.DUMMYFUNCTION("""COMPUTED_VALUE"""),"Shiny Relicanth") -> Shiny Relicanth
A78: Shiny Ninetales | B78: T1 | C78: Fire | L78: =IFERROR(__xludf.DUMMYFUNCTION("""COMPUTED_VALUE"""),"Shiny Metang") -> Shiny Metang
A79: Jigglypuff | B79: T6 | C79: Fairy | L79: =IFERROR(__xludf.DUMMYFUNCTION("""COMPUTED_VALUE"""),"Torterra") -> Torterra
A80: Shiny Jigglypuff | B80: T5 | C80: Fairy | L80: =IFERROR(__xludf.DUMMYFUNCTION("""COMPUTED_VALUE"""),"Infernape") -> Infernape
A81: Wigglytuff | B81: T4 | C81: Fairy | L81: =IFERROR(__xludf.DUMMYFUNCTION("""COMPUTED_VALUE"""),"Luxray") -> Luxray
A82: Shiny Wigglytuff | B82: T2 | C82: Fairy | L82: =IFERROR(__xludf.DUMMYFUNCTION("""COMPUTED_VALUE"""),"Rampardos") -> Rampardos
A83: Zubat | B83: T7 | C83: Poison | L83: =IFERROR(__xludf.DUMMYFUNCTION("""COMPUTED_VALUE"""),"Rhyperior") -> Rhyperior
A84: Shiny Zubat | B84: T5 | C84: Flying | L84: =IFERROR(__xludf.DUMMYFUNCTION("""COMPUTED_VALUE"""),"Tangrowth") -> Tangrowth
A85: Golbat | B85: T5 | C85: Poison | L85: =IFERROR(__xludf.DUMMYFUNCTION("""COMPUTED_VALUE"""),"Gliscor") -> Gliscor
A86: Shiny Golbat | B86: T4 | C86: Flying | L86: =IFERROR(__xludf.DUMMYFUNCTION("""COMPUTED_VALUE"""),"Dusknoir") -> Dusknoir
A87: Oddish | B87: T7 | C87: Grass | L87: =IFERROR(__xludf.DUMMYFUNCTION("""COMPUTED_VALUE"""),"Garbodor") -> Garbodor
A88: Shiny Oddish | B88: T6 | C88: Poison | L88: =IFERROR(__xludf.DUMMYFUNCTION("""COMPUTED_VALUE"""),"Shiny Druddigon") -> Shiny Druddigon
A89: Gloom | B89: T5 | C89: Poison | L89: =IFERROR(__xludf.DUMMYFUNCTION("""COMPUTED_VALUE"""),"Gogoat") -> Gogoat
A90: Shiny Gloom | B90: T4 | C90: Poison
A91: Vileplume | B91: T4 | C91: Grass
A92: Shiny Vileplume | B92: T3 | C92: Grass
A93: Paras | B93: T7 | C93: Bug
A94: Shiny Paras | B94: T5 | C94: Bug
A95: Parasect | B95: T5 | C95: Bug
A96: Shiny Parasect | B96: T4 | C96: Bug
A97: Venonat | B97: T6 | C97: Poison
A98: Shiny Venonat | B98: T5 | C98: Bug
A99: Venomoth | B99: T4 | C99: Bug
A100: Shiny Venomoth | B100: T2 | C100: Bug
...

Sheet Shiny Rate
A1: =IFERROR(__xludf.DUMMYFUNCTION("IMPORTRANGE(""https://docs.google.com/spreadsheets/d/1ID3qu1P4Zey82OSLntg4O0xoZlY1hGK58tte0D_Cv_s/edit?pli=1&gid=1677455532#gid=1677455532"",""Shiny Rate!X4:AK10"")"),2.55) -> 2.55 | C1: =IFERROR(__xludf.DUMMYFUNCTION("""COMPUTED_VALUE"""),2.45) -> 2.45 | E1: =IFERROR(__xludf.DUMMYFUNCTION("""COMPUTED_VALUE"""),2.35) -> 2.35 | G1: =IFERROR(__xludf.DUMMYFUNCTION("""COMPUTED_VALUE"""),2.05) -> 2.05 | I1: =IFERROR(__xludf.DUMMYFUNCTION("""COMPUTED_VALUE"""),1.55) -> 1.55 | K1: =IFERROR(__xludf.DUMMYFUNCTION("""COMPUTED_VALUE"""),0.55) -> 0.55 | M1: =IFERROR(__xludf.DUMMYFUNCTION("""COMPUTED_VALUE"""),0.25) -> 0.25
A2: =IFERROR(__xludf.DUMMYFUNCTION("""COMPUTED_VALUE"""),"Tier") -> Tier | B2: =IFERROR(__xludf.DUMMYFUNCTION("""COMPUTED_VALUE"""),"Normal/Shiny") -> Normal/Shiny | C2: =IFERROR(__xludf.DUMMYFUNCTION("""COMPUTED_VALUE"""),"Tier") -> Tier | D2: =IFERROR(__xludf.DUMMYFUNCTION("""COMPUTED_VALUE"""),"Normal/Shiny") -> Normal/Shiny | E2: =IFERROR(__xludf.DUMMYFUNCTION("""COMPUTED_VALUE"""),"Tier") -> Tier | F2: =IFERROR(__xludf.DUMMYFUNCTION("""COMPUTED_VALUE"""),"Normal/Shiny") -> Normal/Shiny | G2: =IFERROR(__xludf.DUMMYFUNCTION("""COMPUTED_VALUE"""),"Tier") -> Tier | H2: =IFERROR(__xludf.DUMMYFUNCTION("""COMPUTED_VALUE"""),"Normal/Shiny") -> Normal/Shiny | I2: =IFERROR(__xludf.DUMMYFUNCTION("""COMPUTED_VALUE"""),"Tier") -> Tier | J2: =IFERROR(__xludf.DUMMYFUNCTION("""COMPUTED_VALUE"""),"Normal/Shiny") -> Normal/Shiny | K2: =IFERROR(__xludf.DUMMYFUNCTION("""COMPUTED_VALUE"""),"Tier") -> Tier | L2: =IFERROR(__xludf.DUMMYFUNCTION("""COMPUTED_VALUE"""),"Normal/Shiny") -> Normal/Shiny | M2: =IFERROR(__xludf.DUMMYFUNCTION("""COMPUTED_VALUE"""),"Tier") -> Tier | N2: =IFERROR(__xludf.DUMMYFUNCTION("""COMPUTED_VALUE"""),"Normal/Shiny") -> Normal/Shiny
A3: =IFERROR(__xludf.DUMMYFUNCTION("""COMPUTED_VALUE"""),"T1") -> T1 | B3: =IFERROR(__xludf.DUMMYFUNCTION("""COMPUTED_VALUE"""),33.433870492846964) -> 33.43387 | C3: =IFERROR(__xludf.DUMMYFUNCTION("""COMPUTED_VALUE"""),"T1") -> T1 | D3: =IFERROR(__xludf.DUMMYFUNCTION("""COMPUTED_VALUE"""),34.580728366284774) -> 34.580728 | E3: =IFERROR(__xludf.DUMMYFUNCTION("""COMPUTED_VALUE"""),"T1") -> T1 | F3: =IFERROR(__xludf.DUMMYFUNCTION("""COMPUTED_VALUE"""),31.819907090398896) -> 31.819907 | G3: =IFERROR(__xludf.DUMMYFUNCTION("""COMPUTED_VALUE"""),"T1") -> T1 | H3: =IFERROR(__xludf.DUMMYFUNCTION("""COMPUTED_VALUE"""),39.17275042444822) -> 39.17275 | I3: =IFERROR(__xludf.DUMMYFUNCTION("""COMPUTED_VALUE"""),"T1") -> T1 | J3: =IFERROR(__xludf.DUMMYFUNCTION("""COMPUTED_VALUE"""),31.384615384615383) -> 31.384615 | K3: =IFERROR(__xludf.DUMMYFUNCTION("""COMPUTED_VALUE"""),"T1") -> T1 | L3: =IFERROR(__xludf.DUMMYFUNCTION("""COMPUTED_VALUE"""),65.23809523809524) -> 65.238095 | M3: =IFERROR(__xludf.DUMMYFUNCTION("""COMPUTED_VALUE"""),"T1") -> T1 | N3: =IFERROR(__xludf.DUMMYFUNCTION("""COMPUTED_VALUE"""),50.48148148148148) -> 50.481481
A4: =IFERROR(__xludf.DUMMYFUNCTION("""COMPUTED_VALUE"""),"Super Rare") -> Super Rare | B4: =IFERROR(__xludf.DUMMYFUNCTION("""COMPUTED_VALUE"""),37.555658977327816) -> 37.555659 | C4: =IFERROR(__xludf.DUMMYFUNCTION("""COMPUTED_VALUE"""),"Super Rare") -> Super Rare | D4: =IFERROR(__xludf.DUMMYFUNCTION("""COMPUTED_VALUE"""),41.136154665118084) -> 41.136155 | E4: =IFERROR(__xludf.DUMMYFUNCTION("""COMPUTED_VALUE"""),"Super Rare") -> Super Rare | F4: =IFERROR(__xludf.DUMMYFUNCTION("""COMPUTED_VALUE"""),49.55348181012482) -> 49.553482 | G4: =IFERROR(__xludf.DUMMYFUNCTION("""COMPUTED_VALUE"""),"Super Rare") -> Super Rare | H4: =IFERROR(__xludf.DUMMYFUNCTION("""COMPUTED_VALUE"""),52.890894515572846) -> 52.890895 | I4: =IFERROR(__xludf.DUMMYFUNCTION("""COMPUTED_VALUE"""),"Super Rare") -> Super Rare | J4: =IFERROR(__xludf.DUMMYFUNCTION("""COMPUTED_VALUE"""),"-") -> - | K4: =IFERROR(__xludf.DUMMYFUNCTION("""COMPUTED_VALUE"""),"Super Rare") -> Super Rare | L4: =IFERROR(__xludf.DUMMYFUNCTION("""COMPUTED_VALUE"""),"-") -> - | M4: =IFERROR(__xludf.DUMMYFUNCTION("""COMPUTED_VALUE"""),"Super Rare") -> Super Rare | N4: =IFERROR(__xludf.DUMMYFUNCTION("""COMPUTED_VALUE"""),"-") -> -
A5: =IFERROR(__xludf.DUMMYFUNCTION("""COMPUTED_VALUE"""),"Ultra Rare") -> Ultra Rare | B5: =IFERROR(__xludf.DUMMYFUNCTION("""COMPUTED_VALUE"""),28.075554702237678) -> 28.075555 | C5: =IFERROR(__xludf.DUMMYFUNCTION("""COMPUTED_VALUE"""),"Ultra Rare") -> Ultra Rare | D5: =IFERROR(__xludf.DUMMYFUNCTION("""COMPUTED_VALUE"""),31.62962379150904) -> 31.629624 | E5: =IFERROR(__xludf.DUMMYFUNCTION("""COMPUTED_VALUE"""),"Ultra Rare") -> Ultra Rare | F5: =IFERROR(__xludf.DUMMYFUNCTION("""COMPUTED_VALUE"""),30.844220971712275) -> 30.844221 | G5: =IFERROR(__xludf.DUMMYFUNCTION("""COMPUTED_VALUE"""),"Ultra Rare") -> Ultra Rare | H5: =IFERROR(__xludf.DUMMYFUNCTION("""COMPUTED_VALUE"""),42.26229508196721) -> 42.262295 | I5: =IFERROR(__xludf.DUMMYFUNCTION("""COMPUTED_VALUE"""),"Ultra Rare") -> Ultra Rare | J5: =IFERROR(__xludf.DUMMYFUNCTION("""COMPUTED_VALUE"""),"-") -> - | K5: =IFERROR(__xludf.DUMMYFUNCTION("""COMPUTED_VALUE"""),"Ultra Rare") -> Ultra Rare | L5: =IFERROR(__xludf.DUMMYFUNCTION("""COMPUTED_VALUE"""),"-") -> - | M5: =IFERROR(__xludf.DUMMYFUNCTION("""COMPUTED_VALUE"""),"Ultra Rare") -> Ultra Rare | N5: =IFERROR(__xludf.DUMMYFUNCTION("""COMPUTED_VALUE"""),"-") -> -
A6: =IFERROR(__xludf.DUMMYFUNCTION("""COMPUTED_VALUE"""),"Legendary") -> Legendary | B6: =IFERROR(__xludf.DUMMYFUNCTION("""COMPUTED_VALUE"""),29.99126153918417) -> 29.991262 | C6: =IFERROR(__xludf.DUMMYFUNCTION("""COMPUTED_VALUE"""),"Legendary") -> Legendary | D6: =IFERROR(__xludf.DUMMYFUNCTION("""COMPUTED_VALUE"""),31.82819890842935) -> 31.828199 | E6: =IFERROR(__xludf.DUMMYFUNCTION("""COMPUTED_VALUE"""),"Legendary") -> Legendary | F6: =IFERROR(__xludf.DUMMYFUNCTION("""COMPUTED_VALUE"""),29.950660195580504) -> 29.95066 | G6: =IFERROR(__xludf.DUMMYFUNCTION("""COMPUTED_VALUE"""),"Legendary") -> Legendary | H6: =IFERROR(__xludf.DUMMYFUNCTION("""COMPUTED_VALUE"""),"-") -> - | I6: =IFERROR(__xludf.DUMMYFUNCTION("""COMPUTED_VALUE"""),"Legendary") -> Legendary | J6: =IFERROR(__xludf.DUMMYFUNCTION("""COMPUTED_VALUE"""),"-") -> - | K6: =IFERROR(__xludf.DUMMYFUNCTION("""COMPUTED_VALUE"""),"Legendary") -> Legendary | L6: =IFERROR(__xludf.DUMMYFUNCTION("""COMPUTED_VALUE"""),"-") -> - | M6: =IFERROR(__xludf.DUMMYFUNCTION("""COMPUTED_VALUE"""),"Legendary") -> Legendary | N6: =IFERROR(__xludf.DUMMYFUNCTION("""COMPUTED_VALUE"""),"-") -> -
A7: =IFERROR(__xludf.DUMMYFUNCTION("""COMPUTED_VALUE"""),"Mythic") -> Mythic | B7: =IFERROR(__xludf.DUMMYFUNCTION("""COMPUTED_VALUE"""),"-") -> - | C7: =IFERROR(__xludf.DUMMYFUNCTION("""COMPUTED_VALUE"""),"Mythic") -> Mythic | D7: =IFERROR(__xludf.DUMMYFUNCTION("""COMPUTED_VALUE"""),49.90662410215483) -> 49.906624 | E7: =IFERROR(__xludf.DUMMYFUNCTION("""COMPUTED_VALUE"""),"Mythic") -> Mythic | F7: =IFERROR(__xludf.DUMMYFUNCTION("""COMPUTED_VALUE"""),"-") -> - | G7: =IFERROR(__xludf.DUMMYFUNCTION("""COMPUTED_VALUE"""),"Mythic") -> Mythic | H7: =IFERROR(__xludf.DUMMYFUNCTION("""COMPUTED_VALUE"""),"-") -> - | I7: =IFERROR(__xludf.DUMMYFUNCTION("""COMPUTED_VALUE"""),"Mythic") -> Mythic | J7: =IFERROR(__xludf.DUMMYFUNCTION("""COMPUTED_VALUE"""),"-") -> - | K7: =IFERROR(__xludf.DUMMYFUNCTION("""COMPUTED_VALUE"""),"Mythic") -> Mythic | L7: =IFERROR(__xludf.DUMMYFUNCTION("""COMPUTED_VALUE"""),"-") -> - | M7: =IFERROR(__xludf.DUMMYFUNCTION("""COMPUTED_VALUE"""),"Mythic") -> Mythic | N7: =IFERROR(__xludf.DUMMYFUNCTION("""COMPUTED_VALUE"""),"-") -> -
A9: Ajude a tabela a ser mais precisa, mande os dados do seu analyzer pelo form:
A10: https://docs.google.com/forms/d/e/1FAIpQLSfDhUaqGeUK-6uLphsluOpr_FMMDLni0Q3uPvx69x19tYVfvg/viewform
A11: Obrigado! :)

Sheet DGs
A1: w | B1: Cidade | C1: Pokemon 1 | D1: Pokemon 2 | E1: Pokemon 3
A2: The Rocky Mountain | B2: Pewter | C2: Larvitar | D2: Pupitar | E2: Tyranitar
A3: The Fairy Garden | B3: Pewter | C3: Flabébé | D3: Foette | E3: Florges
A4: The Fighting Dojo | B4: Pewter

Sheet GYM
A1: =IFERROR(__xludf.DUMMYFUNCTION("IMPORTRANGE(""Https://docs.google.com/spreadsheets/d/1ID3qu1P4Zey82OSLntg4O0xoZlY1hGK58tte0D_Cv_s/edit?pli=1&gid=1217370921#gid=1217370921"", ""GYM!A1:D9"")"),"Cidade") -> Cidade | B1: =IFERROR(__xludf.DUMMYFUNCTION("""COMPUTED_VALUE"""),"Task 1") -> Task 1 | C1: =IFERROR(__xludf.DUMMYFUNCTION("""COMPUTED_VALUE"""),"Task 2") -> Task 2 | D1: =IFERROR(__xludf.DUMMYFUNCTION("""COMPUTED_VALUE"""),"Dungeon") -> Dungeon | E1: Informações extras: - Precisa ser lvl 250+ - Pra começar a task, fale com o NPC Alfred na entrada de cada ginásio - Pra completar a task, fale com o NPC Alfred novamente - As dungeons possuem um limite de 10 minutos, e não é possível usar revive - Se morrer na dungeon, conta como uma morte normal (perde xp/bless) - Caso falhe na dungeon, é cobrado 250k para tentar novamente - Caso falhe no líder do ginásio, é cobrado 3 simple orbs do tipo respectivo - Caso falhe pros outros membros do ginásio, é cobrado 1 simple orb - Recompensa: 4 Potent Boost Stones (Lvl 21-25) do tipo respectivo - Mais informações: https://www.youtube.com/watch?v=khbKeyFrczI
A2: =IFERROR(__xludf.DUMMYFUNCTION("""COMPUTED_VALUE"""),"Viridian") -> Viridian | B2: =IFERROR(__xludf.DUMMYFUNCTION("""COMPUTED_VALUE"""),"10 Shiny Nidoqueen") -> 10 Shiny Nidoqueen | C2: =IFERROR(__xludf.DUMMYFUNCTION("""COMPUTED_VALUE"""),"10 Shiny Nidoking") -> 10 Shiny Nidoking | D2: =IFERROR(__xludf.DUMMYFUNCTION("""COMPUTED_VALUE"""),"https://imgur.com/a/CNjdEEP") -> https://imgur.com/a/CNjdEEP
A3: =IFERROR(__xludf.DUMMYFUNCTION("""COMPUTED_VALUE"""),"Pewter") -> Pewter | B3: =IFERROR(__xludf.DUMMYFUNCTION("""COMPUTED_VALUE"""),"10 Shiny Marowak") -> 10 Shiny Marowak | C3: =IFERROR(__xludf.DUMMYFUNCTION("""COMPUTED_VALUE"""),"10 Shiny Steelix") -> 10 Shiny Steelix | D3: =IFERROR(__xludf.DUMMYFUNCTION("""COMPUTED_VALUE"""),"https://imgur.com/a/TdDDQvL") -> https://imgur.com/a/TdDDQvL
A4: =IFERROR(__xludf.DUMMYFUNCTION("""COMPUTED_VALUE"""),"Cerulean") -> Cerulean | B4: =IFERROR(__xludf.DUMMYFUNCTION("""COMPUTED_VALUE"""),"10 Shiny Blastoise") -> 10 Shiny Blastoise | C4: =IFERROR(__xludf.DUMMYFUNCTION("""COMPUTED_VALUE"""),"10 Shiny Feraligatr") -> 10 Shiny Feraligatr | D4: =IFERROR(__xludf.DUMMYFUNCTION("""COMPUTED_VALUE"""),"https://imgur.com/a/9zLq4Sq") -> https://imgur.com/a/9zLq4Sq
A5: =IFERROR(__xludf.DUMMYFUNCTION("""COMPUTED_VALUE"""),"Vermilion") -> Vermilion | B5: =IFERROR(__xludf.DUMMYFUNCTION("""COMPUTED_VALUE"""),"10 Shiny Raichu") -> 10 Shiny Raichu | C5: =IFERROR(__xludf.DUMMYFUNCTION("""COMPUTED_VALUE"""),"10 Shiny Lanturn") -> 10 Shiny Lanturn | D5: =IFERROR(__xludf.DUMMYFUNCTION("""COMPUTED_VALUE"""),"https://imgur.com/a/X1JlKl5") -> https://imgur.com/a/X1JlKl5
A6: =IFERROR(__xludf.DUMMYFUNCTION("""COMPUTED_VALUE"""),"Celadon") -> Celadon | B6: =IFERROR(__xludf.DUMMYFUNCTION("""COMPUTED_VALUE"""),"10 Shiny Venusaur") -> 10 Shiny Venusaur | C6: =IFERROR(__xludf.DUMMYFUNCTION("""COMPUTED_VALUE"""),"10 Shiny Meganium") -> 10 Shiny Meganium | D6: =IFERROR(__xludf.DUMMYFUNCTION("""COMPUTED_VALUE"""),"https://imgur.com/a/M7Jk4Ip") -> https://imgur.com/a/M7Jk4Ip
A7: =IFERROR(__xludf.DUMMYFUNCTION("""COMPUTED_VALUE"""),"Fuchsia") -> Fuchsia | B7: =IFERROR(__xludf.DUMMYFUNCTION("""COMPUTED_VALUE"""),"10 Shiny Tentacruel") -> 10 Shiny Tentacruel | C7: =IFERROR(__xludf.DUMMYFUNCTION("""COMPUTED_VALUE"""),"10 Shiny Muk") -> 10 Shiny Muk | D7: =IFERROR(__xludf.DUMMYFUNCTION("""COMPUTED_VALUE"""),"https://imgur.com/a/has6KOr") -> https://imgur.com/a/has6KOr
A8: =IFERROR(__xludf.DUMMYFUNCTION("""COMPUTED_VALUE"""),"Saffron") -> Saffron | B8: =IFERROR(__xludf.DUMMYFUNCTION("""COMPUTED_VALUE"""),"10 Shiny Espeon") -> 10 Shiny Espeon | C8: =IFERROR(__xludf.DUMMYFUNCTION("""COMPUTED_VALUE"""),"10 Shiny Xatu") -> 10 Shiny Xatu | D8: =IFERROR(__xludf.DUMMYFUNCTION("""COMPUTED_VALUE"""),"https://imgur.com/a/ZJrqy4w") -> https://imgur.com/a/ZJrqy4w
A9: =IFERROR(__xludf.DUMMYFUNCTION("""COMPUTED_VALUE"""),"Cinnabar") -> Cinnabar | B9: =IFERROR(__xludf.DUMMYFUNCTION("""COMPUTED_VALUE"""),"10 Shiny Charizard") -> 10 Shiny Charizard | C9: =IFERROR(__xludf.DUMMYFUNCTION("""COMPUTED_VALUE"""),"10 Shiny Typhlosion") -> 10 Shiny Typhlosion | D9: =IFERROR(__xludf.DUMMYFUNCTION("""COMPUTED_VALUE"""),"https://imgur.com/a/hLzaofv") -> https://imgur.com/a/hLzaofv
A11: POKEMONS DOS LÍDERES
A12: Viridian | B12: Pewter | C12: Cerulean | D12: Vermilion | E12: Celadon | F12: Fuchsia | G12: Saffron | H12: Cinnabar
A13: sh Kangaskhan | B13: sh Marowak | C13: sh Blastoise | D13: sh Magneton | E13: sh Exeggutor | F13: sh Nidoking | G13: sh Alakazam | H13: sh Magmar
A14: sh Nidoking | B14: sh Onix | C14: sh Vaporeon | D14: sh Ampharos | E14: sh Venusaur | F14: sh Nidoqueen | G14: sh Xatu | H14: sh Flareon
A15: sh Nidoqueen | B15: sh Rhydon | C15: sh Tentacruel | D15: sh Raichu | E15: sh Meganium | F15: sh Crobat | G15: sh Wobbuffet | H15: sh Ninetales
A16: sh Dugtrio | B16: sh Golem | C16: sh Feraligatr | D16: sh Lanturn | E16: sh Tangela | F16: sh Tentacruel | G16: sh Espeon | H16: sh Arcanine
